Workbook
Name Roster: 'All-time'!$A$3:$A$30

Sheet README
B2: THAMESLINK HAJDUCI — TEAM TRACKER
B4: HOW IT WORKS
B5: Each season lives on ONE tab (S1–S6, S8). Everything for that season — fixtures, results, appearances, goals, assists, costs — is on that tab.
B6: Aggregator tabs (All-time, Money) sit after the season tabs and update automatically.
B7: Yellow cells are the weekly inputs: Our goals, Their goals, Match cost. Grey cells are calculated — don’t type in them.
B9: LOGGING A GAME (on the season tab)
B10: 1. Enter the score in the "Our goals" / "Their goals" rows (Score and W/D/L fill in automatically — this also permanently fixes the old problem of scores like 3-10 turning into dates).
B11: 2. Put a 1 in the APPEARANCES grid for everyone who played.
B12: 3. Enter goals/assists per player in the GOALS and ASSISTS grids.
B13: 4. Enter the Match cost (£). It’s split evenly across that game’s players and lands on each player’s Cost (£) column and the Money tab.
B15: MONEY
B16: All seasons before Season 8 are settled, so player tabs start from S8. The Money tab shows what each player has been charged (from the season tabs), what they’ve paid (from the Payments tab), and the balance they owe.
... B45: Season 8 fixtures loaded from playfootball.net (Whitechapel Tuesday 6’s, Premier League, "Season 2 2026") — 18 games, 1 Sep 2026 to 12 Jan 2027.

Sheet S1
A1: Season 1 · Play5aside Hoxton (sand, 5-a-side) · Sep–Nov 2024
A2: Match | B2: GW1 | C2: GW2 | D2: GW3 | E2: GW4 | F2: GW5 | G2: GW6 | H2: GW7 | I2: GW8 | J2: GW9 | K2: GW10 | L2: GW11 | M2: GW12 | N2: GW13 | O2: GW14 | P2: GW15 | Q2: GW16 | R2: GW17 | S2: GW18 | T2: GW19 | U2: GW20 | X2: SEASON SUMMARY
A3: Date | B3: 45546 | C3: 45553 | D3: 45560 | E3: 45567 | F3: 45574 | G3: 45581 | H3: 45588 | I3: 45595 | J3: 45602 | K3: 45609 | X3: Played | Y3: =Y4+Y5+Y6 -> 10
A4: Kick-off | X4: Won | Y4: =SUMPRODUCT(($B$9:$U$9="W")*($B$16:$U$16="")) -> 2
A5: Opponent | B5: MBS | C5: Barkways Sisters | D5: Safe FC | E5: Hardly Athletic | F5: Clapham Casuals | G5: MBS | H5: Barkways Sisters | I5: Safe FC | J5: Hardly Athletic | K5: Clapham Casuals | X5: Drawn | Y5: =SUMPRODUCT(($B$9:$U$9="D")*($B$16:$U$16="")) -> 1
A6: Our goals | B6: 3 | C6: 4 | D6: 1 | E6: 0 | F6: 1 | G6: 5 | H6: 3 | I6: 2 | J6: 3 | K6: 1 | X6: Lost | Y6: =SUMPRODUCT(($B$9:$U$9="L")*($B$16:$U$16="")) -> 7
A7: Their goals | B7: 11 | C7: 3 | D7: 5 | E7: 3 | F7: 2 | G7: 9 | H7: 3 | I7: 5 | J7: 2 | K7: 2 | X7: Goals for | Y7: =SUMPRODUCT($B$6:$U$6*($B$16:$U$16="")) -> 23
A8: Score | B8: =IF(COUNT(B6:B7)<2,"",B6&"-"&B7) -> 3-11 | C8: =IF(COUNT(C6:C7)<2,"",C6&"-"&C7) -> 4-3 | D8: =IF(COUNT(D6:D7)<2,"",D6&"-"&D7) -> 1-5 | E8: =IF(COUNT(E6:E7)<2,"",E6&"-"&E7) -> 0-3 | F8: =IF(COUNT(F6:F7)<2,"",F6&"-"&F7) -> 1-2 | G8: =IF(COUNT(G6:G7)<2,"",G6&"-"&G7) -> 5-9 | H8: =IF(COUNT(H6:H7)<2,"",H6&"-"&H7) -> 3-3 | I8: =IF(COUNT(I6:I7)<2,"",I6&"-"&I7) -> 2-5 | ... U8: =IF(COUNT(U6:U7)<2,"",U6&"-"&U7) | X8: Goals against | Y8: =SUMPRODUCT($B$7:$U$7*($B$16:$U$16="")) -> 45
A9: Result | B9: =IF(COUNT(B6:B7)<2,"",IF(B6>B7,"W",IF(B6<B7,"L","D"))) -> L | C9: =IF(COUNT(C6:C7)<2,"",IF(C6>C7,"W",IF(C6<C7,"L","D"))) -> W | D9: =IF(COUNT(D6:D7)<2,"",IF(D6>D7,"W",IF(D6<D7,"L","D"))) -> L | E9: =IF(COUNT(E6:E7)<2,"",IF(E6>E7,"W",IF(E6<E7,"L","D"))) -> L | F9: =IF(COUNT(F6:F7)<2,"",IF(F6>F7,"W",IF(F6<F7,"L","D"))) -> L | G9: =IF(COUNT(G6:G7)<2,"",IF(G6>G7,"W",IF(G6<G7,"L","D"))) -> L | H9: =IF(COUNT(H6:H7)<2,"",IF(H6>H7,"W",IF(H6<H7,"L","D"))) -> D | I9: =IF(COUNT(I6:I7)<2,"",IF(I6>I7,"W",IF(I6<I7,"L","D"))) -> L | ... U9: =IF(COUNT(U6:U7)<2,"",IF(U6>U7,"W",IF(U6<U7,"L","D"))) | X9: Top scorer | Y9: {=IF(MAX($V$49:$V$76)=0,"—",INDEX($A$49:$A$76,MATCH(MAX($V$49:$V$76),$V$49:$V$76,0))&" ("&MAX($V$49:$V$76)&")")} -> Sam Holt (5)
A10: MOTM | B10: Isaac Mond | C10: Callum McCarthy | D10: Phil Knott | E10: Henry Linklater | F10: Max Cobain | G10: Sam Holt | H10: Andy Cowan | I10: Phil Knott | J10: Sam Holt | K10: Isaac Mond | X10: Most apps | Y10: {=IF(MAX($V$18:$V$45)=0,"—",INDEX($A$18:$A$45,MATCH(MAX($V$18:$V$45),$V$18:$V$45,0))&" ("&MAX($V$18:$V$45)&")")} -> Phil Knott (10)
A11: Champagne moment | B11: Henry Linklater | C11: Max Cobain | E11: Max Cobain | F11: Abdul | H11: Ben Merrett | J11: Neeraj Radia | K11: Isaac Mond | X11: Season cost | Y11: =SUM($B$13:$U$13) -> 0
A12: Comments | C12: Phantom pullback | E12: "Anyone want to sub off" | F12: Tackled by his own teammate | H12: Shooting from kick off | J12: Claiming 4 assists | K12: 5 yard freekick | X12: Paid by
A13: Match cost (£)
A14: Players in game | B14: =COUNT(B$18:B$45) -> 6 | C14: =COUNT(C$18:C$45) -> 6 | D14: =COUNT(D$18:D$45) -> 5 | E14: =COUNT(E$18:E$45) -> 7 | F14: =COUNT(F$18:F$45) -> 7 | G14: =COUNT(G$18:G$45) -> 10 | H14: =COUNT(H$18:H$45) -> 7 | I14: =COUNT(I$18:I$45) -> 6 | ... U14: =COUNT(U$18:U$45) -> 0
A15: Cost per player (£) | B15: =IF(B$14=0,0,N(B$13)/B$14) -> 0 | C15: =IF(C$14=0,0,N(C$13)/C$14) -> 0 | D15: =IF(D$14=0,0,N(D$13)/D$14) -> 0 | E15: =IF(E$14=0,0,N(E$13)/E$14) -> 0 | F15: =IF(F$14=0,0,N(F$13)/F$14) -> 0 | G15: =IF(G$14=0,0,N(G$13)/G$14) -> 0 | H15: =IF(H$14=0,0,N(H$13)/H$14) -> 0 | I15: =IF(I$14=0,0,N(I$13)/I$14) -> 0 | ... U15: =IF(U$14=0,0,N(U$13)/U$14) -> 0
A16: Type (excl. from records)
A17: APPEARANCES (1 = played) | B17: GW1 | C17: GW2 | D17: GW3 | E17: GW4 | F17: GW5 | G17: GW6 | H17: GW7 | I17: GW8 | J17: GW9 | K17: GW10 | L17: GW11 | M17: GW12 | N17: GW13 | O17: GW14 | P17: GW15 | Q17: GW16 | R17: GW17 | S17: GW18 | T17: GW19 | U17: GW20 | V17: Apps | W17: Cost (£)
A18: Ahmed | V18: =SUMPRODUCT(B18:U18*($B$16:$U$16="")) -> 0 | W18: =SUMPRODUCT($B18:$U18,$B$15:$U$15) -> 0
A19: Alex Ruben | V19: =SUMPRODUCT(B19:U19*($B$16:$U$16="")) -> 0 | W19: =SUMPRODUCT($B19:$U19,$B$15:$U$15) -> 0
A20: Andy Cowan | D20: 1 | G20: 1 | H20: 1 | V20: =SUMPRODUCT(B20:U20*($B$16:$U$16="")) -> 3 | W20: =SUMPRODUCT($B20:$U20,$B$15:$U$15) -> 0
A21: Ben Merrett | F21: 1 | H21: 1 | I21: 1 | J21: 1 | K21: 1 | V21: =SUMPRODUCT(B21:U21*($B$16:$U$16="")) -> 5 | W21: =SUMPRODUCT($B21:$U21,$B$15:$U$15) -> 0
A22: Callum McCarthy | C22: 1 | E22: 1 | G22: 1 | V22: =SUMPRODUCT(B22:U22*($B$16:$U$16="")) -> 3 | W22: =SUMPRODUCT($B22:$U22,$B$15:$U$15) -> 0
A23: Cecil Watson | I23: 1 | J23: 1 | V23: =SUMPRODUCT(B23:U23*($B$16:$U$16="")) -> 2 | W23: =SUMPRODUCT($B23:$U23,$B$15:$U$15) -> 0
A24: Conall Templeman | V24: =SUMPRODUCT(B24:U24*($B$16:$U$16="")) -> 0 | W24: =SUMPRODUCT($B24:$U24,$B$15:$U$15) -> 0
A25: Eddie Ringer | V25: =SUMPRODUCT(B25:U25*($B$16:$U$16="")) -> 0 | W25: =SUMPRODUCT($B25:$U25,$B$15:$U$15) -> 0
A26: Finn Cawley | V26: =SUMPRODUCT(B26:U26*($B$16:$U$16="")) -> 0 | W26: =SUMPRODUCT($B26:$U26,$B$15:$U$15) -> 0
A27: George Barbantan | B27: 1 | C27: 1 | D27: 1 | G27: 1 | I27: 1 | V27: =SUMPRODUCT(B27:U27*($B$16:$U$16="")) -> 5 | W27: =SUMPRODUCT($B27:$U27,$B$15:$U$15) -> 0
A28: Henry Linklater | B28: 1 | C28: 1 | E28: 1 | F28: 1 | G28: 1 | H28: 1 | J28: 1 | K28: 1 | V28: =SUMPRODUCT(B28:U28*($B$16:$U$16="")) -> 8 | W28: =SUMPRODUCT($B28:$U28,$B$15:$U$15) -> 0
A29: Isaac Mond | B29: 1 | E29: 1 | F29: 1 | G29: 1 | H29: 1 | I29: 1 | J29: 1 | K29: 1 | V29: =SUMPRODUCT(B29:U29*($B$16:$U$16="")) -> 8 | W29: =SUMPRODUCT($B29:$U29,$B$15:$U$15) -> 0
A30: Jake Harrison | V30: =SUMPRODUCT(B30:U30*($B$16:$U$16="")) -> 0 | W30: =SUMPRODUCT($B30:$U30,$B$15:$U$15) -> 0
A31: Jake Ringer | V31: =SUMPRODUCT(B31:U31*($B$16:$U$16="")) -> 0 | W31: =SUMPRODUCT($B31:$U31,$B$15:$U$15) -> 0
A32: Keshav Singh | V32: =SUMPRODUCT(B32:U32*($B$16:$U$16="")) -> 0 | W32: =SUMPRODUCT($B32:$U32,$B$15:$U$15) -> 0
A33: Mark Pellowe | V33: =SUMPRODUCT(B33:U33*($B$16:$U$16="")) -> 0 | W33: =SUMPRODUCT($B33:$U33,$B$15:$U$15) -> 0
A34: Max Cobain | B34: 1 | C34: 1 | D34: 1 | E34: 1 | F34: 1 | G34: 1 | H34: 1 | K34: 1 | V34: =SUMPRODUCT(B34:U34*($B$16:$U$16="")) -> 8 | W34: =SUMPRODUCT($B34:$U34,$B$15:$U$15) -> 0
A35: Neeraj Radia | C35: 1 | D35: 1 | E35: 1 | F35: 1 | G35: 1 | H35: 1 | I35: 1 | J35: 1 | K35: 1 | V35: =SUMPRODUCT(B35:U35*($B$16:$U$16="")) -> 9 | W35: =SUMPRODUCT($B35:$U35,$B$15:$U$15) -> 0
A36: Phil Knott | B36: 1 | C36: 1 | D36: 1 | E36: 1 | F36: 1 | G36: 1 | H36: 1 | I36: 1 | J36: 1 | K36: 1 | V36: =SUMPRODUCT(B36:U36*($B$16:$U$16="")) -> 10 | W36: =SUMPRODUCT($B36:$U36,$B$15:$U$15) -> 0
A37: Robin | G37: 1 | V37: =SUMPRODUCT(B37:U37*($B$16:$U$16="")) -> 1 | W37: =SUMPRODUCT($B37:$U37,$B$15:$U$15) -> 0
A38: Sam Holt | B38: 1 | E38: 1 | F38: 1 | G38: 1 | J38: 1 | K38: 1 | V38: =SUMPRODUCT(B38:U38*($B$16:$U$16="")) -> 6 | W38: =SUMPRODUCT($B38:$U38,$B$15:$U$15) -> 0
A39: Seb Burgess | V39: =SUMPRODUCT(B39:U39*($B$16:$U$16="")) -> 0 | W39: =SUMPRODUCT($B39:$U39,$B$15:$U$15) -> 0
V40: =SUMPRODUCT(B40:U40*($B$16:$U$16="")) -> 0 | W40: =SUMPRODUCT($B40:$U40,$B$15:$U$15) -> 0
V41: =SUMPRODUCT(B41:U41*($B$16:$U$16="")) -> 0 | W41: =SUMPRODUCT($B41:$U41,$B$15:$U$15) -> 0
V42: =SUMPRODUCT(B42:U42*($B$16:$U$16="")) -> 0 | W42: =SUMPRODUCT($B42:$U42,$B$15:$U$15) -> 0
V43: =SUMPRODUCT(B43:U43*($B$16:$U$16="")) -> 0 | W43: =SUMPRODUCT($B43:$U43,$B$15:$U$15) -> 0
V44: =SUMPRODUCT(B44:U44*($B$16:$U$16="")) -> 0 | W44: =SUMPRODUCT($B44:$U44,$B$15:$U$15) -> 0
V45: =SUMPRODUCT(B45:U45*($B$16:$U$16="")) -> 0 | W45: =SUMPRODUCT($B45:$U45,$B$15:$U$15) -> 0
A46: Total | V46: =SUM(V18:V45) -> 68 | W46: =SUM(W18:W45) -> 0
A48: GOALS — number scored | B48: GW1 | C48: GW2 | D48: GW3 | E48: GW4 | F48: GW5 | G48: GW6 | H48: GW7 | I48: GW8 | J48: GW9 | K48: GW10 | L48: GW11 | M48: GW12 | N48: GW13 | O48: GW14 | P48: GW15 | Q48: GW16 | R48: GW17 | S48: GW18 | T48: GW19 | U48: GW20 | V48: Goals
A49: =IF($A18="","",$A18) -> Ahmed | V49: =SUMPRODUCT(B49:U49*($B$16:$U$16="")) -> 0
A50: =IF($A19="","",$A19) -> Alex Ruben | V50: =SUMPRODUCT(B50:U50*($B$16:$U$16="")) -> 0
A51: =IF($A20="","",$A20) -> Andy Cowan | H51: 1 | V51: =SUMPRODUCT(B51:U51*($B$16:$U$16="")) -> 1
A52: =IF($A21="","",$A21) -> Ben Merrett | H52: 1 | V52: =SUMPRODUCT(B52:U52*($B$16:$U$16="")) -> 1
A53: =IF($A22="","",$A22) -> Callum McCarthy | C53: 2 | V53: =SUMPRODUCT(B53:U53*($B$16:$U$16="")) -> 2
A54: =IF($A23="","",$A23) -> Cecil Watson | V54: =SUMPRODUCT(B54:U54*($B$16:$U$16="")) -> 0
A55: =IF($A24="","",$A24) -> Conall Templeman | V55: =SUMPRODUCT(B55:U55*($B$16:$U$16="")) -> 0
A56: =IF($A25="","",$A25) -> Eddie Ringer | V56: =SUMPRODUCT(B56:U56*($B$16:$U$16="")) -> 0
A57: =IF($A26="","",$A26) -> Finn Cawley | V57: =SUMPRODUCT(B57:U57*($B$16:$U$16="")) -> 0
A58: =IF($A27="","",$A27) -> George Barbantan | B58: 1 | D58: 1 | G58: 1 | V58: =SUMPRODUCT(B58:U58*($B$16:$U$16="")) -> 3
A59: =IF($A28="","",$A28) -> Henry Linklater | V59: =SUMPRODUCT(B59:U59*($B$16:$U$16="")) -> 0
A60: =IF($A29="","",$A29) -> Isaac Mond | H60: 1 | V60: =SUMPRODUCT(B60:U60*($B$16:$U$16="")) -> 1
A61: =IF($A30="","",$A30) -> Jake Harrison | V61: =SUMPRODUCT(B61:U61*($B$16:$U$16="")) -> 0
A62: =IF($A31="","",$A31) -> Jake Ringer | V62: =SUMPRODUCT(B62:U62*($B$16:$U$16="")) -> 0
A63: =IF($A32="","",$A32) -> Keshav Singh | V63: =SUMPRODUCT(B63:U63*($B$16:$U$16="")) -> 0
A64: =IF($A33="","",$A33) -> Mark Pellowe | V64: =SUMPRODUCT(B64:U64*($B$16:$U$16="")) -> 0
A65: =IF($A34="","",$A34) -> Max Cobain | B65: 1 | C65: 1 | F65: 1 | K65: 1 | V65: =SUMPRODUCT(B65:U65*($B$16:$U$16="")) -> 4
A66: =IF($A35="","",$A35) -> Neeraj Radia | C66: 1 | V66: =SUMPRODUCT(B66:U66*($B$16:$U$16="")) -> 1
A67: =IF($A36="","",$A36) -> Phil Knott | F67: 1 | I67: 2 | J67: 1 | V67: =SUMPRODUCT(B67:U67*($B$16:$U$16="")) -> 4
A68: =IF($A37="","",$A37) -> Robin | G68: 1 | V68: =SUMPRODUCT(B68:U68*($B$16:$U$16="")) -> 1
A69: =IF($A38="","",$A38) -> Sam Holt | B69: 1 | G69: 2 | J69: 2 | V69: =SUMPRODUCT(B69:U69*($B$16:$U$16="")) -> 5
A70: =IF($A39="","",$A39) -> Seb Burgess | V70: =SUMPRODUCT(B70:U70*($B$16:$U$16="")) -> 0
A71: =IF($A40="","",$A40) | V71: =SUMPRODUCT(B71:U71*($B$16:$U$16="")) -> 0
A72: =IF($A41="","",$A41) | V72: =SUMPRODUCT(B72:U72*($B$16:$U$16="")) -> 0
A73: =IF($A42="","",$A42) | V73: =SUMPRODUCT(B73:U73*($B$16:$U$16="")) -> 0
A74: =IF($A43="","",$A43) | V74: =SUMPRODUCT(B74:U74*($B$16:$U$16="")) -> 0
A75: =IF($A44="","",$A44) | V75: =SUMPRODUCT(B75:U75*($B$16:$U$16="")) -> 0
A76: =IF($A45="","",$A45) | V76: =SUMPRODUCT(B76:U76*($B$16:$U$16="")) -> 0
A77: Total | V77: =SUM(V49:V76) -> 23
A79: ASSISTS — number made | B79: GW1 | C79: GW2 | D79: GW3 | E79: GW4 | F79: GW5 | G79: GW6 | H79: GW7 | I79: GW8 | J79: GW9 | K79: GW10 | L79: GW11 | M79: GW12 | N79: GW13 | O79: GW14 | P79: GW15 | Q79: GW16 | R79: GW17 | S79: GW18 | T79: GW19 | U79: GW20 | V79: Assists
A80: =IF($A18="","",$A18) -> Ahmed | V80: =SUMPRODUCT(B80:U80*($B$16:$U$16="")) -> 0
A81: =IF($A19="","",$A19) -> Alex Ruben | V81: =SUMPRODUCT(B81:U81*($B$16:$U$16="")) -> 0
A82: =IF($A20="","",$A20) -> Andy Cowan | V82: =SUMPRODUCT(B82:U82*($B$16:$U$16="")) -> 0
A83: =IF($A21="","",$A21) -> Ben Merrett | F83: 2 | V83: =SUMPRODUCT(B83:U83*($B$16:$U$16="")) -> 2
A84: =IF($A22="","",$A22) -> Callum McCarthy | V84: =SUMPRODUCT(B84:U84*($B$16:$U$16="")) -> 0
A85: =IF($A23="","",$A23) -> Cecil Watson | J85: 1 | V85: =SUMPRODUCT(B85:U85*($B$16:$U$16="")) -> 1
A86: =IF($A24="","",$A24) -> Conall Templeman | V86: =SUMPRODUCT(B86:U86*($B$16:$U$16="")) -> 0
A87: =IF($A25="","",$A25) -> Eddie Ringer | V87: =SUMPRODUCT(B87:U87*($B$16:$U$16="")) -> 0
A88: =IF($A26="","",$A26) -> Finn Cawley | V88: =SUMPRODUCT(B88:U88*($B$16:$U$16="")) -> 0
A89: =IF($A27="","",$A27) -> George Barbantan | C89: 1 | V89: =SUMPRODUCT(B89:U89*($B$16:$U$16="")) -> 1
A90: =IF($A28="","",$A28) -> Henry Linklater | V90: =SUMPRODUCT(B90:U90*($B$16:$U$16="")) -> 0
A91: =IF($A29="","",$A29) -> Isaac Mond | B91: 1 | G91: 1 | H91: 1 | I91: 1 | V91: =SUMPRODUCT(B91:U91*($B$16:$U$16="")) -> 4
A92: =IF($A30="","",$A30) -> Jake Harrison | V92: =SUMPRODUCT(B92:U92*($B$16:$U$16="")) -> 0
A93: =IF($A31="","",$A31) -> Jake Ringer | V93: =SUMPRODUCT(B93:U93*($B$16:$U$16="")) -> 0
A94: =IF($A32="","",$A32) -> Keshav Singh | V94: =SUMPRODUCT(B94:U94*($B$16:$U$16="")) -> 0
A95: =IF($A33="","",$A33) -> Mark Pellowe | V95: =SUMPRODUCT(B95:U95*($B$16:$U$16="")) -> 0
A96: =IF($A34="","",$A34) -> Max Cobain | C96: 1 | V96: =SUMPRODUCT(B96:U96*($B$16:$U$16="")) -> 1
A97: =IF($A35="","",$A35) -> Neeraj Radia | C97: 1 | I97: 1 | J97: 1 | V97: =SUMPRODUCT(B97:U97*($B$16:$U$16="")) -> 3
A98: =IF($A36="","",$A36) -> Phil Knott | B98: 2 | C98: 1 | G98: 1 | H98: 1 | K98: 1 | V98: =SUMPRODUCT(B98:U98*($B$16:$U$16="")) -> 6
A99: =IF($A37="","",$A37) -> Robin | V99: =SUMPRODUCT(B99:U99*($B$16:$U$16="")) -> 0
A100: =IF($A38="","",$A38) -> Sam Holt | V100: =SUMPRODUCT(B100:U100*($B$16:$U$16="")) -> 0
A101: =IF($A39="","",$A39) -> Seb Burgess | V101: =SUMPRODUCT(B101:U101*($B$16:$U$16="")) -> 0
A102: =IF($A40="","",$A40) | V102: =SUMPRODUCT(B102:U102*($B$16:$U$16="")) -> 0
...

Sheet S2
A1: Season 2 · Powerleague Shoreditch (5G, 7-a-side) · Nov 2024–Jan 2025
A2: Match | B2: GW1 | C2: GW2 | D2: GW3 | E2: GW4 | F2: GW5 | G2: GW6 | H2: GW7 | I2: GW8 | J2: GW9 | K2: GW10 | L2: GW11 | M2: GW12 | N2: GW13 | O2: GW14 | P2: GW15 | Q2: GW16 | R2: GW17 | S2: GW18 | T2: GW19 | U2: GW20 | X2: SEASON SUMMARY
A3: Date | B3: 45624 | C3: 45631 | D3: 45638 | E3: 45645 | F3: 45666 | G3: 45673 | H3: 45680 | I3: 45687 | X3: Played | Y3: =Y4+Y5+Y6 -> 8
A4: Kick-off | X4: Won | Y4: =SUMPRODUCT(($B$9:$U$9="W")*($B$16:$U$16="")) -> 3
A5: Opponent | B5: Dalston Eagles | C5: Mutus | D5: LCG United | E5: Brighton | F5: City ACS | G5: Dalston | H5: Mutus | I5: LCG United | X5: Drawn | Y5: =SUMPRODUCT(($B$9:$U$9="D")*($B$16:$U$16="")) -> 0
A6: Our goals | B6: 3 | C6: 0 | D6: 2 | E6: 8 | F6: 4 | G6: 2 | H6: 2 | I6: 5 | X6: Lost | Y6: =SUMPRODUCT(($B$9:$U$9="L")*($B$16:$U$16="")) -> 5
A7: Their goals | B7: 10 | C7: 5 | D7: 5 | E7: 2 | F7: 3 | G7: 8 | H7: 11 | I7: 4 | X7: Goals for | Y7: =SUMPRODUCT($B$6:$U$6*($B$16:$U$16="")) -> 26
A8: Score | B8: =IF(COUNT(B6:B7)<2,"",B6&"-"&B7) -> 3-10 | C8: =IF(COUNT(C6:C7)<2,"",C6&"-"&C7) -> 0-5 | D8: =IF(COUNT(D6:D7)<2,"",D6&"-"&D7) -> 2-5 | E8: =IF(COUNT(E6:E7)<2,"",E6&"-"&E7) -> 8-2 | F8: =IF(COUNT(F6:F7)<2,"",F6&"-"&F7) -> 4-3 | G8: =IF(COUNT(G6:G7)<2,"",G6&"-"&G7) -> 2-8 | H8: =IF(COUNT(H6:H7)<2,"",H6&"-"&H7) -> 2-11 | I8: =IF(COUNT(I6:I7)<2,"",I6&"-"&I7) -> 5-4 | ... U8: =IF(COUNT(U6:U7)<2,"",U6&"-"&U7) | X8: Goals against | Y8: =SUMPRODUCT($B$7:$U$7*($B$16:$U$16="")) -> 48
A9: Result | B9: =IF(COUNT(B6:B7)<2,"",IF(B6>B7,"W",IF(B6<B7,"L","D"))) -> L | C9: =IF(COUNT(C6:C7)<2,"",IF(C6>C7,"W",IF(C6<C7,"L","D"))) -> L | D9: =IF(COUNT(D6:D7)<2,"",IF(D6>D7,"W",IF(D6<D7,"L","D"))) -> L | E9: =IF(COUNT(E6:E7)<2,"",IF(E6>E7,"W",IF(E6<E7,"L","D"))) -> W | F9: =IF(COUNT(F6:F7)<2,"",IF(F6>F7,"W",IF(F6<F7,"L","D"))) -> W | G9: =IF(COUNT(G6:G7)<2,"",IF(G6>G7,"W",IF(G6<G7,"L","D"))) -> L | H9: =IF(COUNT(H6:H7)<2,"",IF(H6>H7,"W",IF(H6<H7,"L","D"))) -> L | I9: =IF(COUNT(I6:I7)<2,"",IF(I6>I7,"W",IF(I6<I7,"L","D"))) -> W | ... U9: =IF(COUNT(U6:U7)<2,"",IF(U6>U7,"W",IF(U6<U7,"L","D"))) | X9: Top scorer | Y9: {=IF(MAX($V$49:$V$76)=0,"—",INDEX($A$49:$A$76,MATCH(MAX($V$49:$V$76),$V$49:$V$76,0))&" ("&MAX($V$49:$V$76)&")")} -> Seb Burgess (5)
A10: MOTM | B10: Sam Holt | C10: Henry Linklater | D10: Andy Cowan | E10: Finn Cawley | X10: Most apps | Y10: {=IF(MAX($V$18:$V$45)=0,"—",INDEX($A$18:$A$45,MATCH(MAX($V$18:$V$45),$V$18:$V$45,0))&" ("&MAX($V$18:$V$45)&")")} -> Andy Cowan (6)
A11: Champagne moment | X11: Season cost | Y11: =SUM($B$13:$U$13) -> 0
A12: Comments | X12: Paid by
A13: Match cost (£)
A14: Players in game | B14: =COUNT(B$18:B$45) -> 7 | C14: =COUNT(C$18:C$45) -> 8 | D14: =COUNT(D$18:D$45) -> 7 | E14: =COUNT(E$18:E$45) -> 4 | F14: =COUNT(F$18:F$45) -> 9 | G14: =COUNT(G$18:G$45) -> 8 | H14: =COUNT(H$18:H$45) -> 6 | I14: =COUNT(I$18:I$45) -> 7 | ... U14: =COUNT(U$18:U$45) -> 0
A15: Cost per player (£) | B15: =IF(B$14=0,0,N(B$13)/B$14) -> 0 | C15: =IF(C$14=0,0,N(C$13)/C$14) -> 0 | D15: =IF(D$14=0,0,N(D$13)/D$14) -> 0 | E15: =IF(E$14=0,0,N(E$13)/E$14) -> 0 | F15: =IF(F$14=0,0,N(F$13)/F$14) -> 0 | G15: =IF(G$14=0,0,N(G$13)/G$14) -> 0 | H15: =IF(H$14=0,0,N(H$13)/H$14) -> 0 | I15: =IF(I$14=0,0,N(I$13)/I$14) -> 0 | ... U15: =IF(U$14=0,0,N(U$13)/U$14) -> 0
A16: Type (excl. from records)
A17: APPEARANCES (1 = played) | B17: GW1 | C17: GW2 | D17: GW3 | E17: GW4 | F17: GW5 | G17: GW6 | H17: GW7 | I17: GW8 | J17: GW9 | K17: GW10 | L17: GW11 | M17: GW12 | N17: GW13 | O17: GW14 | P17: GW15 | Q17: GW16 | R17: GW17 | S17: GW18 | T17: GW19 | U17: GW20 | V17: Apps | W17: Cost (£)
A18: Ahmed | V18: =SUMPRODUCT(B18:U18*($B$16:$U$16="")) -> 0 | W18: =SUMPRODUCT($B18:$U18,$B$15:$U$15) -> 0
A19: Alex Ruben | H19: 1 | V19: =SUMPRODUCT(B19:U19*($B$16:$U$16="")) -> 1 | W19: =SUMPRODUCT($B19:$U19,$B$15:$U$15) -> 0
A20: Andy Cowan | B20: 1 | C20: 1 | D20: 1 | F20: 1 | G20: 1 | I20: 1 | V20: =SUMPRODUCT(B20:U20*($B$16:$U$16="")) -> 6 | W20: =SUMPRODUCT($B20:$U20,$B$15:$U$15) -> 0
A21: Ben Merrett | D21: 1 | F21: 1 | G21: 1 | H21: 1 | V21: =SUMPRODUCT(B21:U21*($B$16:$U$16="")) -> 4 | W21: =SUMPRODUCT($B21:$U21,$B$15:$U$15) -> 0
A22: Callum McCarthy | B22: 1 | C22: 1 | V22: =SUMPRODUCT(B22:U22*($B$16:$U$16="")) -> 2 | W22: =SUMPRODUCT($B22:$U22,$B$15:$U$15) -> 0
A23: Cecil Watson | V23: =SUMPRODUCT(B23:U23*($B$16:$U$16="")) -> 0 | W23: =SUMPRODUCT($B23:$U23,$B$15:$U$15) -> 0
A24: Conall Templeman | V24: =SUMPRODUCT(B24:U24*($B$16:$U$16="")) -> 0 | W24: =SUMPRODUCT($B24:$U24,$B$15:$U$15) -> 0
A25: Eddie Ringer | V25: =SUMPRODUCT(B25:U25*($B$16:$U$16="")) -> 0 | W25: =SUMPRODUCT($B25:$U25,$B$15:$U$15) -> 0
A26: Finn Cawley | E26: 1 | F26: 1 | G26: 1 | I26: 1 | V26: =SUMPRODUCT(B26:U26*($B$16:$U$16="")) -> 4 | W26: =SUMPRODUCT($B26:$U26,$B$15:$U$15) -> 0
A27: George Barbantan | C27: 1 | D27: 1 | F27: 1 | H27: 1 | I27: 1 | V27: =SUMPRODUCT(B27:U27*($B$16:$U$16="")) -> 5 | W27: =SUMPRODUCT($B27:$U27,$B$15:$U$15) -> 0
A28: Henry Linklater | B28: 1 | C28: 1 | E28: 1 | G28: 1 | H28: 1 | I28: 1 | V28: =SUMPRODUCT(B28:U28*($B$16:$U$16="")) -> 6 | W28: =SUMPRODUCT($B28:$U28,$B$15:$U$15) -> 0
A29: Isaac Mond | B29: 1 | D29: 1 | F29: 1 | V29: =SUMPRODUCT(B29:U29*($B$16:$U$16="")) -> 3 | W29: =SUMPRODUCT($B29:$U29,$B$15:$U$15) -> 0
A30: Jake Harrison | F30: 1 | V30: =SUMPRODUCT(B30:U30*($B$16:$U$16="")) -> 1 | W30: =SUMPRODUCT($B30:$U30,$B$15:$U$15) -> 0
A31: Jake Ringer | V31: =SUMPRODUCT(B31:U31*($B$16:$U$16="")) -> 0 | W31: =SUMPRODUCT($B31:$U31,$B$15:$U$15) -> 0
A32: Keshav Singh | V32: =SUMPRODUCT(B32:U32*($B$16:$U$16="")) -> 0 | W32: =SUMPRODUCT($B32:$U32,$B$15:$U$15) -> 0
A33: Mark Pellowe | V33: =SUMPRODUCT(B33:U33*($B$16:$U$16="")) -> 0 | W33: =SUMPRODUCT($B33:$U33,$B$15:$U$15) -> 0
A34: Max Cobain | D34: 1 | F34: 1 | G34: 1 | H34: 1 | I34: 1 | V34: =SUMPRODUCT(B34:U34*($B$16:$U$16="")) -> 5 | W34: =SUMPRODUCT($B34:$U34,$B$15:$U$15) -> 0
A35: Neeraj Radia | C35: 1 | F35: 1 | G35: 1 | V35: =SUMPRODUCT(B35:U35*($B$16:$U$16="")) -> 3 | W35: =SUMPRODUCT($B35:$U35,$B$15:$U$15) -> 0
A36: Phil Knott | B36: 1 | C36: 1 | D36: 1 | E36: 1 | V36: =SUMPRODUCT(B36:U36*($B$16:$U$16="")) -> 4 | W36: =SUMPRODUCT($B36:$U36,$B$15:$U$15) -> 0
A37: Robin | C37: 1 | V37: =SUMPRODUCT(B37:U37*($B$16:$U$16="")) -> 1 | W37: =SUMPRODUCT($B37:$U37,$B$15:$U$15) -> 0
A38: Sam Holt | B38: 1 | D38: 1 | F38: 1 | G38: 1 | H38: 1 | I38: 1 | V38: =SUMPRODUCT(B38:U38*($B$16:$U$16="")) -> 6 | W38: =SUMPRODUCT($B38:$U38,$B$15:$U$15) -> 0
A39: Seb Burgess | B39: 1 | C39: 1 | E39: 1 | G39: 1 | I39: 1 | V39: =SUMPRODUCT(B39:U39*($B$16:$U$16="")) -> 5 | W39: =SUMPRODUCT($B39:$U39,$B$15:$U$15) -> 0
V40: =SUMPRODUCT(B40:U40*($B$16:$U$16="")) -> 0 | W40: =SUMPRODUCT($B40:$U40,$B$15:$U$15) -> 0
V41: =SUMPRODUCT(B41:U41*($B$16:$U$16="")) -> 0 | W41: =SUMPRODUCT($B41:$U41,$B$15:$U$15) -> 0
V42: =SUMPRODUCT(B42:U42*($B$16:$U$16="")) -> 0 | W42: =SUMPRODUCT($B42:$U42,$B$15:$U$15) -> 0
V43: =SUMPRODUCT(B43:U43*($B$16:$U$16="")) -> 0 | W43: =SUMPRODUCT($B43:$U43,$B$15:$U$15) -> 0
V44: =SUMPRODUCT(B44:U44*($B$16:$U$16="")) -> 0 | W44: =SUMPRODUCT($B44:$U44,$B$15:$U$15) -> 0
V45: =SUMPRODUCT(B45:U45*($B$16:$U$16="")) -> 0 | W45: =SUMPRODUCT($B45:$U45,$B$15:$U$15) -> 0
A46: Total | V46: =SUM(V18:V45) -> 56 | W46: =SUM(W18:W45) -> 0
A48: GOALS — number scored | B48: GW1 | C48: GW2 | D48: GW3 | E48: GW4 | F48: GW5 | G48: GW6 | H48: GW7 | I48: GW8 | J48: GW9 | K48: GW10 | L48: GW11 | M48: GW12 | N48: GW13 | O48: GW14 | P48: GW15 | Q48: GW16 | R48: GW17 | S48: GW18 | T48: GW19 | U48: GW20 | V48: Goals
A49: =IF($A18="","",$A18) -> Ahmed | V49: =SUMPRODUCT(B49:U49*($B$16:$U$16="")) -> 0
A50: =IF($A19="","",$A19) -> Alex Ruben | V50: =SUMPRODUCT(B50:U50*($B$16:$U$16="")) -> 0
A51: =IF($A20="","",$A20) -> Andy Cowan | V51: =SUMPRODUCT(B51:U51*($B$16:$U$16="")) -> 0
A52: =IF($A21="","",$A21) -> Ben Merrett | V52: =SUMPRODUCT(B52:U52*($B$16:$U$16="")) -> 0
A53: =IF($A22="","",$A22) -> Callum McCarthy | V53: =SUMPRODUCT(B53:U53*($B$16:$U$16="")) -> 0
A54: =IF($A23="","",$A23) -> Cecil Watson | V54: =SUMPRODUCT(B54:U54*($B$16:$U$16="")) -> 0
A55: =IF($A24="","",$A24) -> Conall Templeman | V55: =SUMPRODUCT(B55:U55*($B$16:$U$16="")) -> 0
A56: =IF($A25="","",$A25) -> Eddie Ringer | V56: =SUMPRODUCT(B56:U56*($B$16:$U$16="")) -> 0
A57: =IF($A26="","",$A26) -> Finn Cawley | F57: 2 | G57: 1 | V57: =SUMPRODUCT(B57:U57*($B$16:$U$16="")) -> 3
A58: =IF($A27="","",$A27) -> George Barbantan | I58: 2 | V58: =SUMPRODUCT(B58:U58*($B$16:$U$16="")) -> 2
A59: =IF($A28="","",$A28) -> Henry Linklater | V59: =SUMPRODUCT(B59:U59*($B$16:$U$16="")) -> 0
A60: =IF($A29="","",$A29) -> Isaac Mond | V60: =SUMPRODUCT(B60:U60*($B$16:$U$16="")) -> 0
A61: =IF($A30="","",$A30) -> Jake Harrison | V61: =SUMPRODUCT(B61:U61*($B$16:$U$16="")) -> 0
A62: =IF($A31="","",$A31) -> Jake Ringer | V62: =SUMPRODUCT(B62:U62*($B$16:$U$16="")) -> 0
A63: =IF($A32="","",$A32) -> Keshav Singh | V63: =SUMPRODUCT(B63:U63*($B$16:$U$16="")) -> 0
A64: =IF($A33="","",$A33) -> Mark Pellowe | V64: =SUMPRODUCT(B64:U64*($B$16:$U$16="")) -> 0
A65: =IF($A34="","",$A34) -> Max Cobain | D65: 1 | F65: 1 | G65: 1 | H65: 1 | V65: =SUMPRODUCT(B65:U65*($B$16:$U$16="")) -> 4
A66: =IF($A35="","",$A35) -> Neeraj Radia | V66: =SUMPRODUCT(B66:U66*($B$16:$U$16="")) -> 0
A67: =IF($A36="","",$A36) -> Phil Knott | E67: 1 | V67: =SUMPRODUCT(B67:U67*($B$16:$U$16="")) -> 1
A68: =IF($A37="","",$A37) -> Robin | V68: =SUMPRODUCT(B68:U68*($B$16:$U$16="")) -> 0
A69: =IF($A38="","",$A38) -> Sam Holt | B69: 1 | V69: =SUMPRODUCT(B69:U69*($B$16:$U$16="")) -> 1
A70: =IF($A39="","",$A39) -> Seb Burgess | B70: 1 | E70: 2 | I70: 2 | V70: =SUMPRODUCT(B70:U70*($B$16:$U$16="")) -> 5
A71: =IF($A40="","",$A40) | V71: =SUMPRODUCT(B71:U71*($B$16:$U$16="")) -> 0
A72: =IF($A41="","",$A41) | V72: =SUMPRODUCT(B72:U72*($B$16:$U$16="")) -> 0
A73: =IF($A42="","",$A42) | V73: =SUMPRODUCT(B73:U73*($B$16:$U$16="")) -> 0
A74: =IF($A43="","",$A43) | V74: =SUMPRODUCT(B74:U74*($B$16:$U$16="")) -> 0
A75: =IF($A44="","",$A44) | V75: =SUMPRODUCT(B75:U75*($B$16:$U$16="")) -> 0
A76: =IF($A45="","",$A45) | V76: =SUMPRODUCT(B76:U76*($B$16:$U$16="")) -> 0
A77: Total | V77: =SUM(V49:V76) -> 16
A79: ASSISTS — number made | B79: GW1 | C79: GW2 | D79: GW3 | E79: GW4 | F79: GW5 | G79: GW6 | H79: GW7 | I79: GW8 | J79: GW9 | K79: GW10 | L79: GW11 | M79: GW12 | N79: GW13 | O79: GW14 | P79: GW15 | Q79: GW16 | R79: GW17 | S79: GW18 | T79: GW19 | U79: GW20 | V79: Assists
A80: =IF($A18="","",$A18) -> Ahmed | V80: =SUMPRODUCT(B80:U80*($B$16:$U$16="")) -> 0
A81: =IF($A19="","",$A19) -> Alex Ruben | V81: =SUMPRODUCT(B81:U81*($B$16:$U$16="")) -> 0
A82: =IF($A20="","",$A20) -> Andy Cowan | B82: 1 | V82: =SUMPRODUCT(B82:U82*($B$16:$U$16="")) -> 1
A83: =IF($A21="","",$A21) -> Ben Merrett | V83: =SUMPRODUCT(B83:U83*($B$16:$U$16="")) -> 0
A84: =IF($A22="","",$A22) -> Callum McCarthy | V84: =SUMPRODUCT(B84:U84*($B$16:$U$16="")) -> 0
A85: =IF($A23="","",$A23) -> Cecil Watson | V85: =SUMPRODUCT(B85:U85*($B$16:$U$16="")) -> 0
A86: =IF($A24="","",$A24) -> Conall Templeman | V86: =SUMPRODUCT(B86:U86*($B$16:$U$16="")) -> 0
A87: =IF($A25="","",$A25) -> Eddie Ringer | V87: =SUMPRODUCT(B87:U87*($B$16:$U$16="")) -> 0
A88: =IF($A26="","",$A26) -> Finn Cawley | V88: =SUMPRODUCT(B88:U88*($B$16:$U$16="")) -> 0
A89: =IF($A27="","",$A27) -> George Barbantan | V89: =SUMPRODUCT(B89:U89*($B$16:$U$16="")) -> 0
A90: =IF($A28="","",$A28) -> Henry Linklater | V90: =SUMPRODUCT(B90:U90*($B$16:$U$16="")) -> 0
A91: =IF($A29="","",$A29) -> Isaac Mond | V91: =SUMPRODUCT(B91:U91*($B$16:$U$16="")) -> 0
A92: =IF($A30="","",$A30) -> Jake Harrison | V92: =SUMPRODUCT(B92:U92*($B$16:$U$16="")) -> 0
A93: =IF($A31="","",$A31) -> Jake Ringer | V93: =SUMPRODUCT(B93:U93*($B$16:$U$16="")) -> 0
A94: =IF($A32="","",$A32) -> Keshav Singh | V94: =SUMPRODUCT(B94:U94*($B$16:$U$16="")) -> 0
... A97: =IF($A35="","",$A35) -> Neeraj Radia | V97: =SUMPRODUCT(B97:U97*($B$16:$U$16="")) -> 0
A98: =IF($A36="","",$A36) -> Phil Knott | B98: 1 | D98: 1 | V98: =SUMPRODUCT(B98:U98*($B$16:$U$16="")) -> 2
A99: =IF($A37="","",$A37) -> Robin | V99: =SUMPRODUCT(B99:U99*($B$16:$U$16="")) -> 0
A100: =IF($A38="","",$A38) -> Sam Holt | V100: =SUMPRODUCT(B100:U100*($B$16:$U$16="")) -> 0
A101: =IF($A39="","",$A39) -> Seb Burgess | V101: =SUMPRODUCT(B101:U101*($B$16:$U$16="")) -> 0
A102: =IF($A40="","",$A40) | V102: =SUMPRODUCT(B102:U102*($B$16:$U$16="")) -> 0
A103: =IF($A41="","",$A41) | V103: =SUMPRODUCT(B103:U103*($B$16:$U$16="")) -> 0
A104: =IF($A42="","",$A42) | V104: =SUMPRODUCT(B104:U104*($B$16:$U$16="")) -> 0
...

Sheet S3
A1: Season 3 · PlayFootball Old Street (5G, 6-a-side) · Mar–Jun 2025
A2: Match | B2: GW1 | C2: GW2 | D2: GW3 | E2: GW4 | F2: GW5 | G2: GW6 | H2: GW7 | I2: GW8 | J2: GW9 | K2: GW10 | L2: GW11 | M2: GW12 | N2: GW13 | O2: GW14 | P2: GW15 | Q2: GW16 | R2: GW17 | S2: GW18 | T2: GW19 | U2: GW20 | X2: SEASON SUMMARY
A3: Date | B3: 45742 | C3: 45743 | D3: 45750 | E3: 45757 | F3: 45764 | G3: 45771 | H3: 45778 | I3: 45785 | J3: 45792 | K3: 45799 | L3: 45806 | M3: 45813 | N3: 45820 | O3: 45827 | X3: Played | Y3: =Y4+Y5+Y6 -> 13
A4: Kick-off | X4: Won | Y4: =SUMPRODUCT(($B$9:$U$9="W")*($B$16:$U$16="")) -> 1
A5: Opponent | B5: Forfeit | C5: Enjoy your Mane Jane | D5: Dukes Select | E5: Dign Cats | F5: Old Ivy | G5: Green of the South | H5: The Britannias | I5: Spudos | J5: Old Ivy | K5: Green of the South | L5: Ding cats | M5: The Britannias | N5: Dukes Select | O5: Enjoy your Mane Jane | X5: Drawn | Y5: =SUMPRODUCT(($B$9:$U$9="D")*($B$16:$U$16="")) -> 1
A6: Our goals | B6: 8 | C6: 2 | D6: 1 | E6: 2 | F6: 4 | G6: 2 | H6: 1 | I6: 10 | J6: 3 | K6: 3 | L6: 1 | M6: 2 | N6: 3 | O6: 1 | X6: Lost | Y6: =SUMPRODUCT(($B$9:$U$9="L")*($B$16:$U$16="")) -> 11
A7: Their goals | B7: 0 | C7: 11 | D7: 7 | E7: 6 | F7: 8 | G7: 5 | H7: 4 | I7: 0 | J7: 9 | K7: 13 | L7: 6 | M7: 13 | N7: 3 | O7: 12 | X7: Goals for | Y7: =SUMPRODUCT($B$6:$U$6*($B$16:$U$16="")) -> 35
A8: Score | B8: =IF(COUNT(B6:B7)<2,"",B6&"-"&B7) -> 8-0 | C8: =IF(COUNT(C6:C7)<2,"",C6&"-"&C7) -> 2-11 | D8: =IF(COUNT(D6:D7)<2,"",D6&"-"&D7) -> 1-7 | E8: =IF(COUNT(E6:E7)<2,"",E6&"-"&E7) -> 2-6 | F8: =IF(COUNT(F6:F7)<2,"",F6&"-"&F7) -> 4-8 | G8: =IF(COUNT(G6:G7)<2,"",G6&"-"&G7) -> 2-5 | H8: =IF(COUNT(H6:H7)<2,"",H6&"-"&H7) -> 1-4 | I8: =IF(COUNT(I6:I7)<2,"",I6&"-"&I7) -> 10-0 | ... U8: =IF(COUNT(U6:U7)<2,"",U6&"-"&U7) | X8: Goals against | Y8: =SUMPRODUCT($B$7:$U$7*($B$16:$U$16="")) -> 97
A9: Result | B9: =IF(COUNT(B6:B7)<2,"",IF(B6>B7,"W",IF(B6<B7,"L","D"))) -> W | C9: =IF(COUNT(C6:C7)<2,"",IF(C6>C7,"W",IF(C6<C7,"L","D"))) -> L | D9: =IF(COUNT(D6:D7)<2,"",IF(D6>D7,"W",IF(D6<D7,"L","D"))) -> L | E9: =IF(COUNT(E6:E7)<2,"",IF(E6>E7,"W",IF(E6<E7,"L","D"))) -> L | F9: =IF(COUNT(F6:F7)<2,"",IF(F6>F7,"W",IF(F6<F7,"L","D"))) -> L | G9: =IF(COUNT(G6:G7)<2,"",IF(G6>G7,"W",IF(G6<G7,"L","D"))) -> L | H9: =IF(COUNT(H6:H7)<2,"",IF(H6>H7,"W",IF(H6<H7,"L","D"))) -> L | I9: =IF(COUNT(I6:I7)<2,"",IF(I6>I7,"W",IF(I6<I7,"L","D"))) -> W | ... U9: =IF(COUNT(U6:U7)<2,"",IF(U6>U7,"W",IF(U6<U7,"L","D"))) | X9: Top scorer | Y9: {=IF(MAX($V$49:$V$76)=0,"—",INDEX($A$49:$A$76,MATCH(MAX($V$49:$V$76),$V$49:$V$76,0))&" ("&MAX($V$49:$V$76)&")")} -> Phil Knott (7)
A10: MOTM | X10: Most apps | Y10: {=IF(MAX($V$18:$V$45)=0,"—",INDEX($A$18:$A$45,MATCH(MAX($V$18:$V$45),$V$18:$V$45,0))&" ("&MAX($V$18:$V$45)&")")} -> Andy Cowan (10)
A11: Champagne moment | X11: Season cost | Y11: =SUM($B$13:$U$13) -> 0
A12: Comments | X12: Paid by
A13: Match cost (£)
A14: Players in game | B14: =COUNT(B$18:B$45) -> 0 | C14: =COUNT(C$18:C$45) -> 6 | D14: =COUNT(D$18:D$45) -> 8 | E14: =COUNT(E$18:E$45) -> 6 | F14: =COUNT(F$18:F$45) -> 7 | G14: =COUNT(G$18:G$45) -> 7 | H14: =COUNT(H$18:H$45) -> 8 | I14: =COUNT(I$18:I$45) -> 8 | ... U14: =COUNT(U$18:U$45) -> 0
A15: Cost per player (£) | B15: =IF(B$14=0,0,N(B$13)/B$14) -> 0 | C15: =IF(C$14=0,0,N(C$13)/C$14) -> 0 | D15: =IF(D$14=0,0,N(D$13)/D$14) -> 0 | E15: =IF(E$14=0,0,N(E$13)/E$14) -> 0 | F15: =IF(F$14=0,0,N(F$13)/F$14) -> 0 | G15: =IF(G$14=0,0,N(G$13)/G$14) -> 0 | H15: =IF(H$14=0,0,N(H$13)/H$14) -> 0 | I15: =IF(I$14=0,0,N(I$13)/I$14) -> 0 | ... U15: =IF(U$14=0,0,N(U$13)/U$14) -> 0
A16: Type (excl. from records) | B16: Forfeit
A17: APPEARANCES (1 = played) | B17: GW1 | C17: GW2 | D17: GW3 | E17: GW4 | F17: GW5 | G17: GW6 | H17: GW7 | I17: GW8 | J17: GW9 | K17: GW10 | L17: GW11 | M17: GW12 | N17: GW13 | O17: GW14 | P17: GW15 | Q17: GW16 | R17: GW17 | S17: GW18 | T17: GW19 | U17: GW20 | V17: Apps | W17: Cost (£)
A18: Ahmed | V18: =SUMPRODUCT(B18:U18*($B$16:$U$16="")) -> 0 | W18: =SUMPRODUCT($B18:$U18,$B$15:$U$15) -> 0
A19: Alex Ruben | K19: 1 | O19: 1 | V19: =SUMPRODUCT(B19:U19*($B$16:$U$16="")) -> 2 | W19: =SUMPRODUCT($B19:$U19,$B$15:$U$15) -> 0
A20: Andy Cowan | C20: 1 | E20: 1 | F20: 1 | G20: 1 | I20: 1 | K20: 1 | L20: 1 | M20: 1 | N20: 1 | O20: 1 | V20: =SUMPRODUCT(B20:U20*($B$16:$U$16="")) -> 10 | W20: =SUMPRODUCT($B20:$U20,$B$15:$U$15) -> 0
A21: Ben Merrett | D21: 1 | F21: 1 | G21: 1 | H21: 1 | I21: 1 | K21: 1 | L21: 1 | N21: 1 | V21: =SUMPRODUCT(B21:U21*($B$16:$U$16="")) -> 8 | W21: =SUMPRODUCT($B21:$U21,$B$15:$U$15) -> 0
A22: Callum McCarthy | D22: 1 | E22: 1 | H22: 1 | I22: 1 | J22: 1 | L22: 1 | N22: 1 | V22: =SUMPRODUCT(B22:U22*($B$16:$U$16="")) -> 7 | W22: =SUMPRODUCT($B22:$U22,$B$15:$U$15) -> 0
A23: Cecil Watson | J23: 1 | V23: =SUMPRODUCT(B23:U23*($B$16:$U$16="")) -> 1 | W23: =SUMPRODUCT($B23:$U23,$B$15:$U$15) -> 0
A24: Conall Templeman | V24: =SUMPRODUCT(B24:U24*($B$16:$U$16="")) -> 0 | W24: =SUMPRODUCT($B24:$U24,$B$15:$U$15) -> 0
A25: Eddie Ringer | V25: =SUMPRODUCT(B25:U25*($B$16:$U$16="")) -> 0 | W25: =SUMPRODUCT($B25:$U25,$B$15:$U$15) -> 0
A26: Finn Cawley | C26: 1 | D26: 1 | E26: 1 | I26: 1 | K26: 1 | M26: 1 | O26: 1 | V26: =SUMPRODUCT(B26:U26*($B$16:$U$16="")) -> 7 | W26: =SUMPRODUCT($B26:$U26,$B$15:$U$15) -> 0
A27: George Barbantan | F27: 1 | H27: 1 | I27: 1 | J27: 1 | K27: 1 | V27: =SUMPRODUCT(B27:U27*($B$16:$U$16="")) -> 5 | W27: =SUMPRODUCT($B27:$U27,$B$15:$U$15) -> 0
A28: Henry Linklater | C28: 1 | J28: 1 | V28: =SUMPRODUCT(B28:U28*($B$16:$U$16="")) -> 2 | W28: =SUMPRODUCT($B28:$U28,$B$15:$U$15) -> 0
A29: Isaac Mond | C29: 1 | D29: 1 | E29: 1 | F29: 1 | G29: 1 | H29: 1 | I29: 1 | K29: 1 | L29: 1 | N29: 1 | V29: =SUMPRODUCT(B29:U29*($B$16:$U$16="")) -> 10 | W29: =SUMPRODUCT($B29:$U29,$B$15:$U$15) -> 0
A30: Jake Harrison | V30: =SUMPRODUCT(B30:U30*($B$16:$U$16="")) -> 0 | W30: =SUMPRODUCT($B30:$U30,$B$15:$U$15) -> 0
A31: Jake Ringer | V31: =SUMPRODUCT(B31:U31*($B$16:$U$16="")) -> 0 | W31: =SUMPRODUCT($B31:$U31,$B$15:$U$15) -> 0
A32: Keshav Singh | V32: =SUMPRODUCT(B32:U32*($B$16:$U$16="")) -> 0 | W32: =SUMPRODUCT($B32:$U32,$B$15:$U$15) -> 0
A33: Mark Pellowe | V33: =SUMPRODUCT(B33:U33*($B$16:$U$16="")) -> 0 | W33: =SUMPRODUCT($B33:$U33,$B$15:$U$15) -> 0
A34: Max Cobain | C34: 1 | D34: 1 | F34: 1 | G34: 1 | H34: 1 | J34: 1 | M34: 1 | O34: 1 | V34: =SUMPRODUCT(B34:U34*($B$16:$U$16="")) -> 8 | W34: =SUMPRODUCT($B34:$U34,$B$15:$U$15) -> 0
A35: Neeraj Radia | D35: 1 | F35: 1 | G35: 1 | H35: 1 | I35: 1 | J35: 1 | L35: 1 | V35: =SUMPRODUCT(B35:U35*($B$16:$U$16="")) -> 7 | W35: =SUMPRODUCT($B35:$U35,$B$15:$U$15) -> 0
A36: Phil Knott | D36: 1 | E36: 1 | G36: 1 | H36: 1 | I36: 1 | K36: 1 | L36: 1 | N36: 1 | O36: 1 | V36: =SUMPRODUCT(B36:U36*($B$16:$U$16="")) -> 9 | W36: =SUMPRODUCT($B36:$U36,$B$15:$U$15) -> 0
A37: Robin | V37: =SUMPRODUCT(B37:U37*($B$16:$U$16="")) -> 0 | W37: =SUMPRODUCT($B37:$U37,$B$15:$U$15) -> 0
A38: Sam Holt | C38: 1 | V38: =SUMPRODUCT(B38:U38*($B$16:$U$16="")) -> 1 | W38: =SUMPRODUCT($B38:$U38,$B$15:$U$15) -> 0
A39: Seb Burgess | D39: 1 | E39: 1 | F39: 1 | G39: 1 | H39: 1 | K39: 1 | L39: 1 | M39: 1 | N39: 1 | V39: =SUMPRODUCT(B39:U39*($B$16:$U$16="")) -> 9 | W39: =SUMPRODUCT($B39:$U39,$B$15:$U$15) -> 0
V40: =SUMPRODUCT(B40:U40*($B$16:$U$16="")) -> 0 | W40: =SUMPRODUCT($B40:$U40,$B$15:$U$15) -> 0
V41: =SUMPRODUCT(B41:U41*($B$16:$U$16="")) -> 0 | W41: =SUMPRODUCT($B41:$U41,$B$15:$U$15) -> 0
V42: =SUMPRODUCT(B42:U42*($B$16:$U$16="")) -> 0 | W42: =SUMPRODUCT($B42:$U42,$B$15:$U$15) -> 0
V43: =SUMPRODUCT(B43:U43*($B$16:$U$16="")) -> 0 | W43: =SUMPRODUCT($B43:$U43,$B$15:$U$15) -> 0
V44: =SUMPRODUCT(B44:U44*($B$16:$U$16="")) -> 0 | W44: =SUMPRODUCT($B44:$U44,$B$15:$U$15) -> 0
V45: =SUMPRODUCT(B45:U45*($B$16:$U$16="")) -> 0 | W45: =SUMPRODUCT($B45:$U45,$B$15:$U$15) -> 0
A46: Total | V46: =SUM(V18:V45) -> 86 | W46: =SUM(W18:W45) -> 0
A48: GOALS — number scored | B48: GW1 | C48: GW2 | D48: GW3 | E48: GW4 | F48: GW5 | G48: GW6 | H48: GW7 | I48: GW8 | J48: GW9 | K48: GW10 | L48: GW11 | M48: GW12 | N48: GW13 | O48: GW14 | P48: GW15 | Q48: GW16 | R48: GW17 | S48: GW18 | T48: GW19 | U48: GW20 | V48: Goals
A49: =IF($A18="","",$A18) -> Ahmed | V49: =SUMPRODUCT(B49:U49*($B$16:$U$16="")) -> 0
A50: =IF($A19="","",$A19) -> Alex Ruben | V50: =SUMPRODUCT(B50:U50*($B$16:$U$16="")) -> 0
A51: =IF($A20="","",$A20) -> Andy Cowan | I51: 1 | V51: =SUMPRODUCT(B51:U51*($B$16:$U$16="")) -> 1
A52: =IF($A21="","",$A21) -> Ben Merrett | I52: 1 | K52: 1 | V52: =SUMPRODUCT(B52:U52*($B$16:$U$16="")) -> 2
A53: =IF($A22="","",$A22) -> Callum McCarthy | I53: 2 | V53: =SUMPRODUCT(B53:U53*($B$16:$U$16="")) -> 2
A54: =IF($A23="","",$A23) -> Cecil Watson | V54: =SUMPRODUCT(B54:U54*($B$16:$U$16="")) -> 0
A55: =IF($A24="","",$A24) -> Conall Templeman | V55: =SUMPRODUCT(B55:U55*($B$16:$U$16="")) -> 0
A56: =IF($A25="","",$A25) -> Eddie Ringer | V56: =SUMPRODUCT(B56:U56*($B$16:$U$16="")) -> 0
A57: =IF($A26="","",$A26) -> Finn Cawley | C57: 2 | K57: 1 | M57: 1 | O57: 1 | V57: =SUMPRODUCT(B57:U57*($B$16:$U$16="")) -> 5
A58: =IF($A27="","",$A27) -> George Barbantan | I58: 1 | V58: =SUMPRODUCT(B58:U58*($B$16:$U$16="")) -> 1
A59: =IF($A28="","",$A28) -> Henry Linklater | V59: =SUMPRODUCT(B59:U59*($B$16:$U$16="")) -> 0
A60: =IF($A29="","",$A29) -> Isaac Mond | I60: 1 | V60: =SUMPRODUCT(B60:U60*($B$16:$U$16="")) -> 1
A61: =IF($A30="","",$A30) -> Jake Harrison | V61: =SUMPRODUCT(B61:U61*($B$16:$U$16="")) -> 0
A62: =IF($A31="","",$A31) -> Jake Ringer | V62: =SUMPRODUCT(B62:U62*($B$16:$U$16="")) -> 0
A63: =IF($A32="","",$A32) -> Keshav Singh | V63: =SUMPRODUCT(B63:U63*($B$16:$U$16="")) -> 0
A64: =IF($A33="","",$A33) -> Mark Pellowe | V64: =SUMPRODUCT(B64:U64*($B$16:$U$16="")) -> 0
A65: =IF($A34="","",$A34) -> Max Cobain | F65: 2 | J65: 2 | M65: 1 | V65: =SUMPRODUCT(B65:U65*($B$16:$U$16="")) -> 5
A66: =IF($A35="","",$A35) -> Neeraj Radia | G66: 1 | I66: 2 | J66: 1 | V66: =SUMPRODUCT(B66:U66*($B$16:$U$16="")) -> 4
A67: =IF($A36="","",$A36) -> Phil Knott | D67: 1 | E67: 1 | I67: 2 | K67: 1 | N67: 2 | V67: =SUMPRODUCT(B67:U67*($B$16:$U$16="")) -> 7
A68: =IF($A37="","",$A37) -> Robin | V68: =SUMPRODUCT(B68:U68*($B$16:$U$16="")) -> 0
A69: =IF($A38="","",$A38) -> Sam Holt | V69: =SUMPRODUCT(B69:U69*($B$16:$U$16="")) -> 0
A70: =IF($A39="","",$A39) -> Seb Burgess | E70: 1 | F70: 1 | G70: 1 | H70: 1 | L70: 1 | N70: 1 | V70: =SUMPRODUCT(B70:U70*($B$16:$U$16="")) -> 6
A71: =IF($A40="","",$A40) | V71: =SUMPRODUCT(B71:U71*($B$16:$U$16="")) -> 0
A72: =IF($A41="","",$A41) | V72: =SUMPRODUCT(B72:U72*($B$16:$U$16="")) -> 0
A73: =IF($A42="","",$A42) | V73: =SUMPRODUCT(B73:U73*($B$16:$U$16="")) -> 0
A74: =IF($A43="","",$A43) | V74: =SUMPRODUCT(B74:U74*($B$16:$U$16="")) -> 0
A75: =IF($A44="","",$A44) | V75: =SUMPRODUCT(B75:U75*($B$16:$U$16="")) -> 0
A76: =IF($A45="","",$A45) | V76: =SUMPRODUCT(B76:U76*($B$16:$U$16="")) -> 0
A77: Total | V77: =SUM(V49:V76) -> 34
A79: ASSISTS — number made | B79: GW1 | C79: GW2 | D79: GW3 | E79: GW4 | F79: GW5 | G79: GW6 | H79: GW7 | I79: GW8 | J79: GW9 | K79: GW10 | L79: GW11 | M79: GW12 | N79: GW13 | O79: GW14 | P79: GW15 | Q79: GW16 | R79: GW17 | S79: GW18 | T79: GW19 | U79: GW20 | V79: Assists
A80: =IF($A18="","",$A18) -> Ahmed | V80: =SUMPRODUCT(B80:U80*($B$16:$U$16="")) -> 0
A81: =IF($A19="","",$A19) -> Alex Ruben | V81: =SUMPRODUCT(B81:U81*($B$16:$U$16="")) -> 0
A82: =IF($A20="","",$A20) -> Andy Cowan | V82: =SUMPRODUCT(B82:U82*($B$16:$U$16="")) -> 0
A83: =IF($A21="","",$A21) -> Ben Merrett | V83: =SUMPRODUCT(B83:U83*($B$16:$U$16="")) -> 0
A84: =IF($A22="","",$A22) -> Callum McCarthy | V84: =SUMPRODUCT(B84:U84*($B$16:$U$16="")) -> 0
A85: =IF($A23="","",$A23) -> Cecil Watson | V85: =SUMPRODUCT(B85:U85*($B$16:$U$16="")) -> 0
A86: =IF($A24="","",$A24) -> Conall Templeman | V86: =SUMPRODUCT(B86:U86*($B$16:$U$16="")) -> 0
A87: =IF($A25="","",$A25) -> Eddie Ringer | V87: =SUMPRODUCT(B87:U87*($B$16:$U$16="")) -> 0
A88: =IF($A26="","",$A26) -> Finn Cawley | V88: =SUMPRODUCT(B88:U88*($B$16:$U$16="")) -> 0
A89: =IF($A27="","",$A27) -> George Barbantan | V89: =SUMPRODUCT(B89:U89*($B$16:$U$16="")) -> 0
A90: =IF($A28="","",$A28) -> Henry Linklater | V90: =SUMPRODUCT(B90:U90*($B$16:$U$16="")) -> 0
A91: =IF($A29="","",$A29) -> Isaac Mond | V91: =SUMPRODUCT(B91:U91*($B$16:$U$16="")) -> 0
... A107: =IF($A45="","",$A45) | V107: =SUMPRODUCT(B107:U107*($B$16:$U$16="")) -> 0
A108: Total | V108: =SUM(V80:V107) -> 0

Sheet S4
A1: Season 4 · PlayFootball Old Street (5G, 6-a-side) · Jul–Oct 2025
A2: Match | B2: GW1 | C2: GW2 | D2: GW3 | E2: GW4 | F2: GW5 | G2: GW6 | H2: GW7 | I2: GW8 | J2: GW9 | K2: GW10 | L2: GW11 | M2: GW12 | N2: GW13 | O2: GW14 | P2: GW15 | Q2: GW16 | R2: GW17 | S2: GW18 | T2: GW19 | U2: GW20 | X2: SEASON SUMMARY
A3: Date | B3: 45841 | C3: 45848 | D3: 45855 | E3: 45862 | F3: 45869 | G3: 45876 | H3: 45883 | I3: 45890 | J3: 45897 | K3: 45904 | L3: 45911 | M3: 45918 | N3: 45925 | O3: 45932 | X3: Played | Y3: =Y4+Y5+Y6 -> 11
A4: Kick-off | X4: Won | Y4: =SUMPRODUCT(($B$9:$U$9="W")*($B$16:$U$16="")) -> 2
A5: Opponent | B5: Dukes Select | C5: Ding Cats | D5: Green of the South | E5: Enjoy your Mane Jane | F5: Old Ivy | G5: Spudos FC | H5: The Britannias | I5: DingCats | J5: Dukes Select | K5: Old ivy | L5: Spudos | M5: Enjoy your mane Jane | N5: The Britannias | O5: Green of the South | X5: Drawn | Y5: =SUMPRODUCT(($B$9:$U$9="D")*($B$16:$U$16="")) -> 0
A6: Our goals | B6: 3 | C6: 2 | D6: 4 | E6: 4 | F6: 2 | G6: 2 | H6: 4 | I6: 2 | L6: 5 | N6: 0 | O6: 2 | X6: Lost | Y6: =SUMPRODUCT(($B$9:$U$9="L")*($B$16:$U$16="")) -> 9
A7: Their goals | B7: 8 | C7: 7 | D7: 8 | E7: 7 | F7: 6 | G7: 7 | H7: 3 | I7: 6 | L7: 1 | N7: 3 | O7: 4 | X7: Goals for | Y7: =SUMPRODUCT($B$6:$U$6*($B$16:$U$16="")) -> 30
A8: Score | B8: =IF(COUNT(B6:B7)<2,"",B6&"-"&B7) -> 3-8 | C8: =IF(COUNT(C6:C7)<2,"",C6&"-"&C7) -> 2-7 | D8: =IF(COUNT(D6:D7)<2,"",D6&"-"&D7) -> 4-8 | E8: =IF(COUNT(E6:E7)<2,"",E6&"-"&E7) -> 4-7 | F8: =IF(COUNT(F6:F7)<2,"",F6&"-"&F7) -> 2-6 | G8: =IF(COUNT(G6:G7)<2,"",G6&"-"&G7) -> 2-7 | H8: =IF(COUNT(H6:H7)<2,"",H6&"-"&H7) -> 4-3 | I8: =IF(COUNT(I6:I7)<2,"",I6&"-"&I7) -> 2-6 | ... U8: =IF(COUNT(U6:U7)<2,"",U6&"-"&U7) | X8: Goals against | Y8: =SUMPRODUCT($B$7:$U$7*($B$16:$U$16="")) -> 60
A9: Result | B9: =IF(COUNT(B6:B7)<2,"",IF(B6>B7,"W",IF(B6<B7,"L","D"))) -> L | C9: =IF(COUNT(C6:C7)<2,"",IF(C6>C7,"W",IF(C6<C7,"L","D"))) -> L | D9: =IF(COUNT(D6:D7)<2,"",IF(D6>D7,"W",IF(D6<D7,"L","D"))) -> L | E9: =IF(COUNT(E6:E7)<2,"",IF(E6>E7,"W",IF(E6<E7,"L","D"))) -> L | F9: =IF(COUNT(F6:F7)<2,"",IF(F6>F7,"W",IF(F6<F7,"L","D"))) -> L | G9: =IF(COUNT(G6:G7)<2,"",IF(G6>G7,"W",IF(G6<G7,"L","D"))) -> L | H9: =IF(COUNT(H6:H7)<2,"",IF(H6>H7,"W",IF(H6<H7,"L","D"))) -> W | I9: =IF(COUNT(I6:I7)<2,"",IF(I6>I7,"W",IF(I6<I7,"L","D"))) -> L | ... U9: =IF(COUNT(U6:U7)<2,"",IF(U6>U7,"W",IF(U6<U7,"L","D"))) | X9: Top scorer | Y9: {=IF(MAX($V$49:$V$76)=0,"—",INDEX($A$49:$A$76,MATCH(MAX($V$49:$V$76),$V$49:$V$76,0))&" ("&MAX($V$49:$V$76)&")")} -> Seb Burgess (14)
A10: MOTM | B10: Phil Knott | X10: Most apps | Y10: {=IF(MAX($V$18:$V$45)=0,"—",INDEX($A$18:$A$45,MATCH(MAX($V$18:$V$45),$V$18:$V$45,0))&" ("&MAX($V$18:$V$45)&")")} -> Seb Burgess (13)
A11: Champagne moment | X11: Season cost | Y11: =SUM($B$13:$U$13) -> 0
A12: Comments | J12: score not recorded | K12: score not recorded | M12: score not recorded | X12: Paid by
A13: Match cost (£)
A14: Players in game | B14: =COUNT(B$18:B$45) -> 5 | C14: =COUNT(C$18:C$45) -> 7 | D14: =COUNT(D$18:D$45) -> 6 | E14: =COUNT(E$18:E$45) -> 7 | F14: =COUNT(F$18:F$45) -> 6 | G14: =COUNT(G$18:G$45) -> 7 | H14: =COUNT(H$18:H$45) -> 5 | I14: =COUNT(I$18:I$45) -> 6 | ... U14: =COUNT(U$18:U$45) -> 0
A15: Cost per player (£) | B15: =IF(B$14=0,0,N(B$13)/B$14) -> 0 | C15: =IF(C$14=0,0,N(C$13)/C$14) -> 0 | D15: =IF(D$14=0,0,N(D$13)/D$14) -> 0 | E15: =IF(E$14=0,0,N(E$13)/E$14) -> 0 | F15: =IF(F$14=0,0,N(F$13)/F$14) -> 0 | G15: =IF(G$14=0,0,N(G$13)/G$14) -> 0 | H15: =IF(H$14=0,0,N(H$13)/H$14) -> 0 | I15: =IF(I$14=0,0,N(I$13)/I$14) -> 0 | ... U15: =IF(U$14=0,0,N(U$13)/U$14) -> 0
A16: Type (excl. from records)
A17: APPEARANCES (1 = played) | B17: GW1 | C17: GW2 | D17: GW3 | E17: GW4 | F17: GW5 | G17: GW6 | H17: GW7 | I17: GW8 | J17: GW9 | K17: GW10 | L17: GW11 | M17: GW12 | N17: GW13 | O17: GW14 | P17: GW15 | Q17: GW16 | R17: GW17 | S17: GW18 | T17: GW19 | U17: GW20 | V17: Apps | W17: Cost (£)
A18: Ahmed | V18: =SUMPRODUCT(B18:U18*($B$16:$U$16="")) -> 0 | W18: =SUMPRODUCT($B18:$U18,$B$15:$U$15) -> 0
A19: Alex Ruben | D19: 1 | V19: =SUMPRODUCT(B19:U19*($B$16:$U$16="")) -> 1 | W19: =SUMPRODUCT($B19:$U19,$B$15:$U$15) -> 0
A20: Andy Cowan | B20: 1 | C20: 1 | F20: 1 | H20: 1 | J20: 1 | K20: 1 | L20: 1 | N20: 1 | O20: 1 | V20: =SUMPRODUCT(B20:U20*($B$16:$U$16="")) -> 9 | W20: =SUMPRODUCT($B20:$U20,$B$15:$U$15) -> 0
A21: Ben Merrett | C21: 1 | D21: 1 | E21: 1 | I21: 1 | J21: 1 | K21: 1 | L21: 1 | M21: 1 | V21: =SUMPRODUCT(B21:U21*($B$16:$U$16="")) -> 8 | W21: =SUMPRODUCT($B21:$U21,$B$15:$U$15) -> 0
A22: Callum McCarthy | B22: 1 | D22: 1 | H22: 1 | J22: 1 | K22: 1 | L22: 1 | V22: =SUMPRODUCT(B22:U22*($B$16:$U$16="")) -> 6 | W22: =SUMPRODUCT($B22:$U22,$B$15:$U$15) -> 0
A23: Cecil Watson | E23: 1 | V23: =SUMPRODUCT(B23:U23*($B$16:$U$16="")) -> 1 | W23: =SUMPRODUCT($B23:$U23,$B$15:$U$15) -> 0
A24: Conall Templeman | V24: =SUMPRODUCT(B24:U24*($B$16:$U$16="")) -> 0 | W24: =SUMPRODUCT($B24:$U24,$B$15:$U$15) -> 0
A25: Eddie Ringer | V25: =SUMPRODUCT(B25:U25*($B$16:$U$16="")) -> 0 | W25: =SUMPRODUCT($B25:$U25,$B$15:$U$15) -> 0
A26: Finn Cawley | C26: 1 | E26: 1 | G26: 1 | I26: 1 | V26: =SUMPRODUCT(B26:U26*($B$16:$U$16="")) -> 4 | W26: =SUMPRODUCT($B26:$U26,$B$15:$U$15) -> 0
A27: George Barbantan | D27: 1 | E27: 1 | F27: 1 | G27: 1 | H27: 1 | I27: 1 | J27: 1 | N27: 1 | O27: 1 | V27: =SUMPRODUCT(B27:U27*($B$16:$U$16="")) -> 9 | W27: =SUMPRODUCT($B27:$U27,$B$15:$U$15) -> 0
A28: Henry Linklater | V28: =SUMPRODUCT(B28:U28*($B$16:$U$16="")) -> 0 | W28: =SUMPRODUCT($B28:$U28,$B$15:$U$15) -> 0
A29: Isaac Mond | C29: 1 | F29: 1 | G29: 1 | J29: 1 | K29: 1 | L29: 1 | M29: 1 | N29: 1 | O29: 1 | V29: =SUMPRODUCT(B29:U29*($B$16:$U$16="")) -> 9 | W29: =SUMPRODUCT($B29:$U29,$B$15:$U$15) -> 0
A30: Jake Harrison | V30: =SUMPRODUCT(B30:U30*($B$16:$U$16="")) -> 0 | W30: =SUMPRODUCT($B30:$U30,$B$15:$U$15) -> 0
A31: Jake Ringer | V31: =SUMPRODUCT(B31:U31*($B$16:$U$16="")) -> 0 | W31: =SUMPRODUCT($B31:$U31,$B$15:$U$15) -> 0
A32: Keshav Singh | V32: =SUMPRODUCT(B32:U32*($B$16:$U$16="")) -> 0 | W32: =SUMPRODUCT($B32:$U32,$B$15:$U$15) -> 0
A33: Mark Pellowe | V33: =SUMPRODUCT(B33:U33*($B$16:$U$16="")) -> 0 | W33: =SUMPRODUCT($B33:$U33,$B$15:$U$15) -> 0
A34: Max Cobain | B34: 1 | C34: 1 | D34: 1 | G34: 1 | I34: 1 | K34: 1 | M34: 1 | N34: 1 | V34: =SUMPRODUCT(B34:U34*($B$16:$U$16="")) -> 8 | W34: =SUMPRODUCT($B34:$U34,$B$15:$U$15) -> 0
A35: Neeraj Radia | C35: 1 | E35: 1 | F35: 1 | G35: 1 | H35: 1 | I35: 1 | J35: 1 | K35: 1 | L35: 1 | V35: =SUMPRODUCT(B35:U35*($B$16:$U$16="")) -> 9 | W35: =SUMPRODUCT($B35:$U35,$B$15:$U$15) -> 0
A36: Phil Knott | B36: 1 | E36: 1 | F36: 1 | G36: 1 | L36: 1 | V36: =SUMPRODUCT(B36:U36*($B$16:$U$16="")) -> 5 | W36: =SUMPRODUCT($B36:$U36,$B$15:$U$15) -> 0
A37: Robin | V37: =SUMPRODUCT(B37:U37*($B$16:$U$16="")) -> 0 | W37: =SUMPRODUCT($B37:$U37,$B$15:$U$15) -> 0
A38: Sam Holt | M38: 1 | N38: 1 | O38: 1 | V38: =SUMPRODUCT(B38:U38*($B$16:$U$16="")) -> 3 | W38: =SUMPRODUCT($B38:$U38,$B$15:$U$15) -> 0
A39: Seb Burgess | B39: 1 | C39: 1 | D39: 1 | E39: 1 | F39: 1 | G39: 1 | H39: 1 | I39: 1 | K39: 1 | L39: 1 | M39: 1 | N39: 1 | O39: 1 | V39: =SUMPRODUCT(B39:U39*($B$16:$U$16="")) -> 13 | W39: =SUMPRODUCT($B39:$U39,$B$15:$U$15) -> 0
V40: =SUMPRODUCT(B40:U40*($B$16:$U$16="")) -> 0 | W40: =SUMPRODUCT($B40:$U40,$B$15:$U$15) -> 0
V41: =SUMPRODUCT(B41:U41*($B$16:$U$16="")) -> 0 | W41: =SUMPRODUCT($B41:$U41,$B$15:$U$15) -> 0
V42: =SUMPRODUCT(B42:U42*($B$16:$U$16="")) -> 0 | W42: =SUMPRODUCT($B42:$U42,$B$15:$U$15) -> 0
V43: =SUMPRODUCT(B43:U43*($B$16:$U$16="")) -> 0 | W43: =SUMPRODUCT($B43:$U43,$B$15:$U$15) -> 0
V44: =SUMPRODUCT(B44:U44*($B$16:$U$16="")) -> 0 | W44: =SUMPRODUCT($B44:$U44,$B$15:$U$15) -> 0
V45: =SUMPRODUCT(B45:U45*($B$16:$U$16="")) -> 0 | W45: =SUMPRODUCT($B45:$U45,$B$15:$U$15) -> 0
A46: Total | V46: =SUM(V18:V45) -> 85 | W46: =SUM(W18:W45) -> 0
A48: GOALS — number scored | B48: GW1 | C48: GW2 | D48: GW3 | E48: GW4 | F48: GW5 | G48: GW6 | H48: GW7 | I48: GW8 | J48: GW9 | K48: GW10 | L48: GW11 | M48: GW12 | N48: GW13 | O48: GW14 | P48: GW15 | Q48: GW16 | R48: GW17 | S48: GW18 | T48: GW19 | U48: GW20 | V48: Goals
A49: =IF($A18="","",$A18) -> Ahmed | V49: =SUMPRODUCT(B49:U49*($B$16:$U$16="")) -> 0
A50: =IF($A19="","",$A19) -> Alex Ruben | V50: =SUMPRODUCT(B50:U50*($B$16:$U$16="")) -> 0
A51: =IF($A20="","",$A20) -> Andy Cowan | F51: 1 | H51: 1 | V51: =SUMPRODUCT(B51:U51*($B$16:$U$16="")) -> 2
A52: =IF($A21="","",$A21) -> Ben Merrett | V52: =SUMPRODUCT(B52:U52*($B$16:$U$16="")) -> 0
A53: =IF($A22="","",$A22) -> Callum McCarthy | B53: 1 | H53: 1 | V53: =SUMPRODUCT(B53:U53*($B$16:$U$16="")) -> 2
A54: =IF($A23="","",$A23) -> Cecil Watson | V54: =SUMPRODUCT(B54:U54*($B$16:$U$16="")) -> 0
A55: =IF($A24="","",$A24) -> Conall Templeman | V55: =SUMPRODUCT(B55:U55*($B$16:$U$16="")) -> 0
A56: =IF($A25="","",$A25) -> Eddie Ringer | V56: =SUMPRODUCT(B56:U56*($B$16:$U$16="")) -> 0
A57: =IF($A26="","",$A26) -> Finn Cawley | E57: 1 | V57: =SUMPRODUCT(B57:U57*($B$16:$U$16="")) -> 1
A58: =IF($A27="","",$A27) -> George Barbantan | G58: 1 | V58: =SUMPRODUCT(B58:U58*($B$16:$U$16="")) -> 1
A59: =IF($A28="","",$A28) -> Henry Linklater | V59: =SUMPRODUCT(B59:U59*($B$16:$U$16="")) -> 0
A60: =IF($A29="","",$A29) -> Isaac Mond | V60: =SUMPRODUCT(B60:U60*($B$16:$U$16="")) -> 0
A61: =IF($A30="","",$A30) -> Jake Harrison | V61: =SUMPRODUCT(B61:U61*($B$16:$U$16="")) -> 0
A62: =IF($A31="","",$A31) -> Jake Ringer | V62: =SUMPRODUCT(B62:U62*($B$16:$U$16="")) -> 0
A63: =IF($A32="","",$A32) -> Keshav Singh | V63: =SUMPRODUCT(B63:U63*($B$16:$U$16="")) -> 0
A64: =IF($A33="","",$A33) -> Mark Pellowe | V64: =SUMPRODUCT(B64:U64*($B$16:$U$16="")) -> 0
A65: =IF($A34="","",$A34) -> Max Cobain | I65: 1 | V65: =SUMPRODUCT(B65:U65*($B$16:$U$16="")) -> 1
A66: =IF($A35="","",$A35) -> Neeraj Radia | V66: =SUMPRODUCT(B66:U66*($B$16:$U$16="")) -> 0
A67: =IF($A36="","",$A36) -> Phil Knott | B67: 1 | E67: 1 | V67: =SUMPRODUCT(B67:U67*($B$16:$U$16="")) -> 2
A68: =IF($A37="","",$A37) -> Robin | V68: =SUMPRODUCT(B68:U68*($B$16:$U$16="")) -> 0
A69: =IF($A38="","",$A38) -> Sam Holt | V69: =SUMPRODUCT(B69:U69*($B$16:$U$16="")) -> 0
A70: =IF($A39="","",$A39) -> Seb Burgess | C70: 2 | E70: 2 | F70: 1 | G70: 1 | H70: 2 | I70: 1 | L70: 5 | V70: =SUMPRODUCT(B70:U70*($B$16:$U$16="")) -> 14
A71: =IF($A40="","",$A40) | V71: =SUMPRODUCT(B71:U71*($B$16:$U$16="")) -> 0
A72: =IF($A41="","",$A41) | V72: =SUMPRODUCT(B72:U72*($B$16:$U$16="")) -> 0
A73: =IF($A42="","",$A42) | V73: =SUMPRODUCT(B73:U73*($B$16:$U$16="")) -> 0
A74: =IF($A43="","",$A43) | V74: =SUMPRODUCT(B74:U74*($B$16:$U$16="")) -> 0
A75: =IF($A44="","",$A44) | V75: =SUMPRODUCT(B75:U75*($B$16:$U$16="")) -> 0
A76: =IF($A45="","",$A45) | V76: =SUMPRODUCT(B76:U76*($B$16:$U$16="")) -> 0
A77: Total | V77: =SUM(V49:V76) -> 23
A79: ASSISTS — number made | B79: GW1 | C79: GW2 | D79: GW3 | E79: GW4 | F79: GW5 | G79: GW6 | H79: GW7 | I79: GW8 | J79: GW9 | K79: GW10 | L79: GW11 | M79: GW12 | N79: GW13 | O79: GW14 | P79: GW15 | Q79: GW16 | R79: GW17 | S79: GW18 | T79: GW19 | U79: GW20 | V79: Assists
A80: =IF($A18="","",$A18) -> Ahmed | V80: =SUMPRODUCT(B80:U80*($B$16:$U$16="")) -> 0
A81: =IF($A19="","",$A19) -> Alex Ruben | V81: =SUMPRODUCT(B81:U81*($B$16:$U$16="")) -> 0
A82: =IF($A20="","",$A20) -> Andy Cowan | V82: =SUMPRODUCT(B82:U82*($B$16:$U$16="")) -> 0
A83: =IF($A21="","",$A21) -> Ben Merrett | V83: =SUMPRODUCT(B83:U83*($B$16:$U$16="")) -> 0
A84: =IF($A22="","",$A22) -> Callum McCarthy | V84: =SUMPRODUCT(B84:U84*($B$16:$U$16="")) -> 0
A85: =IF($A23="","",$A23) -> Cecil Watson | V85: =SUMPRODUCT(B85:U85*($B$16:$U$16="")) -> 0
A86: =IF($A24="","",$A24) -> Conall Templeman | V86: =SUMPRODUCT(B86:U86*($B$16:$U$16="")) -> 0
A87: =IF($A25="","",$A25) -> Eddie Ringer | V87: =SUMPRODUCT(B87:U87*($B$16:$U$16="")) -> 0
A88: =IF($A26="","",$A26) -> Finn Cawley | V88: =SUMPRODUCT(B88:U88*($B$16:$U$16="")) -> 0
A89: =IF($A27="","",$A27) -> George Barbantan | V89: =SUMPRODUCT(B89:U89*($B$16:$U$16="")) -> 0
A90: =IF($A28="","",$A28) -> Henry Linklater | V90: =SUMPRODUCT(B90:U90*($B$16:$U$16="")) -> 0
A91: =IF($A29="","",$A29) -> Isaac Mond | V91: =SUMPRODUCT(B91:U91*($B$16:$U$16="")) -> 0
... A107: =IF($A45="","",$A45) | V107: =SUMPRODUCT(B107:U107*($B$16:$U$16="")) -> 0
A108: Total | V108: =SUM(V80:V107) -> 0

Sheet S5
A1: Season 5 · PlayFootball Old Street (5G, 6-a-side) · Oct 2025–Feb 2026
A2: Match | B2: GW1 | C2: GW2 | D2: GW3 | E2: GW4 | F2: GW5 | G2: GW6 | H2: GW7 | I2: GW8 | J2: GW9 | K2: GW10 | L2: GW11 | M2: GW12 | N2: GW13 | O2: GW14 | P2: GW15 | Q2: GW16 | R2: GW17 | S2: GW18 | T2: GW19 | U2: GW20 | X2: SEASON SUMMARY
A3: Date | B3: 45946 | C3: 45953 | D3: 45960 | E3: 45967 | F3: 45974 | G3: 45981 | H3: 45988 | I3: 45995 | J3: 46002 | K3: 46030 | L3: 46037 | M3: 46044 | N3: 46051 | O3: 46058 | X3: Played | Y3: =Y4+Y5+Y6 -> 13
A4: Kick-off | X4: Won | Y4: =SUMPRODUCT(($B$9:$U$9="W")*($B$16:$U$16="")) -> 2
A5: Opponent | B5: Dukes Select | C5: Green of the South | D5: Enjoy your mane Jane | E5: Old ivy | F5: Not Very often | G5: britannias | H5: DingCats | I5: Dukes | J5: Old ivy | K5: Enjoy | L5: Britannias | M5: Green of the South | N5: DingCats | O5: Not very often | X5: Drawn | Y5: =SUMPRODUCT(($B$9:$U$9="D")*($B$16:$U$16="")) -> 0
A6: Our goals | B6: 3 | C6: 0 | D6: 2 | E6: 1 | F6: 5 | G6: 1 | H6: 0 | I6: 8 | J6: 2 | K6: 1 | L6: 0 | M6: 2 | N6: 2 | O6: 10 | X6: Lost | Y6: =SUMPRODUCT(($B$9:$U$9="L")*($B$16:$U$16="")) -> 11
A7: Their goals | B7: 4 | C7: 2 | D7: 4 | E7: 6 | F7: 3 | G7: 4 | H7: 6 | I7: 0 | J7: 10 | K7: 6 | L7: 5 | M7: 10 | N7: 5 | O7: 5 | X7: Goals for | Y7: =SUMPRODUCT($B$6:$U$6*($B$16:$U$16="")) -> 29
A8: Score | B8: =IF(COUNT(B6:B7)<2,"",B6&"-"&B7) -> 3-4 | C8: =IF(COUNT(C6:C7)<2,"",C6&"-"&C7) -> 0-2 | D8: =IF(COUNT(D6:D7)<2,"",D6&"-"&D7) -> 2-4 | E8: =IF(COUNT(E6:E7)<2,"",E6&"-"&E7) -> 1-6 | F8: =IF(COUNT(F6:F7)<2,"",F6&"-"&F7) -> 5-3 | G8: =IF(COUNT(G6:G7)<2,"",G6&"-"&G7) -> 1-4 | H8: =IF(COUNT(H6:H7)<2,"",H6&"-"&H7) -> 0-6 | I8: =IF(COUNT(I6:I7)<2,"",I6&"-"&I7) -> 8-0 | ... U8: =IF(COUNT(U6:U7)<2,"",U6&"-"&U7) | X8: Goals against | Y8: =SUMPRODUCT($B$7:$U$7*($B$16:$U$16="")) -> 70
A9: Result | B9: =IF(COUNT(B6:B7)<2,"",IF(B6>B7,"W",IF(B6<B7,"L","D"))) -> L | C9: =IF(COUNT(C6:C7)<2,"",IF(C6>C7,"W",IF(C6<C7,"L","D"))) -> L | D9: =IF(COUNT(D6:D7)<2,"",IF(D6>D7,"W",IF(D6<D7,"L","D"))) -> L | E9: =IF(COUNT(E6:E7)<2,"",IF(E6>E7,"W",IF(E6<E7,"L","D"))) -> L | F9: =IF(COUNT(F6:F7)<2,"",IF(F6>F7,"W",IF(F6<F7,"L","D"))) -> W | G9: =IF(COUNT(G6:G7)<2,"",IF(G6>G7,"W",IF(G6<G7,"L","D"))) -> L | H9: =IF(COUNT(H6:H7)<2,"",IF(H6>H7,"W",IF(H6<H7,"L","D"))) -> L | I9: =IF(COUNT(I6:I7)<2,"",IF(I6>I7,"W",IF(I6<I7,"L","D"))) -> W | ... U9: =IF(COUNT(U6:U7)<2,"",IF(U6>U7,"W",IF(U6<U7,"L","D"))) | X9: Top scorer | Y9: {=IF(MAX($V$49:$V$76)=0,"—",INDEX($A$49:$A$76,MATCH(MAX($V$49:$V$76),$V$49:$V$76,0))&" ("&MAX($V$49:$V$76)&")")} -> Seb Burgess (10)
A10: MOTM | K10: Isaac Mond | L10: Phil Knott | M10: Seb Burgess | N10: Jake Ringer | O10: Eddie Ringer | X10: Most apps | Y10: {=IF(MAX($V$18:$V$45)=0,"—",INDEX($A$18:$A$45,MATCH(MAX($V$18:$V$45),$V$18:$V$45,0))&" ("&MAX($V$18:$V$45)&")")} -> Max Cobain (12)
A11: Champagne moment | X11: Season cost | Y11: =SUM($B$13:$U$13) -> 0
A12: Comments | I12: Forfeit | X12: Paid by
A13: Match cost (£)
A14: Players in game | B14: =COUNT(B$18:B$45) -> 8 | C14: =COUNT(C$18:C$45) -> 5 | D14: =COUNT(D$18:D$45) -> 6 | E14: =COUNT(E$18:E$45) -> 7 | F14: =COUNT(F$18:F$45) -> 6 | G14: =COUNT(G$18:G$45) -> 5 | H14: =COUNT(H$18:H$45) -> 7 | I14: =COUNT(I$18:I$45) -> 0 | ... U14: =COUNT(U$18:U$45) -> 0
A15: Cost per player (£) | B15: =IF(B$14=0,0,N(B$13)/B$14) -> 0 | C15: =IF(C$14=0,0,N(C$13)/C$14) -> 0 | D15: =IF(D$14=0,0,N(D$13)/D$14) -> 0 | E15: =IF(E$14=0,0,N(E$13)/E$14) -> 0 | F15: =IF(F$14=0,0,N(F$13)/F$14) -> 0 | G15: =IF(G$14=0,0,N(G$13)/G$14) -> 0 | H15: =IF(H$14=0,0,N(H$13)/H$14) -> 0 | I15: =IF(I$14=0,0,N(I$13)/I$14) -> 0 | ... U15: =IF(U$14=0,0,N(U$13)/U$14) -> 0
A16: Type (excl. from records) | I16: Forfeit
A17: APPEARANCES (1 = played) | B17: GW1 | C17: GW2 | D17: GW3 | E17: GW4 | F17: GW5 | G17: GW6 | H17: GW7 | I17: GW8 | J17: GW9 | K17: GW10 | L17: GW11 | M17: GW12 | N17: GW13 | O17: GW14 | P17: GW15 | Q17: GW16 | R17: GW17 | S17: GW18 | T17: GW19 | U17: GW20 | V17: Apps | W17: Cost (£)
A18: Ahmed | V18: =SUMPRODUCT(B18:U18*($B$16:$U$16="")) -> 0 | W18: =SUMPRODUCT($B18:$U18,$B$15:$U$15) -> 0
A19: Alex Ruben | E19: 1 | V19: =SUMPRODUCT(B19:U19*($B$16:$U$16="")) -> 1 | W19: =SUMPRODUCT($B19:$U19,$B$15:$U$15) -> 0
A20: Andy Cowan | B20: 1 | C20: 1 | D20: 1 | E20: 1 | F20: 1 | G20: 1 | H20: 1 | J20: 1 | V20: =SUMPRODUCT(B20:U20*($B$16:$U$16="")) -> 8 | W20: =SUMPRODUCT($B20:$U20,$B$15:$U$15) -> 0
A21: Ben Merrett | K21: 1 | V21: =SUMPRODUCT(B21:U21*($B$16:$U$16="")) -> 1 | W21: =SUMPRODUCT($B21:$U21,$B$15:$U$15) -> 0
A22: Callum McCarthy | V22: =SUMPRODUCT(B22:U22*($B$16:$U$16="")) -> 0 | W22: =SUMPRODUCT($B22:$U22,$B$15:$U$15) -> 0
A23: Cecil Watson | E23: 1 | V23: =SUMPRODUCT(B23:U23*($B$16:$U$16="")) -> 1 | W23: =SUMPRODUCT($B23:$U23,$B$15:$U$15) -> 0
A24: Conall Templeman | V24: =SUMPRODUCT(B24:U24*($B$16:$U$16="")) -> 0 | W24: =SUMPRODUCT($B24:$U24,$B$15:$U$15) -> 0
A25: Eddie Ringer | O25: 1 | V25: =SUMPRODUCT(B25:U25*($B$16:$U$16="")) -> 1 | W25: =SUMPRODUCT($B25:$U25,$B$15:$U$15) -> 0
A26: Finn Cawley | E26: 1 | V26: =SUMPRODUCT(B26:U26*($B$16:$U$16="")) -> 1 | W26: =SUMPRODUCT($B26:$U26,$B$15:$U$15) -> 0
A27: George Barbantan | B27: 1 | D27: 1 | E27: 1 | F27: 1 | G27: 1 | H27: 1 | J27: 1 | M27: 1 | N27: 1 | O27: 1 | V27: =SUMPRODUCT(B27:U27*($B$16:$U$16="")) -> 10 | W27: =SUMPRODUCT($B27:$U27,$B$15:$U$15) -> 0
A28: Henry Linklater | H28: 1 | V28: =SUMPRODUCT(B28:U28*($B$16:$U$16="")) -> 1 | W28: =SUMPRODUCT($B28:$U28,$B$15:$U$15) -> 0
A29: Isaac Mond | B29: 1 | C29: 1 | J29: 1 | K29: 1 | L29: 1 | M29: 1 | N29: 1 | O29: 1 | V29: =SUMPRODUCT(B29:U29*($B$16:$U$16="")) -> 8 | W29: =SUMPRODUCT($B29:$U29,$B$15:$U$15) -> 0
A30: Jake Harrison | V30: =SUMPRODUCT(B30:U30*($B$16:$U$16="")) -> 0 | W30: =SUMPRODUCT($B30:$U30,$B$15:$U$15) -> 0
A31: Jake Ringer | N31: 1 | V31: =SUMPRODUCT(B31:U31*($B$16:$U$16="")) -> 1 | W31: =SUMPRODUCT($B31:$U31,$B$15:$U$15) -> 0
A32: Keshav Singh | V32: =SUMPRODUCT(B32:U32*($B$16:$U$16="")) -> 0 | W32: =SUMPRODUCT($B32:$U32,$B$15:$U$15) -> 0
A33: Mark Pellowe | V33: =SUMPRODUCT(B33:U33*($B$16:$U$16="")) -> 0 | W33: =SUMPRODUCT($B33:$U33,$B$15:$U$15) -> 0
A34: Max Cobain | B34: 1 | C34: 1 | D34: 1 | E34: 1 | F34: 1 | G34: 1 | H34: 1 | J34: 1 | K34: 1 | L34: 1 | N34: 1 | O34: 1 | V34: =SUMPRODUCT(B34:U34*($B$16:$U$16="")) -> 12 | W34: =SUMPRODUCT($B34:$U34,$B$15:$U$15) -> 0
A35: Neeraj Radia | B35: 1 | D35: 1 | J35: 1 | K35: 1 | L35: 1 | M35: 1 | O35: 1 | V35: =SUMPRODUCT(B35:U35*($B$16:$U$16="")) -> 7 | W35: =SUMPRODUCT($B35:$U35,$B$15:$U$15) -> 0
A36: Phil Knott | B36: 1 | C36: 1 | D36: 1 | F36: 1 | H36: 1 | K36: 1 | L36: 1 | M36: 1 | N36: 1 | V36: =SUMPRODUCT(B36:U36*($B$16:$U$16="")) -> 9 | W36: =SUMPRODUCT($B36:$U36,$B$15:$U$15) -> 0
A37: Robin | V37: =SUMPRODUCT(B37:U37*($B$16:$U$16="")) -> 0 | W37: =SUMPRODUCT($B37:$U37,$B$15:$U$15) -> 0
A38: Sam Holt | B38: 1 | C38: 1 | D38: 1 | E38: 1 | F38: 1 | G38: 1 | H38: 1 | J38: 1 | K38: 1 | L38: 1 | O38: 1 | V38: =SUMPRODUCT(B38:U38*($B$16:$U$16="")) -> 11 | W38: =SUMPRODUCT($B38:$U38,$B$15:$U$15) -> 0
A39: Seb Burgess | B39: 1 | F39: 1 | G39: 1 | H39: 1 | J39: 1 | K39: 1 | M39: 1 | N39: 1 | O39: 1 | V39: =SUMPRODUCT(B39:U39*($B$16:$U$16="")) -> 9 | W39: =SUMPRODUCT($B39:$U39,$B$15:$U$15) -> 0
V40: =SUMPRODUCT(B40:U40*($B$16:$U$16="")) -> 0 | W40: =SUMPRODUCT($B40:$U40,$B$15:$U$15) -> 0
V41: =SUMPRODUCT(B41:U41*($B$16:$U$16="")) -> 0 | W41: =SUMPRODUCT($B41:$U41,$B$15:$U$15) -> 0
V42: =SUMPRODUCT(B42:U42*($B$16:$U$16="")) -> 0 | W42: =SUMPRODUCT($B42:$U42,$B$15:$U$15) -> 0
V43: =SUMPRODUCT(B43:U43*($B$16:$U$16="")) -> 0 | W43: =SUMPRODUCT($B43:$U43,$B$15:$U$15) -> 0
V44: =SUMPRODUCT(B44:U44*($B$16:$U$16="")) -> 0 | W44: =SUMPRODUCT($B44:$U44,$B$15:$U$15) -> 0
V45: =SUMPRODUCT(B45:U45*($B$16:$U$16="")) -> 0 | W45: =SUMPRODUCT($B45:$U45,$B$15:$U$15) -> 0
A46: Total | V46: =SUM(V18:V45) -> 81 | W46: =SUM(W18:W45) -> 0
A48: GOALS — number scored | B48: GW1 | C48: GW2 | D48: GW3 | E48: GW4 | F48: GW5 | G48: GW6 | H48: GW7 | I48: GW8 | J48: GW9 | K48: GW10 | L48: GW11 | M48: GW12 | N48: GW13 | O48: GW14 | P48: GW15 | Q48: GW16 | R48: GW17 | S48: GW18 | T48: GW19 | U48: GW20 | V48: Goals
A49: =IF($A18="","",$A18) -> Ahmed | V49: =SUMPRODUCT(B49:U49*($B$16:$U$16="")) -> 0
A50: =IF($A19="","",$A19) -> Alex Ruben | V50: =SUMPRODUCT(B50:U50*($B$16:$U$16="")) -> 0
A51: =IF($A20="","",$A20) -> Andy Cowan | B51: 1 | V51: =SUMPRODUCT(B51:U51*($B$16:$U$16="")) -> 1
A52: =IF($A21="","",$A21) -> Ben Merrett | V52: =SUMPRODUCT(B52:U52*($B$16:$U$16="")) -> 0
A53: =IF($A22="","",$A22) -> Callum McCarthy | V53: =SUMPRODUCT(B53:U53*($B$16:$U$16="")) -> 0
A54: =IF($A23="","",$A23) -> Cecil Watson | V54: =SUMPRODUCT(B54:U54*($B$16:$U$16="")) -> 0
A55: =IF($A24="","",$A24) -> Conall Templeman | V55: =SUMPRODUCT(B55:U55*($B$16:$U$16="")) -> 0
A56: =IF($A25="","",$A25) -> Eddie Ringer | O56: 4 | V56: =SUMPRODUCT(B56:U56*($B$16:$U$16="")) -> 4
A57: =IF($A26="","",$A26) -> Finn Cawley | E57: 1 | V57: =SUMPRODUCT(B57:U57*($B$16:$U$16="")) -> 1
A58: =IF($A27="","",$A27) -> George Barbantan | D58: 1 | J58: 1 | V58: =SUMPRODUCT(B58:U58*($B$16:$U$16="")) -> 2
A59: =IF($A28="","",$A28) -> Henry Linklater | V59: =SUMPRODUCT(B59:U59*($B$16:$U$16="")) -> 0
A60: =IF($A29="","",$A29) -> Isaac Mond | O60: 1 | V60: =SUMPRODUCT(B60:U60*($B$16:$U$16="")) -> 1
A61: =IF($A30="","",$A30) -> Jake Harrison | V61: =SUMPRODUCT(B61:U61*($B$16:$U$16="")) -> 0
A62: =IF($A31="","",$A31) -> Jake Ringer | V62: =SUMPRODUCT(B62:U62*($B$16:$U$16="")) -> 0
A63: =IF($A32="","",$A32) -> Keshav Singh | V63: =SUMPRODUCT(B63:U63*($B$16:$U$16="")) -> 0
A64: =IF($A33="","",$A33) -> Mark Pellowe | V64: =SUMPRODUCT(B64:U64*($B$16:$U$16="")) -> 0
A65: =IF($A34="","",$A34) -> Max Cobain | F65: 2 | G65: 1 | K65: 1 | O65: 1 | V65: =SUMPRODUCT(B65:U65*($B$16:$U$16="")) -> 5
A66: =IF($A35="","",$A35) -> Neeraj Radia | V66: =SUMPRODUCT(B66:U66*($B$16:$U$16="")) -> 0
A67: =IF($A36="","",$A36) -> Phil Knott | B67: 1 | F67: 1 | N67: 1 | V67: =SUMPRODUCT(B67:U67*($B$16:$U$16="")) -> 3
A68: =IF($A37="","",$A37) -> Robin | V68: =SUMPRODUCT(B68:U68*($B$16:$U$16="")) -> 0
A69: =IF($A38="","",$A38) -> Sam Holt | V69: =SUMPRODUCT(B69:U69*($B$16:$U$16="")) -> 0
A70: =IF($A39="","",$A39) -> Seb Burgess | B70: 1 | F70: 2 | J70: 1 | M70: 1 | N70: 1 | O70: 4 | V70: =SUMPRODUCT(B70:U70*($B$16:$U$16="")) -> 10
A71: =IF($A40="","",$A40) | V71: =SUMPRODUCT(B71:U71*($B$16:$U$16="")) -> 0
A72: =IF($A41="","",$A41) | V72: =SUMPRODUCT(B72:U72*($B$16:$U$16="")) -> 0
A73: =IF($A42="","",$A42) | V73: =SUMPRODUCT(B73:U73*($B$16:$U$16="")) -> 0
A74: =IF($A43="","",$A43) | V74: =SUMPRODUCT(B74:U74*($B$16:$U$16="")) -> 0
A75: =IF($A44="","",$A44) | V75: =SUMPRODUCT(B75:U75*($B$16:$U$16="")) -> 0
A76: =IF($A45="","",$A45) | V76: =SUMPRODUCT(B76:U76*($B$16:$U$16="")) -> 0
A77: Total | V77: =SUM(V49:V76) -> 27
A79: ASSISTS — number made | B79: GW1 | C79: GW2 | D79: GW3 | E79: GW4 | F79: GW5 | G79: GW6 | H79: GW7 | I79: GW8 | J79: GW9 | K79: GW10 | L79: GW11 | M79: GW12 | N79: GW13 | O79: GW14 | P79: GW15 | Q79: GW16 | R79: GW17 | S79: GW18 | T79: GW19 | U79: GW20 | V79: Assists
A80: =IF($A18="","",$A18) -> Ahmed | V80: =SUMPRODUCT(B80:U80*($B$16:$U$16="")) -> 0
A81: =IF($A19="","",$A19) -> Alex Ruben | V81: =SUMPRODUCT(B81:U81*($B$16:$U$16="")) -> 0
A82: =IF($A20="","",$A20) -> Andy Cowan | V82: =SUMPRODUCT(B82:U82*($B$16:$U$16="")) -> 0
A83: =IF($A21="","",$A21) -> Ben Merrett | V83: =SUMPRODUCT(B83:U83*($B$16:$U$16="")) -> 0
A84: =IF($A22="","",$A22) -> Callum McCarthy | V84: =SUMPRODUCT(B84:U84*($B$16:$U$16="")) -> 0
A85: =IF($A23="","",$A23) -> Cecil Watson | V85: =SUMPRODUCT(B85:U85*($B$16:$U$16="")) -> 0
A86: =IF($A24="","",$A24) -> Conall Templeman | V86: =SUMPRODUCT(B86:U86*($B$16:$U$16="")) -> 0
A87: =IF($A25="","",$A25) -> Eddie Ringer | V87: =SUMPRODUCT(B87:U87*($B$16:$U$16="")) -> 0
A88: =IF($A26="","",$A26) -> Finn Cawley | V88: =SUMPRODUCT(B88:U88*($B$16:$U$16="")) -> 0
A89: =IF($A27="","",$A27) -> George Barbantan | M89: 1 | V89: =SUMPRODUCT(B89:U89*($B$16:$U$16="")) -> 1
A90: =IF($A28="","",$A28) -> Henry Linklater | V90: =SUMPRODUCT(B90:U90*($B$16:$U$16="")) -> 0
A91: =IF($A29="","",$A29) -> Isaac Mond | O91: 2 | V91: =SUMPRODUCT(B91:U91*($B$16:$U$16="")) -> 2
A92: =IF($A30="","",$A30) -> Jake Harrison | V92: =SUMPRODUCT(B92:U92*($B$16:$U$16="")) -> 0
A93: =IF($A31="","",$A31) -> Jake Ringer | N93: 1 | V93: =SUMPRODUCT(B93:U93*($B$16:$U$16="")) -> 1
A94: =IF($A32="","",$A32) -> Keshav Singh | V94: =SUMPRODUCT(B94:U94*($B$16:$U$16="")) -> 0
A95: =IF($A33="","",$A33) -> Mark Pellowe | V95: =SUMPRODUCT(B95:U95*($B$16:$U$16="")) -> 0
A96: =IF($A34="","",$A34) -> Max Cobain | O96: 4 | V96: =SUMPRODUCT(B96:U96*($B$16:$U$16="")) -> 4
A97: =IF($A35="","",$A35) -> Neeraj Radia | O97: 1 | V97: =SUMPRODUCT(B97:U97*($B$16:$U$16="")) -> 1
A98: =IF($A36="","",$A36) -> Phil Knott | K98: 1 | V98: =SUMPRODUCT(B98:U98*($B$16:$U$16="")) -> 1
A99: =IF($A37="","",$A37) -> Robin | V99: =SUMPRODUCT(B99:U99*($B$16:$U$16="")) -> 0
A100: =IF($A38="","",$A38) -> Sam Holt | O100: 1 | V100: =SUMPRODUCT(B100:U100*($B$16:$U$16="")) -> 1
A101: =IF($A39="","",$A39) -> Seb Burgess | N101: 1 | V101: =SUMPRODUCT(B101:U101*($B$16:$U$16="")) -> 1
A102: =IF($A40="","",$A40) | V102: =SUMPRODUCT(B102:U102*($B$16:$U$16="")) -> 0
...

Sheet S6
A1: Season 6 · PlayFootball Old Street (5G, 6-a-side) · Feb–May 2026
A2: Match | B2: GW1 | C2: GW2 | D2: GW3 | E2: GW4 | F2: GW5 | G2: GW6 | H2: GW7 | I2: GW8 | J2: GW9 | K2: GW10 | L2: GW11 | M2: GW12 | N2: GW13 | O2: GW14 | P2: GW15 | Q2: GW16 | R2: GW17 | S2: GW18 | T2: GW19 | U2: GW20 | X2: SEASON SUMMARY
A3: Date | B3: 46065 | C3: 46072 | D3: 46079 | E3: 46086 | F3: 46093 | G3: 46100 | H3: 46107 | I3: 46114 | J3: 46121 | K3: 46128 | L3: 46135 | M3: 46142 | N3: 46149 | O3: 46156 | X3: Played | Y3: =Y4+Y5+Y6 -> 14
A4: Kick-off | X4: Won | Y4: =SUMPRODUCT(($B$9:$U$9="W")*($B$16:$U$16="")) -> 2
A5: Opponent | B5: Mane Jane | C5: MOB FC | D5: Cottesmore FC | E5: Green of the South | F5: Vauban FC | G5: The Britannias | H5: Old Ivy FC | I5: MOB FC | J5: enjoy your mane | K5: Vauban FC | L5: The Britannias | M5: Green of the South | N5: Old Ivy | O5: Cottesmore | X5: Drawn | Y5: =SUMPRODUCT(($B$9:$U$9="D")*($B$16:$U$16="")) -> 2
A6: Our goals | B6: 3 | C6: 8 | D6: 4 | E6: 3 | F6: 2 | G6: 0 | H6: 2 | I6: 4 | J6: 2 | K6: 6 | L6: 1 | M6: 3 | N6: 7 | O6: 2 | X6: Lost | Y6: =SUMPRODUCT(($B$9:$U$9="L")*($B$16:$U$16="")) -> 10
A7: Their goals | B7: 11 | C7: 2 | D7: 7 | E7: 3 | F7: 8 | G7: 6 | H7: 11 | I7: 6 | J7: 2 | K7: 4 | L7: 11 | M7: 7 | N7: 16 | O7: 7 | X7: Goals for | Y7: =SUMPRODUCT($B$6:$U$6*($B$16:$U$16="")) -> 47
A8: Score | B8: =IF(COUNT(B6:B7)<2,"",B6&"-"&B7) -> 3-11 | C8: =IF(COUNT(C6:C7)<2,"",C6&"-"&C7) -> 8-2 | D8: =IF(COUNT(D6:D7)<2,"",D6&"-"&D7) -> 4-7 | E8: =IF(COUNT(E6:E7)<2,"",E6&"-"&E7) -> 3-3 | F8: =IF(COUNT(F6:F7)<2,"",F6&"-"&F7) -> 2-8 | G8: =IF(COUNT(G6:G7)<2,"",G6&"-"&G7) -> 0-6 | H8: =IF(COUNT(H6:H7)<2,"",H6&"-"&H7) -> 2-11 | I8: =IF(COUNT(I6:I7)<2,"",I6&"-"&I7) -> 4-6 | ... U8: =IF(COUNT(U6:U7)<2,"",U6&"-"&U7) | X8: Goals against | Y8: =SUMPRODUCT($B$7:$U$7*($B$16:$U$16="")) -> 101
A9: Result | B9: =IF(COUNT(B6:B7)<2,"",IF(B6>B7,"W",IF(B6<B7,"L","D"))) -> L | C9: =IF(COUNT(C6:C7)<2,"",IF(C6>C7,"W",IF(C6<C7,"L","D"))) -> W | D9: =IF(COUNT(D6:D7)<2,"",IF(D6>D7,"W",IF(D6<D7,"L","D"))) -> L | E9: =IF(COUNT(E6:E7)<2,"",IF(E6>E7,"W",IF(E6<E7,"L","D"))) -> D | F9: =IF(COUNT(F6:F7)<2,"",IF(F6>F7,"W",IF(F6<F7,"L","D"))) -> L | G9: =IF(COUNT(G6:G7)<2,"",IF(G6>G7,"W",IF(G6<G7,"L","D"))) -> L | H9: =IF(COUNT(H6:H7)<2,"",IF(H6>H7,"W",IF(H6<H7,"L","D"))) -> L | I9: =IF(COUNT(I6:I7)<2,"",IF(I6>I7,"W",IF(I6<I7,"L","D"))) -> L | ... U9: =IF(COUNT(U6:U7)<2,"",IF(U6>U7,"W",IF(U6<U7,"L","D"))) | X9: Top scorer | Y9: {=IF(MAX($V$49:$V$76)=0,"—",INDEX($A$49:$A$76,MATCH(MAX($V$49:$V$76),$V$49:$V$76,0))&" ("&MAX($V$49:$V$76)&")")} -> Seb Burgess (15)
A10: MOTM | C10: Phil Knott | X10: Most apps | Y10: {=IF(MAX($V$18:$V$45)=0,"—",INDEX($A$18:$A$45,MATCH(MAX($V$18:$V$45),$V$18:$V$45,0))&" ("&MAX($V$18:$V$45)&")")} -> Seb Burgess (13)
A11: Champagne moment | X11: Season cost | Y11: =SUM($B$13:$U$13) -> 0
A12: Comments | X12: Paid by
A13: Match cost (£)
A14: Players in game | B14: =COUNT(B$18:B$45) -> 3 | C14: =COUNT(C$18:C$45) -> 5 | D14: =COUNT(D$18:D$45) -> 4 | E14: =COUNT(E$18:E$45) -> 7 | F14: =COUNT(F$18:F$45) -> 7 | G14: =COUNT(G$18:G$45) -> 6 | H14: =COUNT(H$18:H$45) -> 7 | I14: =COUNT(I$18:I$45) -> 7 | ... U14: =COUNT(U$18:U$45) -> 0
A15: Cost per player (£) | B15: =IF(B$14=0,0,N(B$13)/B$14) -> 0 | C15: =IF(C$14=0,0,N(C$13)/C$14) -> 0 | D15: =IF(D$14=0,0,N(D$13)/D$14) -> 0 | E15: =IF(E$14=0,0,N(E$13)/E$14) -> 0 | F15: =IF(F$14=0,0,N(F$13)/F$14) -> 0 | G15: =IF(G$14=0,0,N(G$13)/G$14) -> 0 | H15: =IF(H$14=0,0,N(H$13)/H$14) -> 0 | I15: =IF(I$14=0,0,N(I$13)/I$14) -> 0 | ... U15: =IF(U$14=0,0,N(U$13)/U$14) -> 0
A16: Type (excl. from records)
A17: APPEARANCES (1 = played) | B17: GW1 | C17: GW2 | D17: GW3 | E17: GW4 | F17: GW5 | G17: GW6 | H17: GW7 | I17: GW8 | J17: GW9 | K17: GW10 | L17: GW11 | M17: GW12 | N17: GW13 | O17: GW14 | P17: GW15 | Q17: GW16 | R17: GW17 | S17: GW18 | T17: GW19 | U17: GW20 | V17: Apps | W17: Cost (£)
A18: Ahmed | V18: =SUMPRODUCT(B18:U18*($B$16:$U$16="")) -> 0 | W18: =SUMPRODUCT($B18:$U18,$B$15:$U$15) -> 0
A19: Alex Ruben | V19: =SUMPRODUCT(B19:U19*($B$16:$U$16="")) -> 0 | W19: =SUMPRODUCT($B19:$U19,$B$15:$U$15) -> 0
A20: Andy Cowan | V20: =SUMPRODUCT(B20:U20*($B$16:$U$16="")) -> 0 | W20: =SUMPRODUCT($B20:$U20,$B$15:$U$15) -> 0
A21: Ben Merrett | F21: 1 | H21: 1 | I21: 1 | K21: 1 | M21: 1 | N21: 1 | V21: =SUMPRODUCT(B21:U21*($B$16:$U$16="")) -> 6 | W21: =SUMPRODUCT($B21:$U21,$B$15:$U$15) -> 0
A22: Callum McCarthy | V22: =SUMPRODUCT(B22:U22*($B$16:$U$16="")) -> 0 | W22: =SUMPRODUCT($B22:$U22,$B$15:$U$15) -> 0
A23: Cecil Watson | V23: =SUMPRODUCT(B23:U23*($B$16:$U$16="")) -> 0 | W23: =SUMPRODUCT($B23:$U23,$B$15:$U$15) -> 0
A24: Conall Templeman | L24: 1 | M24: 1 | N24: 1 | V24: =SUMPRODUCT(B24:U24*($B$16:$U$16="")) -> 3 | W24: =SUMPRODUCT($B24:$U24,$B$15:$U$15) -> 0
A25: Eddie Ringer | C25: 1 | V25: =SUMPRODUCT(B25:U25*($B$16:$U$16="")) -> 1 | W25: =SUMPRODUCT($B25:$U25,$B$15:$U$15) -> 0
A26: Finn Cawley | B26: 1 | H26: 1 | M26: 1 | V26: =SUMPRODUCT(B26:U26*($B$16:$U$16="")) -> 3 | W26: =SUMPRODUCT($B26:$U26,$B$15:$U$15) -> 0
A27: George Barbantan | V27: =SUMPRODUCT(B27:U27*($B$16:$U$16="")) -> 0 | W27: =SUMPRODUCT($B27:$U27,$B$15:$U$15) -> 0
A28: Henry Linklater | V28: =SUMPRODUCT(B28:U28*($B$16:$U$16="")) -> 0 | W28: =SUMPRODUCT($B28:$U28,$B$15:$U$15) -> 0
A29: Isaac Mond | E29: 1 | F29: 1 | G29: 1 | L29: 1 | N29: 1 | O29: 1 | V29: =SUMPRODUCT(B29:U29*($B$16:$U$16="")) -> 6 | W29: =SUMPRODUCT($B29:$U29,$B$15:$U$15) -> 0
A30: Jake Harrison | V30: =SUMPRODUCT(B30:U30*($B$16:$U$16="")) -> 0 | W30: =SUMPRODUCT($B30:$U30,$B$15:$U$15) -> 0
A31: Jake Ringer | C31: 1 | G31: 1 | V31: =SUMPRODUCT(B31:U31*($B$16:$U$16="")) -> 2 | W31: =SUMPRODUCT($B31:$U31,$B$15:$U$15) -> 0
A32: Keshav Singh | D32: 1 | E32: 1 | F32: 1 | G32: 1 | I32: 1 | J32: 1 | K32: 1 | L32: 1 | O32: 1 | V32: =SUMPRODUCT(B32:U32*($B$16:$U$16="")) -> 9 | W32: =SUMPRODUCT($B32:$U32,$B$15:$U$15) -> 0
A33: Mark Pellowe | D33: 1 | E33: 1 | F33: 1 | G33: 1 | H33: 1 | I33: 1 | J33: 1 | K33: 1 | L33: 1 | M33: 1 | N33: 1 | O33: 1 | V33: =SUMPRODUCT(B33:U33*($B$16:$U$16="")) -> 12 | W33: =SUMPRODUCT($B33:$U33,$B$15:$U$15) -> 0
A34: Max Cobain | C34: 1 | E34: 1 | G34: 1 | H34: 1 | I34: 1 | J34: 1 | K34: 1 | M34: 1 | N34: 1 | O34: 1 | V34: =SUMPRODUCT(B34:U34*($B$16:$U$16="")) -> 10 | W34: =SUMPRODUCT($B34:$U34,$B$15:$U$15) -> 0
A35: Neeraj Radia | H35: 1 | J35: 1 | N35: 1 | O35: 1 | V35: =SUMPRODUCT(B35:U35*($B$16:$U$16="")) -> 4 | W35: =SUMPRODUCT($B35:$U35,$B$15:$U$15) -> 0
A36: Phil Knott | B36: 1 | C36: 1 | E36: 1 | F36: 1 | H36: 1 | I36: 1 | J36: 1 | K36: 1 | M36: 1 | O36: 1 | V36: =SUMPRODUCT(B36:U36*($B$16:$U$16="")) -> 10 | W36: =SUMPRODUCT($B36:$U36,$B$15:$U$15) -> 0
A37: Robin | V37: =SUMPRODUCT(B37:U37*($B$16:$U$16="")) -> 0 | W37: =SUMPRODUCT($B37:$U37,$B$15:$U$15) -> 0
A38: Sam Holt | D38: 1 | E38: 1 | F38: 1 | H38: 1 | I38: 1 | J38: 1 | K38: 1 | V38: =SUMPRODUCT(B38:U38*($B$16:$U$16="")) -> 7 | W38: =SUMPRODUCT($B38:$U38,$B$15:$U$15) -> 0
A39: Seb Burgess | B39: 1 | C39: 1 | D39: 1 | E39: 1 | F39: 1 | G39: 1 | I39: 1 | J39: 1 | K39: 1 | L39: 1 | M39: 1 | N39: 1 | O39: 1 | V39: =SUMPRODUCT(B39:U39*($B$16:$U$16="")) -> 13 | W39: =SUMPRODUCT($B39:$U39,$B$15:$U$15) -> 0
V40: =SUMPRODUCT(B40:U40*($B$16:$U$16="")) -> 0 | W40: =SUMPRODUCT($B40:$U40,$B$15:$U$15) -> 0
V41: =SUMPRODUCT(B41:U41*($B$16:$U$16="")) -> 0 | W41: =SUMPRODUCT($B41:$U41,$B$15:$U$15) -> 0
V42: =SUMPRODUCT(B42:U42*($B$16:$U$16="")) -> 0 | W42: =SUMPRODUCT($B42:$U42,$B$15:$U$15) -> 0
V43: =SUMPRODUCT(B43:U43*($B$16:$U$16="")) -> 0 | W43: =SUMPRODUCT($B43:$U43,$B$15:$U$15) -> 0
V44: =SUMPRODUCT(B44:U44*($B$16:$U$16="")) -> 0 | W44: =SUMPRODUCT($B44:$U44,$B$15:$U$15) -> 0
V45: =SUMPRODUCT(B45:U45*($B$16:$U$16="")) -> 0 | W45: =SUMPRODUCT($B45:$U45,$B$15:$U$15) -> 0
A46: Total | V46: =SUM(V18:V45) -> 86 | W46: =SUM(W18:W45) -> 0
A48: GOALS — number scored | B48: GW1 | C48: GW2 | D48: GW3 | E48: GW4 | F48: GW5 | G48: GW6 | H48: GW7 | I48: GW8 | J48: GW9 | K48: GW10 | L48: GW11 | M48: GW12 | N48: GW13 | O48: GW14 | P48: GW15 | Q48: GW16 | R48: GW17 | S48: GW18 | T48: GW19 | U48: GW20 | V48: Goals
A49: =IF($A18="","",$A18) -> Ahmed | V49: =SUMPRODUCT(B49:U49*($B$16:$U$16="")) -> 0
A50: =IF($A19="","",$A19) -> Alex Ruben | V50: =SUMPRODUCT(B50:U50*($B$16:$U$16="")) -> 0
A51: =IF($A20="","",$A20) -> Andy Cowan | V51: =SUMPRODUCT(B51:U51*($B$16:$U$16="")) -> 0
A52: =IF($A21="","",$A21) -> Ben Merrett | K52: 1 | V52: =SUMPRODUCT(B52:U52*($B$16:$U$16="")) -> 1
A53: =IF($A22="","",$A22) -> Callum McCarthy | V53: =SUMPRODUCT(B53:U53*($B$16:$U$16="")) -> 0
A54: =IF($A23="","",$A23) -> Cecil Watson | V54: =SUMPRODUCT(B54:U54*($B$16:$U$16="")) -> 0
A55: =IF($A24="","",$A24) -> Conall Templeman | V55: =SUMPRODUCT(B55:U55*($B$16:$U$16="")) -> 0
A56: =IF($A25="","",$A25) -> Eddie Ringer | C56: 2 | V56: =SUMPRODUCT(B56:U56*($B$16:$U$16="")) -> 2
A57: =IF($A26="","",$A26) -> Finn Cawley | H57: 2 | V57: =SUMPRODUCT(B57:U57*($B$16:$U$16="")) -> 2
A58: =IF($A27="","",$A27) -> George Barbantan | V58: =SUMPRODUCT(B58:U58*($B$16:$U$16="")) -> 0
A59: =IF($A28="","",$A28) -> Henry Linklater | V59: =SUMPRODUCT(B59:U59*($B$16:$U$16="")) -> 0
A60: =IF($A29="","",$A29) -> Isaac Mond | V60: =SUMPRODUCT(B60:U60*($B$16:$U$16="")) -> 0
A61: =IF($A30="","",$A30) -> Jake Harrison | V61: =SUMPRODUCT(B61:U61*($B$16:$U$16="")) -> 0
A62: =IF($A31="","",$A31) -> Jake Ringer | V62: =SUMPRODUCT(B62:U62*($B$16:$U$16="")) -> 0
A63: =IF($A32="","",$A32) -> Keshav Singh | E63: 1 | I63: 2 | V63: =SUMPRODUCT(B63:U63*($B$16:$U$16="")) -> 3
A64: =IF($A33="","",$A33) -> Mark Pellowe | D64: 2 | E64: 1 | I64: 1 | M64: 1 | N64: 1 | V64: =SUMPRODUCT(B64:U64*($B$16:$U$16="")) -> 6
A65: =IF($A34="","",$A34) -> Max Cobain | C65: 1 | E65: 1 | K65: 1 | V65: =SUMPRODUCT(B65:U65*($B$16:$U$16="")) -> 3
A66: =IF($A35="","",$A35) -> Neeraj Radia | N66: 1 | V66: =SUMPRODUCT(B66:U66*($B$16:$U$16="")) -> 1
A67: =IF($A36="","",$A36) -> Phil Knott | C67: 2 | F67: 1 | I67: 1 | V67: =SUMPRODUCT(B67:U67*($B$16:$U$16="")) -> 4
A68: =IF($A37="","",$A37) -> Robin | V68: =SUMPRODUCT(B68:U68*($B$16:$U$16="")) -> 0
A69: =IF($A38="","",$A38) -> Sam Holt | J69: 1 | V69: =SUMPRODUCT(B69:U69*($B$16:$U$16="")) -> 1
A70: =IF($A39="","",$A39) -> Seb Burgess | B70: 1 | D70: 1 | F70: 1 | J70: 1 | K70: 1 | L70: 1 | M70: 2 | N70: 5 | O70: 2 | V70: =SUMPRODUCT(B70:U70*($B$16:$U$16="")) -> 15
A71: =IF($A40="","",$A40) | V71: =SUMPRODUCT(B71:U71*($B$16:$U$16="")) -> 0
A72: =IF($A41="","",$A41) | V72: =SUMPRODUCT(B72:U72*($B$16:$U$16="")) -> 0
A73: =IF($A42="","",$A42) | V73: =SUMPRODUCT(B73:U73*($B$16:$U$16="")) -> 0
A74: =IF($A43="","",$A43) | V74: =SUMPRODUCT(B74:U74*($B$16:$U$16="")) -> 0
A75: =IF($A44="","",$A44) | V75: =SUMPRODUCT(B75:U75*($B$16:$U$16="")) -> 0
A76: =IF($A45="","",$A45) | V76: =SUMPRODUCT(B76:U76*($B$16:$U$16="")) -> 0
A77: Total | V77: =SUM(V49:V76) -> 38
A79: ASSISTS — number made | B79: GW1 | C79: GW2 | D79: GW3 | E79: GW4 | F79: GW5 | G79: GW6 | H79: GW7 | I79: GW8 | J79: GW9 | K79: GW10 | L79: GW11 | M79: GW12 | N79: GW13 | O79: GW14 | P79: GW15 | Q79: GW16 | R79: GW17 | S79: GW18 | T79: GW19 | U79: GW20 | V79: Assists
A80: =IF($A18="","",$A18) -> Ahmed | V80: =SUMPRODUCT(B80:U80*($B$16:$U$16="")) -> 0
A81: =IF($A19="","",$A19) -> Alex Ruben | V81: =SUMPRODUCT(B81:U81*($B$16:$U$16="")) -> 0
A82: =IF($A20="","",$A20) -> Andy Cowan | V82: =SUMPRODUCT(B82:U82*($B$16:$U$16="")) -> 0
A83: =IF($A21="","",$A21) -> Ben Merrett | V83: =SUMPRODUCT(B83:U83*($B$16:$U$16="")) -> 0
A84: =IF($A22="","",$A22) -> Callum McCarthy | V84: =SUMPRODUCT(B84:U84*($B$16:$U$16="")) -> 0
A85: =IF($A23="","",$A23) -> Cecil Watson | V85: =SUMPRODUCT(B85:U85*($B$16:$U$16="")) -> 0
A86: =IF($A24="","",$A24) -> Conall Templeman | V86: =SUMPRODUCT(B86:U86*($B$16:$U$16="")) -> 0
A87: =IF($A25="","",$A25) -> Eddie Ringer | V87: =SUMPRODUCT(B87:U87*($B$16:$U$16="")) -> 0
A88: =IF($A26="","",$A26) -> Finn Cawley | V88: =SUMPRODUCT(B88:U88*($B$16:$U$16="")) -> 0
A89: =IF($A27="","",$A27) -> George Barbantan | V89: =SUMPRODUCT(B89:U89*($B$16:$U$16="")) -> 0
A90: =IF($A28="","",$A28) -> Henry Linklater | V90: =SUMPRODUCT(B90:U90*($B$16:$U$16="")) -> 0
A91: =IF($A29="","",$A29) -> Isaac Mond | V91: =SUMPRODUCT(B91:U91*($B$16:$U$16="")) -> 0
... A97: =IF($A35="","",$A35) -> Neeraj Radia | V97: =SUMPRODUCT(B97:U97*($B$16:$U$16="")) -> 0
A98: =IF($A36="","",$A36) -> Phil Knott | C98: 2 | V98: =SUMPRODUCT(B98:U98*($B$16:$U$16="")) -> 2
A99: =IF($A37="","",$A37) -> Robin | V99: =SUMPRODUCT(B99:U99*($B$16:$U$16="")) -> 0
A100: =IF($A38="","",$A38) -> Sam Holt | V100: =SUMPRODUCT(B100:U100*($B$16:$U$16="")) -> 0
A101: =IF($A39="","",$A39) -> Seb Burgess | V101: =SUMPRODUCT(B101:U101*($B$16:$U$16="")) -> 0
A102: =IF($A40="","",$A40) | V102: =SUMPRODUCT(B102:U102*($B$16:$U$16="")) -> 0
A103: =IF($A41="","",$A41) | V103: =SUMPRODUCT(B103:U103*($B$16:$U$16="")) -> 0
A104: =IF($A42="","",$A42) | V104: =SUMPRODUCT(B104:U104*($B$16:$U$16="")) -> 0
A105: =IF($A43="","",$A43) | V105: =SUMPRODUCT(B105:U105*($B$16:$U$16="")) -> 0
A106: =IF($A44="","",$A44) | V106: =SUMPRODUCT(B106:U106*($B$16:$U$16="")) -> 0
A107: =IF($A45="","",$A45) | V107: =SUMPRODUCT(B107:U107*($B$16:$U$16="")) -> 0
...

Sheet S7
A1: Season 7 · PlayFootball Old Street (5G, 6-a-side) · May–Aug 2026 · imported from the team app
A2: Match | B2: GW1 | C2: GW2 | D2: GW3 | E2: GW4 | F2: GW5 | G2: GW6 | H2: GW7 | I2: GW8 | J2: GW9 | K2: GW10 | L2: GW11 | M2: GW12 | N2: GW13 | O2: GW14 | P2: GW15 | Q2: GW16 | R2: GW17 | S2: GW18 | T2: GW19 | U2: GW20 | X2: SEASON SUMMARY
A3: Date | B3: 46163 | C3: 46170 | D3: 46170 | E3: 46177 | F3: 46184 | G3: 46191 | H3: 46200 | I3: 46205 | J3: 46219 | K3: 46227 | L3: 46227 | M3: 46233 | N3: 46240 | O3: 46247 | P3: 46255 | X3: Played | Y3: =Y4+Y5+Y6 -> 11
A4: Kick-off | X4: Won | Y4: =SUMPRODUCT(($B$9:$U$9="W")*($B$16:$U$16="")) -> 3
A5: Opponent | B5: Enjoy your Mane Jane | C5: Recessionary FC | D5: Ref's Mates | E5: XZR FC | F5: Green of the South | G5: Vauban FC | H5: The Britannias | I5: Oly Ivy | J5: Enjoy your mane Jane | K5: Forfeit | L5: Vauban FC | M5: The Britannias | N5: Green of the South | O5: Old Ivy | P5: Xzr Fc | X5: Drawn | Y5: =SUMPRODUCT(($B$9:$U$9="D")*($B$16:$U$16="")) -> 0
A6: Our goals | B6: 3 | C6: 8 | D6: 7 | E6: 4 | F6: 2 | G6: 5 | H6: 1 | I6: 2 | J6: 0 | K6: 8 | L6: 6 | M6: 4 | N6: 3 | O6: 4 | P6: 6 | X6: Lost | Y6: =SUMPRODUCT(($B$9:$U$9="L")*($B$16:$U$16="")) -> 8
A7: Their goals | B7: 6 | C7: 0 | D7: 5 | E7: 2 | F7: 11 | G7: 4 | H7: 11 | I7: 6 | J7: 8 | K7: 0 | L7: 10 | M7: 6 | N7: 9 | O7: 8 | P7: 1 | X7: Goals for | Y7: =SUMPRODUCT($B$6:$U$6*($B$16:$U$16="")) -> 40
A8: Score | B8: =IF(COUNT(B6:B7)<2,"",B6&"-"&B7) -> 3-6 | C8: =IF(COUNT(C6:C7)<2,"",C6&"-"&C7) -> 8-0 | D8: =IF(COUNT(D6:D7)<2,"",D6&"-"&D7) -> 7-5 | E8: =IF(COUNT(E6:E7)<2,"",E6&"-"&E7) -> 4-2 | F8: =IF(COUNT(F6:F7)<2,"",F6&"-"&F7) -> 2-11 | G8: =IF(COUNT(G6:G7)<2,"",G6&"-"&G7) -> 5-4 | H8: =IF(COUNT(H6:H7)<2,"",H6&"-"&H7) -> 1-11 | I8: =IF(COUNT(I6:I7)<2,"",I6&"-"&I7) -> 2-6 | ... U8: =IF(COUNT(U6:U7)<2,"",U6&"-"&U7) | X8: Goals against | Y8: =SUMPRODUCT($B$7:$U$7*($B$16:$U$16="")) -> 74
A9: Result | B9: =IF(COUNT(B6:B7)<2,"",IF(B6>B7,"W",IF(B6<B7,"L","D"))) -> L | C9: =IF(COUNT(C6:C7)<2,"",IF(C6>C7,"W",IF(C6<C7,"L","D"))) -> W | D9: =IF(COUNT(D6:D7)<2,"",IF(D6>D7,"W",IF(D6<D7,"L","D"))) -> W | E9: =IF(COUNT(E6:E7)<2,"",IF(E6>E7,"W",IF(E6<E7,"L","D"))) -> W | F9: =IF(COUNT(F6:F7)<2,"",IF(F6>F7,"W",IF(F6<F7,"L","D"))) -> L | G9: =IF(COUNT(G6:G7)<2,"",IF(G6>G7,"W",IF(G6<G7,"L","D"))) -> W | H9: =IF(COUNT(H6:H7)<2,"",IF(H6>H7,"W",IF(H6<H7,"L","D"))) -> L | I9: =IF(COUNT(I6:I7)<2,"",IF(I6>I7,"W",IF(I6<I7,"L","D"))) -> L | ... U9: =IF(COUNT(U6:U7)<2,"",IF(U6>U7,"W",IF(U6<U7,"L","D"))) | X9: Top scorer | Y9: {=IF(MAX($V$49:$V$76)=0,"—",INDEX($A$49:$A$76,MATCH(MAX($V$49:$V$76),$V$49:$V$76,0))&" ("&MAX($V$49:$V$76)&")")} -> Ahmed (5)
A10: MOTM | X10: Most apps | Y10: {=IF(MAX($V$18:$V$45)=0,"—",INDEX($A$18:$A$45,MATCH(MAX($V$18:$V$45),$V$18:$V$45,0))&" ("&MAX($V$18:$V$45)&")")} -> Mark Pellowe (11)
A11: Champagne moment | X11: Season cost | Y11: =SUM($B$13:$U$13) -> 0
A12: Comments | C12: Forfeit | D12: Friendly | J12: Forfeit | K12: Forfeit | X12: Paid by
A13: Match cost (£)
A14: Players in game | B14: =COUNT(B$18:B$45) -> 7 | C14: =COUNT(C$18:C$45) -> 0 | D14: =COUNT(D$18:D$45) -> 7 | E14: =COUNT(E$18:E$45) -> 6 | F14: =COUNT(F$18:F$45) -> 6 | G14: =COUNT(G$18:G$45) -> 7 | H14: =COUNT(H$18:H$45) -> 5 | I14: =COUNT(I$18:I$45) -> 7 | ... U14: =COUNT(U$18:U$45) -> 0
A15: Cost per player (£) | B15: =IF(B$14=0,0,N(B$13)/B$14) -> 0 | C15: =IF(C$14=0,0,N(C$13)/C$14) -> 0 | D15: =IF(D$14=0,0,N(D$13)/D$14) -> 0 | E15: =IF(E$14=0,0,N(E$13)/E$14) -> 0 | F15: =IF(F$14=0,0,N(F$13)/F$14) -> 0 | G15: =IF(G$14=0,0,N(G$13)/G$14) -> 0 | H15: =IF(H$14=0,0,N(H$13)/H$14) -> 0 | I15: =IF(I$14=0,0,N(I$13)/I$14) -> 0 | ... U15: =IF(U$14=0,0,N(U$13)/U$14) -> 0
A16: Type (excl. from records) | C16: Forfeit | D16: Friendly | J16: Forfeit | K16: Forfeit
A17: APPEARANCES (1 = played) | B17: GW1 | C17: GW2 | D17: GW3 | E17: GW4 | F17: GW5 | G17: GW6 | H17: GW7 | I17: GW8 | J17: GW9 | K17: GW10 | L17: GW11 | M17: GW12 | N17: GW13 | O17: GW14 | P17: GW15 | Q17: GW16 | R17: GW17 | S17: GW18 | T17: GW19 | U17: GW20 | V17: Apps | W17: Cost (£)
A18: Ahmed | H18: 1 | M18: 1 | O18: 1 | V18: =SUMPRODUCT(B18:U18*($B$16:$U$16="")) -> 3 | W18: =SUMPRODUCT($B18:$U18,$B$15:$U$15) -> 0
A19: Alex Ruben | V19: =SUMPRODUCT(B19:U19*($B$16:$U$16="")) -> 0 | W19: =SUMPRODUCT($B19:$U19,$B$15:$U$15) -> 0
A20: Andy Cowan | V20: =SUMPRODUCT(B20:U20*($B$16:$U$16="")) -> 0 | W20: =SUMPRODUCT($B20:$U20,$B$15:$U$15) -> 0
A21: Ben Merrett | B21: 1 | D21: 1 | G21: 1 | H21: 1 | I21: 1 | L21: 1 | O21: 1 | V21: =SUMPRODUCT(B21:U21*($B$16:$U$16="")) -> 6 | W21: =SUMPRODUCT($B21:$U21,$B$15:$U$15) -> 0
A22: Callum McCarthy | V22: =SUMPRODUCT(B22:U22*($B$16:$U$16="")) -> 0 | W22: =SUMPRODUCT($B22:$U22,$B$15:$U$15) -> 0
A23: Cecil Watson | V23: =SUMPRODUCT(B23:U23*($B$16:$U$16="")) -> 0 | W23: =SUMPRODUCT($B23:$U23,$B$15:$U$15) -> 0
A24: Conall Templeman | B24: 1 | D24: 1 | E24: 1 | F24: 1 | G24: 1 | H24: 1 | I24: 1 | L24: 1 | P24: 1 | V24: =SUMPRODUCT(B24:U24*($B$16:$U$16="")) -> 8 | W24: =SUMPRODUCT($B24:$U24,$B$15:$U$15) -> 0
A25: Eddie Ringer | O25: 1 | V25: =SUMPRODUCT(B25:U25*($B$16:$U$16="")) -> 1 | W25: =SUMPRODUCT($B25:$U25,$B$15:$U$15) -> 0
A26: Finn Cawley | D26: 1 | G26: 1 | L26: 1 | V26: =SUMPRODUCT(B26:U26*($B$16:$U$16="")) -> 2 | W26: =SUMPRODUCT($B26:$U26,$B$15:$U$15) -> 0
A27: George Barbantan | L27: 1 | M27: 1 | O27: 1 | V27: =SUMPRODUCT(B27:U27*($B$16:$U$16="")) -> 3 | W27: =SUMPRODUCT($B27:$U27,$B$15:$U$15) -> 0
A28: Henry Linklater | V28: =SUMPRODUCT(B28:U28*($B$16:$U$16="")) -> 0 | W28: =SUMPRODUCT($B28:$U28,$B$15:$U$15) -> 0
A29: Isaac Mond | B29: 1 | D29: 1 | I29: 1 | N29: 1 | O29: 1 | V29: =SUMPRODUCT(B29:U29*($B$16:$U$16="")) -> 4 | W29: =SUMPRODUCT($B29:$U29,$B$15:$U$15) -> 0
A30: Jake Harrison | V30: =SUMPRODUCT(B30:U30*($B$16:$U$16="")) -> 0 | W30: =SUMPRODUCT($B30:$U30,$B$15:$U$15) -> 0
A31: Jake Ringer | N31: 1 | V31: =SUMPRODUCT(B31:U31*($B$16:$U$16="")) -> 1 | W31: =SUMPRODUCT($B31:$U31,$B$15:$U$15) -> 0
A32: Keshav Singh | E32: 1 | F32: 1 | I32: 1 | L32: 1 | M32: 1 | V32: =SUMPRODUCT(B32:U32*($B$16:$U$16="")) -> 5 | W32: =SUMPRODUCT($B32:$U32,$B$15:$U$15) -> 0
A33: Mark Pellowe | B33: 1 | E33: 1 | F33: 1 | G33: 1 | H33: 1 | I33: 1 | L33: 1 | M33: 1 | N33: 1 | O33: 1 | P33: 1 | V33: =SUMPRODUCT(B33:U33*($B$16:$U$16="")) -> 11 | W33: =SUMPRODUCT($B33:$U33,$B$15:$U$15) -> 0
A34: Max Cobain | B34: 1 | D34: 1 | E34: 1 | F34: 1 | V34: =SUMPRODUCT(B34:U34*($B$16:$U$16="")) -> 3 | W34: =SUMPRODUCT($B34:$U34,$B$15:$U$15) -> 0
A35: Neeraj Radia | B35: 1 | D35: 1 | F35: 1 | G35: 1 | V35: =SUMPRODUCT(B35:U35*($B$16:$U$16="")) -> 3 | W35: =SUMPRODUCT($B35:$U35,$B$15:$U$15) -> 0
A36: Phil Knott | B36: 1 | E36: 1 | G36: 1 | H36: 1 | I36: 1 | M36: 1 | N36: 1 | O36: 1 | V36: =SUMPRODUCT(B36:U36*($B$16:$U$16="")) -> 8 | W36: =SUMPRODUCT($B36:$U36,$B$15:$U$15) -> 0
A37: Robin | V37: =SUMPRODUCT(B37:U37*($B$16:$U$16="")) -> 0 | W37: =SUMPRODUCT($B37:$U37,$B$15:$U$15) -> 0
A38: Sam Holt | V38: =SUMPRODUCT(B38:U38*($B$16:$U$16="")) -> 0 | W38: =SUMPRODUCT($B38:$U38,$B$15:$U$15) -> 0
A39: Seb Burgess | D39: 1 | E39: 1 | F39: 1 | G39: 1 | I39: 1 | V39: =SUMPRODUCT(B39:U39*($B$16:$U$16="")) -> 4 | W39: =SUMPRODUCT($B39:$U39,$B$15:$U$15) -> 0
V40: =SUMPRODUCT(B40:U40*($B$16:$U$16="")) -> 0 | W40: =SUMPRODUCT($B40:$U40,$B$15:$U$15) -> 0
V41: =SUMPRODUCT(B41:U41*($B$16:$U$16="")) -> 0 | W41: =SUMPRODUCT($B41:$U41,$B$15:$U$15) -> 0
V42: =SUMPRODUCT(B42:U42*($B$16:$U$16="")) -> 0 | W42: =SUMPRODUCT($B42:$U42,$B$15:$U$15) -> 0
V43: =SUMPRODUCT(B43:U43*($B$16:$U$16="")) -> 0 | W43: =SUMPRODUCT($B43:$U43,$B$15:$U$15) -> 0
V44: =SUMPRODUCT(B44:U44*($B$16:$U$16="")) -> 0 | W44: =SUMPRODUCT($B44:$U44,$B$15:$U$15) -> 0
V45: =SUMPRODUCT(B45:U45*($B$16:$U$16="")) -> 0 | W45: =SUMPRODUCT($B45:$U45,$B$15:$U$15) -> 0
A46: Total | V46: =SUM(V18:V45) -> 62 | W46: =SUM(W18:W45) -> 0
A48: GOALS — number scored | B48: GW1 | C48: GW2 | D48: GW3 | E48: GW4 | F48: GW5 | G48: GW6 | H48: GW7 | I48: GW8 | J48: GW9 | K48: GW10 | L48: GW11 | M48: GW12 | N48: GW13 | O48: GW14 | P48: GW15 | Q48: GW16 | R48: GW17 | S48: GW18 | T48: GW19 | U48: GW20 | V48: Goals
A49: =IF($A18="","",$A18) -> Ahmed | H49: 1 | M49: 3 | O49: 1 | V49: =SUMPRODUCT(B49:U49*($B$16:$U$16="")) -> 5
A50: =IF($A19="","",$A19) -> Alex Ruben | V50: =SUMPRODUCT(B50:U50*($B$16:$U$16="")) -> 0
A51: =IF($A20="","",$A20) -> Andy Cowan | V51: =SUMPRODUCT(B51:U51*($B$16:$U$16="")) -> 0
A52: =IF($A21="","",$A21) -> Ben Merrett | G52: 1 | O52: 1 | V52: =SUMPRODUCT(B52:U52*($B$16:$U$16="")) -> 2
A53: =IF($A22="","",$A22) -> Callum McCarthy | V53: =SUMPRODUCT(B53:U53*($B$16:$U$16="")) -> 0
A54: =IF($A23="","",$A23) -> Cecil Watson | V54: =SUMPRODUCT(B54:U54*($B$16:$U$16="")) -> 0
A55: =IF($A24="","",$A24) -> Conall Templeman | B55: 1 | I55: 1 | P55: 1 | V55: =SUMPRODUCT(B55:U55*($B$16:$U$16="")) -> 3
A56: =IF($A25="","",$A25) -> Eddie Ringer | O56: 1 | V56: =SUMPRODUCT(B56:U56*($B$16:$U$16="")) -> 1
A57: =IF($A26="","",$A26) -> Finn Cawley | D57: 1 | G57: 2 | L57: 2 | V57: =SUMPRODUCT(B57:U57*($B$16:$U$16="")) -> 4
A58: =IF($A27="","",$A27) -> George Barbantan | L58: 1 | V58: =SUMPRODUCT(B58:U58*($B$16:$U$16="")) -> 1
A59: =IF($A28="","",$A28) -> Henry Linklater | V59: =SUMPRODUCT(B59:U59*($B$16:$U$16="")) -> 0
A60: =IF($A29="","",$A29) -> Isaac Mond | B60: 1 | V60: =SUMPRODUCT(B60:U60*($B$16:$U$16="")) -> 1
A61: =IF($A30="","",$A30) -> Jake Harrison | V61: =SUMPRODUCT(B61:U61*($B$16:$U$16="")) -> 0
A62: =IF($A31="","",$A31) -> Jake Ringer | V62: =SUMPRODUCT(B62:U62*($B$16:$U$16="")) -> 0
A63: =IF($A32="","",$A32) -> Keshav Singh | I63: 1 | V63: =SUMPRODUCT(B63:U63*($B$16:$U$16="")) -> 1
A64: =IF($A33="","",$A33) -> Mark Pellowe | P64: 1 | V64: =SUMPRODUCT(B64:U64*($B$16:$U$16="")) -> 1
A65: =IF($A34="","",$A34) -> Max Cobain | D65: 2 | F65: 1 | V65: =SUMPRODUCT(B65:U65*($B$16:$U$16="")) -> 1
A66: =IF($A35="","",$A35) -> Neeraj Radia | B66: 1 | V66: =SUMPRODUCT(B66:U66*($B$16:$U$16="")) -> 1
A67: =IF($A36="","",$A36) -> Phil Knott | E67: 2 | O67: 1 | V67: =SUMPRODUCT(B67:U67*($B$16:$U$16="")) -> 3
A68: =IF($A37="","",$A37) -> Robin | V68: =SUMPRODUCT(B68:U68*($B$16:$U$16="")) -> 0
A69: =IF($A38="","",$A38) -> Sam Holt | V69: =SUMPRODUCT(B69:U69*($B$16:$U$16="")) -> 0
A70: =IF($A39="","",$A39) -> Seb Burgess | D70: 4 | E70: 2 | F70: 1 | G70: 2 | V70: =SUMPRODUCT(B70:U70*($B$16:$U$16="")) -> 5
A71: =IF($A40="","",$A40) | V71: =SUMPRODUCT(B71:U71*($B$16:$U$16="")) -> 0
A72: =IF($A41="","",$A41) | V72: =SUMPRODUCT(B72:U72*($B$16:$U$16="")) -> 0
A73: =IF($A42="","",$A42) | V73: =SUMPRODUCT(B73:U73*($B$16:$U$16="")) -> 0
A74: =IF($A43="","",$A43) | V74: =SUMPRODUCT(B74:U74*($B$16:$U$16="")) -> 0
A75: =IF($A44="","",$A44) | V75: =SUMPRODUCT(B75:U75*($B$16:$U$16="")) -> 0
A76: =IF($A45="","",$A45) | V76: =SUMPRODUCT(B76:U76*($B$16:$U$16="")) -> 0
A77: Total | V77: =SUM(V49:V76) -> 29
A79: ASSISTS — number made | B79: GW1 | C79: GW2 | D79: GW3 | E79: GW4 | F79: GW5 | G79: GW6 | H79: GW7 | I79: GW8 | J79: GW9 | K79: GW10 | L79: GW11 | M79: GW12 | N79: GW13 | O79: GW14 | P79: GW15 | Q79: GW16 | R79: GW17 | S79: GW18 | T79: GW19 | U79: GW20 | V79: Assists
A80: =IF($A18="","",$A18) -> Ahmed | V80: =SUMPRODUCT(B80:U80*($B$16:$U$16="")) -> 0
A81: =IF($A19="","",$A19) -> Alex Ruben | V81: =SUMPRODUCT(B81:U81*($B$16:$U$16="")) -> 0
A82: =IF($A20="","",$A20) -> Andy Cowan | V82: =SUMPRODUCT(B82:U82*($B$16:$U$16="")) -> 0
A83: =IF($A21="","",$A21) -> Ben Merrett | V83: =SUMPRODUCT(B83:U83*($B$16:$U$16="")) -> 0
A84: =IF($A22="","",$A22) -> Callum McCarthy | V84: =SUMPRODUCT(B84:U84*($B$16:$U$16="")) -> 0
A85: =IF($A23="","",$A23) -> Cecil Watson | V85: =SUMPRODUCT(B85:U85*($B$16:$U$16="")) -> 0
A86: =IF($A24="","",$A24) -> Conall Templeman | V86: =SUMPRODUCT(B86:U86*($B$16:$U$16="")) -> 0
A87: =IF($A25="","",$A25) -> Eddie Ringer | V87: =SUMPRODUCT(B87:U87*($B$16:$U$16="")) -> 0
A88: =IF($A26="","",$A26) -> Finn Cawley | V88: =SUMPRODUCT(B88:U88*($B$16:$U$16="")) -> 0
A89: =IF($A27="","",$A27) -> George Barbantan | V89: =SUMPRODUCT(B89:U89*($B$16:$U$16="")) -> 0
A90: =IF($A28="","",$A28) -> Henry Linklater | V90: =SUMPRODUCT(B90:U90*($B$16:$U$16="")) -> 0
A91: =IF($A29="","",$A29) -> Isaac Mond | V91: =SUMPRODUCT(B91:U91*($B$16:$U$16="")) -> 0
... A107: =IF($A45="","",$A45) | V107: =SUMPRODUCT(B107:U107*($B$16:$U$16="")) -> 0
A108: Total | V108: =SUM(V80:V107) -> 0

Sheet S8
A1: Season 8 · Whitechapel Tuesday 6’s — Premier League · Sep 2026–Jan 2027
A2: Match | B2: GW1 | C2: GW2 | D2: GW3 | E2: GW4 | F2: GW5 | G2: GW6 | H2: GW7 | I2: GW8 | J2: GW9 | K2: GW10 | L2: GW11 | M2: GW12 | N2: GW13 | O2: GW14 | P2: GW15 | Q2: GW16 | R2: GW17 | S2: GW18 | T2: GW19 | U2: GW20 | X2: SEASON SUMMARY
A3: Date | B3: 46266 | C3: 46273 | D3: 46280 | E3: 46287 | F3: 46294 | G3: 46301 | H3: 46308 | I3: 46315 | J3: 46322 | K3: 46329 | L3: 46336 | M3: 46343 | N3: 46350 | O3: 46357 | P3: 46364 | Q3: 46371 | R3: 46392 | S3: 46399 | X3: Played | Y3: =Y4+Y5+Y6 -> 1
A4: Kick-off | B4: 0.81597222 | C4: 0.84375 | D4: 0.76041667 | E4: 0.87152778 | F4: 0.76041667 | G4: 0.76041667 | H4: 0.87152778 | I4: 0.87152778 | J4: 0.78819444 | K4: 0.81597222 | L4: 0.76041667 | M4: 0.84375 | N4: 0.84375 | O4: 0.84375 | P4: 0.78819444 | Q4: 0.87152778 | R4: 0.76041667 | S4: 0.76041667 | X4: Won | Y4: =SUMPRODUCT(($B$9:$U$9="W")*($B$16:$U$16="")) -> 0
A5: Opponent | B5: Spartak High Press, Low Standards | C5: Inter Islington | D5: TMHLR F.C. | E5: Heavy MWEtal Football | F5: Thundering Trunks | G5: Corsicans FC | H5: Monaco Goalkickers | I5: ABHUS FC | J5: MATHOL FC | K5: Spartak High Press, Low Standards | L5: Inter Islington | M5: TMHLR F.C. | N5: Heavy MWEtal Football | O5: Thundering Trunks | P5: Corsicans FC | Q5: Monaco Goalkickers | R5: ABHUS FC | S5: MATHOL FC | X5: Drawn | Y5: =SUMPRODUCT(($B$9:$U$9="D")*($B$16:$U$16="")) -> 0
A6: Our goals | B6: 5 | X6: Lost | Y6: =SUMPRODUCT(($B$9:$U$9="L")*($B$16:$U$16="")) -> 1
A7: Their goals | B7: 7 | X7: Goals for | Y7: =SUMPRODUCT($B$6:$U$6*($B$16:$U$16="")) -> 5
A8: Score | B8: =IF(COUNT(B6:B7)<2,"",B6&"-"&B7) -> 5-7 | C8: =IF(COUNT(C6:C7)<2,"",C6&"-"&C7) | D8: =IF(COUNT(D6:D7)<2,"",D6&"-"&D7) | E8: =IF(COUNT(E6:E7)<2,"",E6&"-"&E7) | F8: =IF(COUNT(F6:F7)<2,"",F6&"-"&F7) | G8: =IF(COUNT(G6:G7)<2,"",G6&"-"&G7) | H8: =IF(COUNT(H6:H7)<2,"",H6&"-"&H7) | I8: =IF(COUNT(I6:I7)<2,"",I6&"-"&I7) | ... U8: =IF(COUNT(U6:U7)<2,"",U6&"-"&U7) | X8: Goals against | Y8: =SUMPRODUCT($B$7:$U$7*($B$16:$U$16="")) -> 7
A9: Result | B9: =IF(COUNT(B6:B7)<2,"",IF(B6>B7,"W",IF(B6<B7,"L","D"))) -> L | C9: =IF(COUNT(C6:C7)<2,"",IF(C6>C7,"W",IF(C6<C7,"L","D"))) | D9: =IF(COUNT(D6:D7)<2,"",IF(D6>D7,"W",IF(D6<D7,"L","D"))) | E9: =IF(COUNT(E6:E7)<2,"",IF(E6>E7,"W",IF(E6<E7,"L","D"))) | F9: =IF(COUNT(F6:F7)<2,"",IF(F6>F7,"W",IF(F6<F7,"L","D"))) | G9: =IF(COUNT(G6:G7)<2,"",IF(G6>G7,"W",IF(G6<G7,"L","D"))) | H9: =IF(COUNT(H6:H7)<2,"",IF(H6>H7,"W",IF(H6<H7,"L","D"))) | I9: =IF(COUNT(I6:I7)<2,"",IF(I6>I7,"W",IF(I6<I7,"L","D"))) | ... U9: =IF(COUNT(U6:U7)<2,"",IF(U6>U7,"W",IF(U6<U7,"L","D"))) | X9: Top scorer | Y9: {=IF(MAX($V$49:$V$76)=0,"—",INDEX($A$49:$A$76,MATCH(MAX($V$49:$V$76),$V$49:$V$76,0))&" ("&MAX($V$49:$V$76)&")")} -> Seb Burgess (3)
A10: MOTM | X10: Most apps | Y10: {=IF(MAX($V$18:$V$45)=0,"—",INDEX($A$18:$A$45,MATCH(MAX($V$18:$V$45),$V$18:$V$45,0))&" ("&MAX($V$18:$V$45)&")")} -> Ben Merrett (1)
A11: Champagne moment | X11: Season cost | Y11: =SUM($B$13:$U$13) -> 1439.1
A12: Comments | X12: Paid by | Y12: Isaac Mond
A13: Match cost (£) | B13: 79.95 | C13: 79.95 | D13: 79.95 | E13: 79.95 | F13: 79.95 | G13: 79.95 | H13: 79.95 | I13: 79.95 | J13: 79.95 | K13: 79.95 | L13: 79.95 | M13: 79.95 | N13: 79.95 | O13: 79.95 | P13: 79.95 | Q13: 79.95 | R13: 79.95 | S13: 79.95
A14: Players in game | B14: =COUNT(B$18:B$45) -> 7 | C14: =COUNT(C$18:C$45) -> 0 | D14: =COUNT(D$18:D$45) -> 0 | E14: =COUNT(E$18:E$45) -> 0 | F14: =COUNT(F$18:F$45) -> 0 | G14: =COUNT(G$18:G$45) -> 0 | H14: =COUNT(H$18:H$45) -> 0 | I14: =COUNT(I$18:I$45) -> 0 | ... U14: =COUNT(U$18:U$45) -> 0
A15: Cost per player (£) | B15: =IF(B$14=0,0,N(B$13)/B$14) -> 11.421429 | C15: =IF(C$14=0,0,N(C$13)/C$14) -> 0 | D15: =IF(D$14=0,0,N(D$13)/D$14) -> 0 | E15: =IF(E$14=0,0,N(E$13)/E$14) -> 0 | F15: =IF(F$14=0,0,N(F$13)/F$14) -> 0 | G15: =IF(G$14=0,0,N(G$13)/G$14) -> 0 | H15: =IF(H$14=0,0,N(H$13)/H$14) -> 0 | I15: =IF(I$14=0,0,N(I$13)/I$14) -> 0 | ... U15: =IF(U$14=0,0,N(U$13)/U$14) -> 0
A16: Type (excl. from records)
A17: APPEARANCES (1 = played) | B17: GW1 | C17: GW2 | D17: GW3 | E17: GW4 | F17: GW5 | G17: GW6 | H17: GW7 | I17: GW8 | J17: GW9 | K17: GW10 | L17: GW11 | M17: GW12 | N17: GW13 | O17: GW14 | P17: GW15 | Q17: GW16 | R17: GW17 | S17: GW18 | T17: GW19 | U17: GW20 | V17: Apps | W17: Cost (£)
A18: Ahmed | V18: =SUMPRODUCT(B18:U18*($B$16:$U$16="")) -> 0 | W18: =SUMPRODUCT($B18:$U18,$B$15:$U$15) -> 0
A19: Alex Ruben | V19: =SUMPRODUCT(B19:U19*($B$16:$U$16="")) -> 0 | W19: =SUMPRODUCT($B19:$U19,$B$15:$U$15) -> 0
A20: Andy Cowan | V20: =SUMPRODUCT(B20:U20*($B$16:$U$16="")) -> 0 | W20: =SUMPRODUCT($B20:$U20,$B$15:$U$15) -> 0
A21: Ben Merrett | B21: 1 | V21: =SUMPRODUCT(B21:U21*($B$16:$U$16="")) -> 1 | W21: =SUMPRODUCT($B21:$U21,$B$15:$U$15) -> 11.421429
A22: Callum McCarthy | V22: =SUMPRODUCT(B22:U22*($B$16:$U$16="")) -> 0 | W22: =SUMPRODUCT($B22:$U22,$B$15:$U$15) -> 0
A23: Cecil Watson | V23: =SUMPRODUCT(B23:U23*($B$16:$U$16="")) -> 0 | W23: =SUMPRODUCT($B23:$U23,$B$15:$U$15) -> 0
A24: Conall Templeman | V24: =SUMPRODUCT(B24:U24*($B$16:$U$16="")) -> 0 | W24: =SUMPRODUCT($B24:$U24,$B$15:$U$15) -> 0
A25: Eddie Ringer | V25: =SUMPRODUCT(B25:U25*($B$16:$U$16="")) -> 0 | W25: =SUMPRODUCT($B25:$U25,$B$15:$U$15) -> 0
A26: Finn Cawley | B26: 1 | V26: =SUMPRODUCT(B26:U26*($B$16:$U$16="")) -> 1 | W26: =SUMPRODUCT($B26:$U26,$B$15:$U$15) -> 11.421429
A27: George Barbantan | V27: =SUMPRODUCT(B27:U27*($B$16:$U$16="")) -> 0 | W27: =SUMPRODUCT($B27:$U27,$B$15:$U$15) -> 0
A28: Henry Linklater | V28: =SUMPRODUCT(B28:U28*($B$16:$U$16="")) -> 0 | W28: =SUMPRODUCT($B28:$U28,$B$15:$U$15) -> 0
A29: Isaac Mond | B29: 1 | V29: =SUMPRODUCT(B29:U29*($B$16:$U$16="")) -> 1 | W29: =SUMPRODUCT($B29:$U29,$B$15:$U$15) -> 11.421429
A30: Jake Harrison | V30: =SUMPRODUCT(B30:U30*($B$16:$U$16="")) -> 0 | W30: =SUMPRODUCT($B30:$U30,$B$15:$U$15) -> 0
A31: Jake Ringer | V31: =SUMPRODUCT(B31:U31*($B$16:$U$16="")) -> 0 | W31: =SUMPRODUCT($B31:$U31,$B$15:$U$15) -> 0
A32: Keshav Singh | B32: 1 | V32: =SUMPRODUCT(B32:U32*($B$16:$U$16="")) -> 1 | W32: =SUMPRODUCT($B32:$U32,$B$15:$U$15) -> 11.421429
A33: Mark Pellowe | V33: =SUMPRODUCT(B33:U33*($B$16:$U$16="")) -> 0 | W33: =SUMPRODUCT($B33:$U33,$B$15:$U$15) -> 0
A34: Max Cobain | B34: 1 | V34: =SUMPRODUCT(B34:U34*($B$16:$U$16="")) -> 1 | W34: =SUMPRODUCT($B34:$U34,$B$15:$U$15) -> 11.421429
A35: Neeraj Radia | V35: =SUMPRODUCT(B35:U35*($B$16:$U$16="")) -> 0 | W35: =SUMPRODUCT($B35:$U35,$B$15:$U$15) -> 0
A36: Phil Knott | B36: 1 | V36: =SUMPRODUCT(B36:U36*($B$16:$U$16="")) -> 1 | W36: =SUMPRODUCT($B36:$U36,$B$15:$U$15) -> 11.421429
A37: Robin | V37: =SUMPRODUCT(B37:U37*($B$16:$U$16="")) -> 0 | W37: =SUMPRODUCT($B37:$U37,$B$15:$U$15) -> 0
A38: Sam Holt | V38: =SUMPRODUCT(B38:U38*($B$16:$U$16="")) -> 0 | W38: =SUMPRODUCT($B38:$U38,$B$15:$U$15) -> 0
A39: Seb Burgess | B39: 1 | V39: =SUMPRODUCT(B39:U39*($B$16:$U$16="")) -> 1 | W39: =SUMPRODUCT($B39:$U39,$B$15:$U$15) -> 11.421429
V40: =SUMPRODUCT(B40:U40*($B$16:$U$16="")) -> 0 | W40: =SUMPRODUCT($B40:$U40,$B$15:$U$15) -> 0
V41: =SUMPRODUCT(B41:U41*($B$16:$U$16="")) -> 0 | W41: =SUMPRODUCT($B41:$U41,$B$15:$U$15) -> 0
V42: =SUMPRODUCT(B42:U42*($B$16:$U$16="")) -> 0 | W42: =SUMPRODUCT($B42:$U42,$B$15:$U$15) -> 0
V43: =SUMPRODUCT(B43:U43*($B$16:$U$16="")) -> 0 | W43: =SUMPRODUCT($B43:$U43,$B$15:$U$15) -> 0
V44: =SUMPRODUCT(B44:U44*($B$16:$U$16="")) -> 0 | W44: =SUMPRODUCT($B44:$U44,$B$15:$U$15) -> 0
V45: =SUMPRODUCT(B45:U45*($B$16:$U$16="")) -> 0 | W45: =SUMPRODUCT($B45:$U45,$B$15:$U$15) -> 0
A46: Total | V46: =SUM(V18:V45) -> 7 | W46: =SUM(W18:W45) -> 79.95
A48: GOALS — number scored | B48: GW1 | C48: GW2 | D48: GW3 | E48: GW4 | F48: GW5 | G48: GW6 | H48: GW7 | I48: GW8 | J48: GW9 | K48: GW10 | L48: GW11 | M48: GW12 | N48: GW13 | O48: GW14 | P48: GW15 | Q48: GW16 | R48: GW17 | S48: GW18 | T48: GW19 | U48: GW20 | V48: Goals
A49: =IF($A18="","",$A18) -> Ahmed | V49: =SUMPRODUCT(B49:U49*($B$16:$U$16="")) -> 0
A50: =IF($A19="","",$A19) -> Alex Ruben | V50: =SUMPRODUCT(B50:U50*($B$16:$U$16="")) -> 0
A51: =IF($A20="","",$A20) -> Andy Cowan | V51: =SUMPRODUCT(B51:U51*($B$16:$U$16="")) -> 0
A52: =IF($A21="","",$A21) -> Ben Merrett | V52: =SUMPRODUCT(B52:U52*($B$16:$U$16="")) -> 0
A53: =IF($A22="","",$A22) -> Callum McCarthy | V53: =SUMPRODUCT(B53:U53*($B$16:$U$16="")) -> 0
A54: =IF($A23="","",$A23) -> Cecil Watson | V54: =SUMPRODUCT(B54:U54*($B$16:$U$16="")) -> 0
A55: =IF($A24="","",$A24) -> Conall Templeman | V55: =SUMPRODUCT(B55:U55*($B$16:$U$16="")) -> 0
A56: =IF($A25="","",$A25) -> Eddie Ringer | V56: =SUMPRODUCT(B56:U56*($B$16:$U$16="")) -> 0
A57: =IF($A26="","",$A26) -> Finn Cawley | B57: 2 | V57: =SUMPRODUCT(B57:U57*($B$16:$U$16="")) -> 2
A58: =IF($A27="","",$A27) -> George Barbantan | V58: =SUMPRODUCT(B58:U58*($B$16:$U$16="")) -> 0
A59: =IF($A28="","",$A28) -> Henry Linklater | V59: =SUMPRODUCT(B59:U59*($B$16:$U$16="")) -> 0
A60: =IF($A29="","",$A29) -> Isaac Mond | V60: =SUMPRODUCT(B60:U60*($B$16:$U$16="")) -> 0
A61: =IF($A30="","",$A30) -> Jake Harrison | V61: =SUMPRODUCT(B61:U61*($B$16:$U$16="")) -> 0
A62: =IF($A31="","",$A31) -> Jake Ringer | V62: =SUMPRODUCT(B62:U62*($B$16:$U$16="")) -> 0
A63: =IF($A32="","",$A32) -> Keshav Singh | V63: =SUMPRODUCT(B63:U63*($B$16:$U$16="")) -> 0
A64: =IF($A33="","",$A33) -> Mark Pellowe | V64: =SUMPRODUCT(B64:U64*($B$16:$U$16="")) -> 0
A65: =IF($A34="","",$A34) -> Max Cobain | V65: =SUMPRODUCT(B65:U65*($B$16:$U$16="")) -> 0
A66: =IF($A35="","",$A35) -> Neeraj Radia | V66: =SUMPRODUCT(B66:U66*($B$16:$U$16="")) -> 0
A67: =IF($A36="","",$A36) -> Phil Knott | V67: =SUMPRODUCT(B67:U67*($B$16:$U$16="")) -> 0
A68: =IF($A37="","",$A37) -> Robin | V68: =SUMPRODUCT(B68:U68*($B$16:$U$16="")) -> 0
A69: =IF($A38="","",$A38) -> Sam Holt | V69: =SUMPRODUCT(B69:U69*($B$16:$U$16="")) -> 0
A70: =IF($A39="","",$A39) -> Seb Burgess | B70: 3 | V70: =SUMPRODUCT(B70:U70*($B$16:$U$16="")) -> 3
A71: =IF($A40="","",$A40) | V71: =SUMPRODUCT(B71:U71*($B$16:$U$16="")) -> 0
A72: =IF($A41="","",$A41) | V72: =SUMPRODUCT(B72:U72*($B$16:$U$16="")) -> 0
A73: =IF($A42="","",$A42) | V73: =SUMPRODUCT(B73:U73*($B$16:$U$16="")) -> 0
A74: =IF($A43="","",$A43) | V74: =SUMPRODUCT(B74:U74*($B$16:$U$16="")) -> 0
A75: =IF($A44="","",$A44) | V75: =SUMPRODUCT(B75:U75*($B$16:$U$16="")) -> 0
A76: =IF($A45="","",$A45) | V76: =SUMPRODUCT(B76:U76*($B$16:$U$16="")) -> 0
A77: Total | V77: =SUM(V49:V76) -> 5
A79: ASSISTS — number made | B79: GW1 | C79: GW2 | D79: GW3 | E79: GW4 | F79: GW5 | G79: GW6 | H79: GW7 | I79: GW8 | J79: GW9 | K79: GW10 | L79: GW11 | M79: GW12 | N79: GW13 | O79: GW14 | P79: GW15 | Q79: GW16 | R79: GW17 | S79: GW18 | T79: GW19 | U79: GW20 | V79: Assists
A80: =IF($A18="","",$A18) -> Ahmed | V80: =SUMPRODUCT(B80:U80*($B$16:$U$16="")) -> 0
A81: =IF($A19="","",$A19) -> Alex Ruben | V81: =SUMPRODUCT(B81:U81*($B$16:$U$16="")) -> 0
A82: =IF($A20="","",$A20) -> Andy Cowan | V82: =SUMPRODUCT(B82:U82*($B$16:$U$16="")) -> 0
A83: =IF($A21="","",$A21) -> Ben Merrett | V83: =SUMPRODUCT(B83:U83*($B$16:$U$16="")) -> 0
A84: =IF($A22="","",$A22) -> Callum McCarthy | V84: =SUMPRODUCT(B84:U84*($B$16:$U$16="")) -> 0
A85: =IF($A23="","",$A23) -> Cecil Watson | V85: =SUMPRODUCT(B85:U85*($B$16:$U$16="")) -> 0
A86: =IF($A24="","",$A24) -> Conall Templeman | V86: =SUMPRODUCT(B86:U86*($B$16:$U$16="")) -> 0
A87: =IF($A25="","",$A25) -> Eddie Ringer | V87: =SUMPRODUCT(B87:U87*($B$16:$U$16="")) -> 0
A88: =IF($A26="","",$A26) -> Finn Cawley | V88: =SUMPRODUCT(B88:U88*($B$16:$U$16="")) -> 0
A89: =IF($A27="","",$A27) -> George Barbantan | V89: =SUMPRODUCT(B89:U89*($B$16:$U$16="")) -> 0
A90: =IF($A28="","",$A28) -> Henry Linklater | V90: =SUMPRODUCT(B90:U90*($B$16:$U$16="")) -> 0
A91: =IF($A29="","",$A29) -> Isaac Mond | B91: 1 | V91: =SUMPRODUCT(B91:U91*($B$16:$U$16="")) -> 1
A92: =IF($A30="","",$A30) -> Jake Harrison | V92: =SUMPRODUCT(B92:U92*($B$16:$U$16="")) -> 0
A93: =IF($A31="","",$A31) -> Jake Ringer | V93: =SUMPRODUCT(B93:U93*($B$16:$U$16="")) -> 0
A94: =IF($A32="","",$A32) -> Keshav Singh | B94: 1 | V94: =SUMPRODUCT(B94:U94*($B$16:$U$16="")) -> 1
A95: =IF($A33="","",$A33) -> Mark Pellowe | V95: =SUMPRODUCT(B95:U95*($B$16:$U$16="")) -> 0
A96: =IF($A34="","",$A34) -> Max Cobain | B96: 2 | V96: =SUMPRODUCT(B96:U96*($B$16:$U$16="")) -> 2
A97: =IF($A35="","",$A35) -> Neeraj Radia | V97: =SUMPRODUCT(B97:U97*($B$16:$U$16="")) -> 0
A98: =IF($A36="","",$A36) -> Phil Knott | B98: 1 | V98: =SUMPRODUCT(B98:U98*($B$16:$U$16="")) -> 1
A99: =IF($A37="","",$A37) -> Robin | V99: =SUMPRODUCT(B99:U99*($B$16:$U$16="")) -> 0
A100: =IF($A38="","",$A38) -> Sam Holt | V100: =SUMPRODUCT(B100:U100*($B$16:$U$16="")) -> 0
A101: =IF($A39="","",$A39) -> Seb Burgess | V101: =SUMPRODUCT(B101:U101*($B$16:$U$16="")) -> 0
A102: =IF($A40="","",$A40) | V102: =SUMPRODUCT(B102:U102*($B$16:$U$16="")) -> 0
...

Sheet Season template
A1: SEASON TEMPLATE — duplicate this tab, rename it (e.g. S9), fill in fixtures
A2: Match | B2: GW1 | C2: GW2 | D2: GW3 | E2: GW4 | F2: GW5 | G2: GW6 | H2: GW7 | I2: GW8 | J2: GW9 | K2: GW10 | L2: GW11 | M2: GW12 | N2: GW13 | O2: GW14 | P2: GW15 | Q2: GW16 | R2: GW17 | S2: GW18 | T2: GW19 | U2: GW20 | X2: SEASON SUMMARY
A3: Date | X3: Played | Y3: =Y4+Y5+Y6 -> 0
A4: Kick-off | X4: Won | Y4: =SUMPRODUCT(($B$9:$U$9="W")*($B$16:$U$16="")) -> 0
A5: Opponent | X5: Drawn | Y5: =SUMPRODUCT(($B$9:$U$9="D")*($B$16:$U$16="")) -> 0
A6: Our goals | X6: Lost | Y6: =SUMPRODUCT(($B$9:$U$9="L")*($B$16:$U$16="")) -> 0
A7: Their goals | X7: Goals for | Y7: =SUMPRODUCT($B$6:$U$6*($B$16:$U$16="")) -> 0
A8: Score | B8: =IF(COUNT(B6:B7)<2,"",B6&"-"&B7) | C8: =IF(COUNT(C6:C7)<2,"",C6&"-"&C7) | D8: =IF(COUNT(D6:D7)<2,"",D6&"-"&D7) | E8: =IF(COUNT(E6:E7)<2,"",E6&"-"&E7) | F8: =IF(COUNT(F6:F7)<2,"",F6&"-"&F7) | G8: =IF(COUNT(G6:G7)<2,"",G6&"-"&G7) | H8: =IF(COUNT(H6:H7)<2,"",H6&"-"&H7) | I8: =IF(COUNT(I6:I7)<2,"",I6&"-"&I7) | ... U8: =IF(COUNT(U6:U7)<2,"",U6&"-"&U7) | X8: Goals against | Y8: =SUMPRODUCT($B$7:$U$7*($B$16:$U$16="")) -> 0
A9: Result | B9: =IF(COUNT(B6:B7)<2,"",IF(B6>B7,"W",IF(B6<B7,"L","D"))) | C9: =IF(COUNT(C6:C7)<2,"",IF(C6>C7,"W",IF(C6<C7,"L","D"))) | D9: =IF(COUNT(D6:D7)<2,"",IF(D6>D7,"W",IF(D6<D7,"L","D"))) | E9: =IF(COUNT(E6:E7)<2,"",IF(E6>E7,"W",IF(E6<E7,"L","D"))) | F9: =IF(COUNT(F6:F7)<2,"",IF(F6>F7,"W",IF(F6<F7,"L","D"))) | G9: =IF(COUNT(G6:G7)<2,"",IF(G6>G7,"W",IF(G6<G7,"L","D"))) | H9: =IF(COUNT(H6:H7)<2,"",IF(H6>H7,"W",IF(H6<H7,"L","D"))) | I9: =IF(COUNT(I6:I7)<2,"",IF(I6>I7,"W",IF(I6<I7,"L","D"))) | ... U9: =IF(COUNT(U6:U7)<2,"",IF(U6>U7,"W",IF(U6<U7,"L","D"))) | X9: Top scorer | Y9: {=IF(MAX($V$49:$V$76)=0,"—",INDEX($A$49:$A$76,MATCH(MAX($V$49:$V$76),$V$49:$V$76,0))&" ("&MAX($V$49:$V$76)&")")} -> —
A10: MOTM | X10: Most apps | Y10: {=IF(MAX($V$18:$V$45)=0,"—",INDEX($A$18:$A$45,MATCH(MAX($V$18:$V$45),$V$18:$V$45,0))&" ("&MAX($V$18:$V$45)&")")} -> —
A11: Champagne moment | X11: Season cost | Y11: =SUM($B$13:$U$13) -> 0
A12: Comments | X12: Paid by
A13: Match cost (£)
A14: Players in game | B14: =COUNT(B$18:B$45) -> 0 | C14: =COUNT(C$18:C$45) -> 0 | D14: =COUNT(D$18:D$45) -> 0 | E14: =COUNT(E$18:E$45) -> 0 | F14: =COUNT(F$18:F$45) -> 0 | G14: =COUNT(G$18:G$45) -> 0 | H14: =COUNT(H$18:H$45) -> 0 | I14: =COUNT(I$18:I$45) -> 0 | ... U14: =COUNT(U$18:U$45) -> 0
A15: Cost per player (£) | B15: =IF(B$14=0,0,N(B$13)/B$14) -> 0 | C15: =IF(C$14=0,0,N(C$13)/C$14) -> 0 | D15: =IF(D$14=0,0,N(D$13)/D$14) -> 0 | E15: =IF(E$14=0,0,N(E$13)/E$14) -> 0 | F15: =IF(F$14=0,0,N(F$13)/F$14) -> 0 | G15: =IF(G$14=0,0,N(G$13)/G$14) -> 0 | H15: =IF(H$14=0,0,N(H$13)/H$14) -> 0 | I15: =IF(I$14=0,0,N(I$13)/I$14) -> 0 | ... U15: =IF(U$14=0,0,N(U$13)/U$14) -> 0
A16: Type (excl. from records)
A17: APPEARANCES (1 = played) | B17: GW1 | C17: GW2 | D17: GW3 | E17: GW4 | F17: GW5 | G17: GW6 | H17: GW7 | I17: GW8 | J17: GW9 | K17: GW10 | L17: GW11 | M17: GW12 | N17: GW13 | O17: GW14 | P17: GW15 | Q17: GW16 | R17: GW17 | S17: GW18 | T17: GW19 | U17: GW20 | V17: Apps | W17: Cost (£)
A18: Ahmed | V18: =SUMPRODUCT(B18:U18*($B$16:$U$16="")) -> 0 | W18: =SUMPRODUCT($B18:$U18,$B$15:$U$15) -> 0
A19: Alex Ruben | V19: =SUMPRODUCT(B19:U19*($B$16:$U$16="")) -> 0 | W19: =SUMPRODUCT($B19:$U19,$B$15:$U$15) -> 0
A20: Andy Cowan | V20: =SUMPRODUCT(B20:U20*($B$16:$U$16="")) -> 0 | W20: =SUMPRODUCT($B20:$U20,$B$15:$U$15) -> 0
A21: Ben Merrett | V21: =SUMPRODUCT(B21:U21*($B$16:$U$16="")) -> 0 | W21: =SUMPRODUCT($B21:$U21,$B$15:$U$15) -> 0
A22: Callum McCarthy | V22: =SUMPRODUCT(B22:U22*($B$16:$U$16="")) -> 0 | W22: =SUMPRODUCT($B22:$U22,$B$15:$U$15) -> 0
A23: Cecil Watson | V23: =SUMPRODUCT(B23:U23*($B$16:$U$16="")) -> 0 | W23: =SUMPRODUCT($B23:$U23,$B$15:$U$15) -> 0
A24: Conall Templeman | V24: =SUMPRODUCT(B24:U24*($B$16:$U$16="")) -> 0 | W24: =SUMPRODUCT($B24:$U24,$B$15:$U$15) -> 0
A25: Eddie Ringer | V25: =SUMPRODUCT(B25:U25*($B$16:$U$16="")) -> 0 | W25: =SUMPRODUCT($B25:$U25,$B$15:$U$15) -> 0
A26: Finn Cawley | V26: =SUMPRODUCT(B26:U26*($B$16:$U$16="")) -> 0 | W26: =SUMPRODUCT($B26:$U26,$B$15:$U$15) -> 0
A27: George Barbantan | V27: =SUMPRODUCT(B27:U27*($B$16:$U$16="")) -> 0 | W27: =SUMPRODUCT($B27:$U27,$B$15:$U$15) -> 0
A28: Henry Linklater | V28: =SUMPRODUCT(B28:U28*($B$16:$U$16="")) -> 0 | W28: =SUMPRODUCT($B28:$U28,$B$15:$U$15) -> 0
A29: Isaac Mond | V29: =SUMPRODUCT(B29:U29*($B$16:$U$16="")) -> 0 | W29: =SUMPRODUCT($B29:$U29,$B$15:$U$15) -> 0
... A39: Seb Burgess | V39: =SUMPRODUCT(B39:U39*($B$16:$U$16="")) -> 0 | W39: =SUMPRODUCT($B39:$U39,$B$15:$U$15) -> 0
V40: =SUMPRODUCT(B40:U40*($B$16:$U$16="")) -> 0 | W40: =SUMPRODUCT($B40:$U40,$B$15:$U$15) -> 0
V41: =SUMPRODUCT(B41:U41*($B$16:$U$16="")) -> 0 | W41: =SUMPRODUCT($B41:$U41,$B$15:$U$15) -> 0
V42: =SUMPRODUCT(B42:U42*($B$16:$U$16="")) -> 0 | W42: =SUMPRODUCT($B42:$U42,$B$15:$U$15) -> 0
V43: =SUMPRODUCT(B43:U43*($B$16:$U$16="")) -> 0 | W43: =SUMPRODUCT($B43:$U43,$B$15:$U$15) -> 0
V44: =SUMPRODUCT(B44:U44*($B$16:$U$16="")) -> 0 | W44: =SUMPRODUCT($B44:$U44,$B$15:$U$15) -> 0
V45: =SUMPRODUCT(B45:U45*($B$16:$U$16="")) -> 0 | W45: =SUMPRODUCT($B45:$U45,$B$15:$U$15) -> 0
A46: Total | V46: =SUM(V18:V45) -> 0 | W46: =SUM(W18:W45) -> 0
A48: GOALS — number scored | B48: GW1 | C48: GW2 | D48: GW3 | E48: GW4 | F48: GW5 | G48: GW6 | H48: GW7 | I48: GW8 | J48: GW9 | K48: GW10 | L48: GW11 | M48: GW12 | N48: GW13 | O48: GW14 | P48: GW15 | Q48: GW16 | R48: GW17 | S48: GW18 | T48: GW19 | U48: GW20 | V48: Goals
A49: =IF($A18="","",$A18) -> Ahmed | V49: =SUMPRODUCT(B49:U49*($B$16:$U$16="")) -> 0
A50: =IF($A19="","",$A19) -> Alex Ruben | V50: =SUMPRODUCT(B50:U50*($B$16:$U$16="")) -> 0
A51: =IF($A20="","",$A20) -> Andy Cowan | V51: =SUMPRODUCT(B51:U51*($B$16:$U$16="")) -> 0
A52: =IF($A21="","",$A21) -> Ben Merrett | V52: =SUMPRODUCT(B52:U52*($B$16:$U$16="")) -> 0
A53: =IF($A22="","",$A22) -> Callum McCarthy | V53: =SUMPRODUCT(B53:U53*($B$16:$U$16="")) -> 0
A54: =IF($A23="","",$A23) -> Cecil Watson | V54: =SUMPRODUCT(B54:U54*($B$16:$U$16="")) -> 0
A55: =IF($A24="","",$A24) -> Conall Templeman | V55: =SUMPRODUCT(B55:U55*($B$16:$U$16="")) -> 0
A56: =IF($A25="","",$A25) -> Eddie Ringer | V56: =SUMPRODUCT(B56:U56*($B$16:$U$16="")) -> 0
A57: =IF($A26="","",$A26) -> Finn Cawley | V57: =SUMPRODUCT(B57:U57*($B$16:$U$16="")) -> 0
A58: =IF($A27="","",$A27) -> George Barbantan | V58: =SUMPRODUCT(B58:U58*($B$16:$U$16="")) -> 0
A59: =IF($A28="","",$A28) -> Henry Linklater | V59: =SUMPRODUCT(B59:U59*($B$16:$U$16="")) -> 0
A60: =IF($A29="","",$A29) -> Isaac Mond | V60: =SUMPRODUCT(B60:U60*($B$16:$U$16="")) -> 0
... A76: =IF($A45="","",$A45) | V76: =SUMPRODUCT(B76:U76*($B$16:$U$16="")) -> 0
A77: Total | V77: =SUM(V49:V76) -> 0
A79: ASSISTS — number made | B79: GW1 | C79: GW2 | D79: GW3 | E79: GW4 | F79: GW5 | G79: GW6 | H79: GW7 | I79: GW8 | J79: GW9 | K79: GW10 | L79: GW11 | M79: GW12 | N79: GW13 | O79: GW14 | P79: GW15 | Q79: GW16 | R79: GW17 | S79: GW18 | T79: GW19 | U79: GW20 | V79: Assists
A80: =IF($A18="","",$A18) -> Ahmed | V80: =SUMPRODUCT(B80:U80*($B$16:$U$16="")) -> 0
A81: =IF($A19="","",$A19) -> Alex Ruben | V81: =SUMPRODUCT(B81:U81*($B$16:$U$16="")) -> 0
A82: =IF($A20="","",$A20) -> Andy Cowan | V82: =SUMPRODUCT(B82:U82*($B$16:$U$16="")) -> 0
A83: =IF($A21="","",$A21) -> Ben Merrett | V83: =SUMPRODUCT(B83:U83*($B$16:$U$16="")) -> 0
A84: =IF($A22="","",$A22) -> Callum McCarthy | V84: =SUMPRODUCT(B84:U84*($B$16:$U$16="")) -> 0
A85: =IF($A23="","",$A23) -> Cecil Watson | V85: =SUMPRODUCT(B85:U85*($B$16:$U$16="")) -> 0
A86: =IF($A24="","",$A24) -> Conall Templeman | V86: =SUMPRODUCT(B86:U86*($B$16:$U$16="")) -> 0
A87: =IF($A25="","",$A25) -> Eddie Ringer | V87: =SUMPRODUCT(B87:U87*($B$16:$U$16="")) -> 0
A88: =IF($A26="","",$A26) -> Finn Cawley | V88: =SUMPRODUCT(B88:U88*($B$16:$U$16="")) -> 0
A89: =IF($A27="","",$A27) -> George Barbantan | V89: =SUMPRODUCT(B89:U89*($B$16:$U$16="")) -> 0
A90: =IF($A28="","",$A28) -> Henry Linklater | V90: =SUMPRODUCT(B90:U90*($B$16:$U$16="")) -> 0
A91: =IF($A29="","",$A29) -> Isaac Mond | V91: =SUMPRODUCT(B91:U91*($B$16:$U$16="")) -> 0
... A107: =IF($A45="","",$A45) | V107: =SUMPRODUCT(B107:U107*($B$16:$U$16="")) -> 0
A108: Total | V108: =SUM(V80:V107) -> 0

Sheet All-time
A1: ALL-TIME RECORDS (updates automatically from the season tabs) | B1: S1 | D1: S2 | F1: S3 | H1: S4 | J1: S5 | L1: S6 | N1: S7 | P1: S8 | R1: S9 | T1: S10 | V1: ALL-TIME
A2: Player | B2: Apps | C2: Goals | D2: Apps | E2: Goals | F2: Apps | G2: Goals | H2: Apps | I2: Goals | J2: Apps | K2: Goals | L2: Apps | M2: Goals | N2: Apps | O2: Goals | P2: Apps | Q2: Goals | R2: Apps | S2: Goals | T2: Apps | U2: Goals | V2: Apps | W2: Goals | X2: Goals/game | Y2: Assists
A3: Ahmed | B3: =IFERROR(INDEX(INDIRECT("'"&B$1&"'!$V$18:$V$45"),MATCH($A3,INDIRECT("'"&B$1&"'!$A$18:$A$45"),0)),0) -> 0 | C3: =IFERROR(INDEX(INDIRECT("'"&B$1&"'!$V$49:$V$76"),MATCH($A3,INDIRECT("'"&B$1&"'!$A$49:$A$76"),0)),0) -> 0 | D3: =IFERROR(INDEX(INDIRECT("'"&D$1&"'!$V$18:$V$45"),MATCH($A3,INDIRECT("'"&D$1&"'!$A$18:$A$45"),0)),0) -> 0 | E3: =IFERROR(INDEX(INDIRECT("'"&D$1&"'!$V$49:$V$76"),MATCH($A3,INDIRECT("'"&D$1&"'!$A$49:$A$76"),0)),0) -> 0 | F3: =IFERROR(INDEX(INDIRECT("'"&F$1&"'!$V$18:$V$45"),MATCH($A3,INDIRECT("'"&F$1&"'!$A$18:$A$45"),0)),0) -> 0 | G3: =IFERROR(INDEX(INDIRECT("'"&F$1&"'!$V$49:$V$76"),MATCH($A3,INDIRECT("'"&F$1&"'!$A$49:$A$76"),0)),0) -> 0 | H3: =IFERROR(INDEX(INDIRECT("'"&H$1&"'!$V$18:$V$45"),MATCH($A3,INDIRECT("'"&H$1&"'!$A$18:$A$45"),0)),0) -> 0 | I3: =IFERROR(INDEX(INDIRECT("'"&H$1&"'!$V$49:$V$76"),MATCH($A3,INDIRECT("'"&H$1&"'!$A$49:$A$76"),0)),0) -> 0 | J3: =IFERROR(INDEX(INDIRECT("'"&J$1&"'!$V$18:$V$45"),MATCH($A3,INDIRECT("'"&J$1&"'!$A$18:$A$45"),0)),0) -> 0 | K3: =IFERROR(INDEX(INDIRECT("'"&J$1&"'!$V$49:$V$76"),MATCH($A3,INDIRECT("'"&J$1&"'!$A$49:$A$76"),0)),0) -> 0 | L3: =IFERROR(INDEX(INDIRECT("'"&L$1&"'!$V$18:$V$45"),MATCH($A3,INDIRECT("'"&L$1&"'!$A$18:$A$45"),0)),0) -> 0 | M3: =IFERROR(INDEX(INDIRECT("'"&L$1&"'!$V$49:$V$76"),MATCH($A3,INDIRECT("'"&L$1&"'!$A$49:$A$76"),0)),0) -> 0 | N3: =IFERROR(INDEX(INDIRECT("'"&N$1&"'!$V$18:$V$45"),MATCH($A3,INDIRECT("'"&N$1&"'!$A$18:$A$45"),0)),0) -> 3 | O3: =IFERROR(INDEX(INDIRECT("'"&N$1&"'!$V$49:$V$76"),MATCH($A3,INDIRECT("'"&N$1&"'!$A$49:$A$76"),0)),0) -> 5 | P3: =IFERROR(INDEX(INDIRECT("'"&P$1&"'!$V$18:$V$45"),MATCH($A3,INDIRECT("'"&P$1&"'!$A$18:$A$45"),0)),0) -> 0 | Q3: =IFERROR(INDEX(INDIRECT("'"&P$1&"'!$V$49:$V$76"),MATCH($A3,INDIRECT("'"&P$1&"'!$A$49:$A$76"),0)),0) -> 0 | R3: =IFERROR(INDEX(INDIRECT("'"&R$1&"'!$V$18:$V$45"),MATCH($A3,INDIRECT("'"&R$1&"'!$A$18:$A$45"),0)),0) -> 0 | S3: =IFERROR(INDEX(INDIRECT("'"&R$1&"'!$V$49:$V$76"),MATCH($A3,INDIRECT("'"&R$1&"'!$A$49:$A$76"),0)),0) -> 0 | T3: =IFERROR(INDEX(INDIRECT("'"&T$1&"'!$V$18:$V$45"),MATCH($A3,INDIRECT("'"&T$1&"'!$A$18:$A$45"),0)),0) -> 0 | U3: =IFERROR(INDEX(INDIRECT("'"&T$1&"'!$V$49:$V$76"),MATCH($A3,INDIRECT("'"&T$1&"'!$A$49:$A$76"),0)),0) -> 0 | V3: =B3+D3+F3+H3+J3+L3+N3+P3+R3+T3 -> 3 | W3: =C3+E3+G3+I3+K3+M3+O3+Q3+S3+U3 -> 5 | X3: =IF(V3=0,"—",ROUND(W3/V3,2)) -> 1.67 | Y3: =IFERROR(INDEX(INDIRECT("'"&B$1&"'!$V$80:$V$107"),MATCH($A3,INDIRECT("'"&B$1&"'!$A$80:$A$107"),0)),0)+IFERROR(INDEX(INDIRECT("'"&D$1&"'!$V$80:$V$107"),MATCH($A3,INDIRECT("'"&D$1&"'!$A$80:$A$107"),0)),0)+IFERROR(INDEX(INDIRECT("'"&F$1&"'!$V$80:$V$107"),MATCH($A3,INDIRECT("'"&F$1&"'!$A$80:$A$107"),0)),0)+IFERROR(INDEX(INDIRECT("'"&H$1&"'!$V$80:$V$107"),MATCH($A3,INDIRECT("'"&H$1&"'!$A$80:$A$107"),0)),0)+IFERROR(INDEX(INDIRECT("'"&J$1&"'!$V$80:$V$107"),MATCH($A3,INDIRECT("'"&J$1&"'!$A$80:$A$107"),0)),0)+IFERROR(INDEX(INDIRECT("'"&L$1&"'!$V$80:$V$107"),MATCH($A3,INDIRECT("'"&L$1&"'!$A$80:$A$107"),0)),0)+IFERROR(INDEX(INDIRECT("'"&N$1&"'!$V$80:$V$107"),MATCH($A3,INDIRECT("'"&N$1&"'!$A$80:$A$107"),0)),0)+IFERROR(INDEX(INDIRECT("'"&P$1&"'!$V$80:$V$107"),MATCH($A3,INDIRECT("'"&P$1&"'!$A$80:$A$107"),0)),0)+IFERROR(INDEX(INDIRECT("'"&R$1&"'!$V$80:$V$107"),MATCH($A3,INDIRECT("'"&R$1&"'!$A$80:$A$107"),0)),0)+IFERROR(INDEX(INDIRECT("'"&T$1&"'!$V$80:$V$107"),MATCH($A3,INDIRECT("'"&T$1&"'!$A$80:$A$107"),0)),0) -> 0
A4: Alex Ruben | B4: =IFERROR(INDEX(INDIRECT("'"&B$1&"'!$V$18:$V$45"),MATCH($A4,INDIRECT("'"&B$1&"'!$A$18:$A$45"),0)),0) -> 0 | C4: =IFERROR(INDEX(INDIRECT("'"&B$1&"'!$V$49:$V$76"),MATCH($A4,INDIRECT("'"&B$1&"'!$A$49:$A$76"),0)),0) -> 0 | D4: =IFERROR(INDEX(INDIRECT("'"&D$1&"'!$V$18:$V$45"),MATCH($A4,INDIRECT("'"&D$1&"'!$A$18:$A$45"),0)),0) -> 1 | E4: =IFERROR(INDEX(INDIRECT("'"&D$1&"'!$V$49:$V$76"),MATCH($A4,INDIRECT("'"&D$1&"'!$A$49:$A$76"),0)),0) -> 0 | F4: =IFERROR(INDEX(INDIRECT("'"&F$1&"'!$V$18:$V$45"),MATCH($A4,INDIRECT("'"&F$1&"'!$A$18:$A$45"),0)),0) -> 2 | G4: =IFERROR(INDEX(INDIRECT("'"&F$1&"'!$V$49:$V$76"),MATCH($A4,INDIRECT("'"&F$1&"'!$A$49:$A$76"),0)),0) -> 0 | H4: =IFERROR(INDEX(INDIRECT("'"&H$1&"'!$V$18:$V$45"),MATCH($A4,INDIRECT("'"&H$1&"'!$A$18:$A$45"),0)),0) -> 1 | I4: =IFERROR(INDEX(INDIRECT("'"&H$1&"'!$V$49:$V$76"),MATCH($A4,INDIRECT("'"&H$1&"'!$A$49:$A$76"),0)),0) -> 0 | J4: =IFERROR(INDEX(INDIRECT("'"&J$1&"'!$V$18:$V$45"),MATCH($A4,INDIRECT("'"&J$1&"'!$A$18:$A$45"),0)),0) -> 1 | K4: =IFERROR(INDEX(INDIRECT("'"&J$1&"'!$V$49:$V$76"),MATCH($A4,INDIRECT("'"&J$1&"'!$A$49:$A$76"),0)),0) -> 0 | L4: =IFERROR(INDEX(INDIRECT("'"&L$1&"'!$V$18:$V$45"),MATCH($A4,INDIRECT("'"&L$1&"'!$A$18:$A$45"),0)),0) -> 0 | M4: =IFERROR(INDEX(INDIRECT("'"&L$1&"'!$V$49:$V$76"),MATCH($A4,INDIRECT("'"&L$1&"'!$A$49:$A$76"),0)),0) -> 0 | N4: =IFERROR(INDEX(INDIRECT("'"&N$1&"'!$V$18:$V$45"),MATCH($A4,INDIRECT("'"&N$1&"'!$A$18:$A$45"),0)),0) -> 0 | O4: =IFERROR(INDEX(INDIRECT("'"&N$1&"'!$V$49:$V$76"),MATCH($A4,INDIRECT("'"&N$1&"'!$A$49:$A$76"),0)),0) -> 0 | P4: =IFERROR(INDEX(INDIRECT("'"&P$1&"'!$V$18:$V$45"),MATCH($A4,INDIRECT("'"&P$1&"'!$A$18:$A$45"),0)),0) -> 0 | Q4: =IFERROR(INDEX(INDIRECT("'"&P$1&"'!$V$49:$V$76"),MATCH($A4,INDIRECT("'"&P$1&"'!$A$49:$A$76"),0)),0) -> 0 | R4: =IFERROR(INDEX(INDIRECT("'"&R$1&"'!$V$18:$V$45"),MATCH($A4,INDIRECT("'"&R$1&"'!$A$18:$A$45"),0)),0) -> 0 | S4: =IFERROR(INDEX(INDIRECT("'"&R$1&"'!$V$49:$V$76"),MATCH($A4,INDIRECT("'"&R$1&"'!$A$49:$A$76"),0)),0) -> 0 | T4: =IFERROR(INDEX(INDIRECT("'"&T$1&"'!$V$18:$V$45"),MATCH($A4,INDIRECT("'"&T$1&"'!$A$18:$A$45"),0)),0) -> 0 | U4: =IFERROR(INDEX(INDIRECT("'"&T$1&"'!$V$49:$V$76"),MATCH($A4,INDIRECT("'"&T$1&"'!$A$49:$A$76"),0)),0) -> 0 | V4: =B4+D4+F4+H4+J4+L4+N4+P4+R4+T4 -> 5 | W4: =C4+E4+G4+I4+K4+M4+O4+Q4+S4+U4 -> 0 | X4: =IF(V4=0,"—",ROUND(W4/V4,2)) -> 0 | Y4: =IFERROR(INDEX(INDIRECT("'"&B$1&"'!$V$80:$V$107"),MATCH($A4,INDIRECT("'"&B$1&"'!$A$80:$A$107"),0)),0)+IFERROR(INDEX(INDIRECT("'"&D$1&"'!$V$80:$V$107"),MATCH($A4,INDIRECT("'"&D$1&"'!$A$80:$A$107"),0)),0)+IFERROR(INDEX(INDIRECT("'"&F$1&"'!$V$80:$V$107"),MATCH($A4,INDIRECT("'"&F$1&"'!$A$80:$A$107"),0)),0)+IFERROR(INDEX(INDIRECT("'"&H$1&"'!$V$80:$V$107"),MATCH($A4,INDIRECT("'"&H$1&"'!$A$80:$A$107"),0)),0)+IFERROR(INDEX(INDIRECT("'"&J$1&"'!$V$80:$V$107"),MATCH($A4,INDIRECT("'"&J$1&"'!$A$80:$A$107"),0)),0)+IFERROR(INDEX(INDIRECT("'"&L$1&"'!$V$80:$V$107"),MATCH($A4,INDIRECT("'"&L$1&"'!$A$80:$A$107"),0)),0)+IFERROR(INDEX(INDIRECT("'"&N$1&"'!$V$80:$V$107"),MATCH($A4,INDIRECT("'"&N$1&"'!$A$80:$A$107"),0)),0)+IFERROR(INDEX(INDIRECT("'"&P$1&"'!$V$80:$V$107"),MATCH($A4,INDIRECT("'"&P$1&"'!$A$80:$A$107"),0)),0)+IFERROR(INDEX(INDIRECT("'"&R$1&"'!$V$80:$V$107"),MATCH($A4,INDIRECT("'"&R$1&"'!$A$80:$A$107"),0)),0)+IFERROR(INDEX(INDIRECT("'"&T$1&"'!$V$80:$V$107"),MATCH($A4,INDIRECT("'"&T$1&"'!$A$80:$A$107"),0)),0) -> 0
A5: Andy Cowan | B5: =IFERROR(INDEX(INDIRECT("'"&B$1&"'!$V$18:$V$45"),MATCH($A5,INDIRECT("'"&B$1&"'!$A$18:$A$45"),0)),0) -> 3 | C5: =IFERROR(INDEX(INDIRECT("'"&B$1&"'!$V$49:$V$76"),MATCH($A5,INDIRECT("'"&B$1&"'!$A$49:$A$76"),0)),0) -> 1 | D5: =IFERROR(INDEX(INDIRECT("'"&D$1&"'!$V$18:$V$45"),MATCH($A5,INDIRECT("'"&D$1&"'!$A$18:$A$45"),0)),0) -> 6 | E5: =IFERROR(INDEX(INDIRECT("'"&D$1&"'!$V$49:$V$76"),MATCH($A5,INDIRECT("'"&D$1&"'!$A$49:$A$76"),0)),0) -> 0 | F5: =IFERROR(INDEX(INDIRECT("'"&F$1&"'!$V$18:$V$45"),MATCH($A5,INDIRECT("'"&F$1&"'!$A$18:$A$45"),0)),0) -> 10 | G5: =IFERROR(INDEX(INDIRECT("'"&F$1&"'!$V$49:$V$76"),MATCH($A5,INDIRECT("'"&F$1&"'!$A$49:$A$76"),0)),0) -> 1 | H5: =IFERROR(INDEX(INDIRECT("'"&H$1&"'!$V$18:$V$45"),MATCH($A5,INDIRECT("'"&H$1&"'!$A$18:$A$45"),0)),0) -> 9 | I5: =IFERROR(INDEX(INDIRECT("'"&H$1&"'!$V$49:$V$76"),MATCH($A5,INDIRECT("'"&H$1&"'!$A$49:$A$76"),0)),0) -> 2 | J5: =IFERROR(INDEX(INDIRECT("'"&J$1&"'!$V$18:$V$45"),MATCH($A5,INDIRECT("'"&J$1&"'!$A$18:$A$45"),0)),0) -> 8 | K5: =IFERROR(INDEX(INDIRECT("'"&J$1&"'!$V$49:$V$76"),MATCH($A5,INDIRECT("'"&J$1&"'!$A$49:$A$76"),0)),0) -> 1 | L5: =IFERROR(INDEX(INDIRECT("'"&L$1&"'!$V$18:$V$45"),MATCH($A5,INDIRECT("'"&L$1&"'!$A$18:$A$45"),0)),0) -> 0 | M5: =IFERROR(INDEX(INDIRECT("'"&L$1&"'!$V$49:$V$76"),MATCH($A5,INDIRECT("'"&L$1&"'!$A$49:$A$76"),0)),0) -> 0 | N5: =IFERROR(INDEX(INDIRECT("'"&N$1&"'!$V$18:$V$45"),MATCH($A5,INDIRECT("'"&N$1&"'!$A$18:$A$45"),0)),0) -> 0 | O5: =IFERROR(INDEX(INDIRECT("'"&N$1&"'!$V$49:$V$76"),MATCH($A5,INDIRECT("'"&N$1&"'!$A$49:$A$76"),0)),0) -> 0 | P5: =IFERROR(INDEX(INDIRECT("'"&P$1&"'!$V$18:$V$45"),MATCH($A5,INDIRECT("'"&P$1&"'!$A$18:$A$45"),0)),0) -> 0 | Q5: =IFERROR(INDEX(INDIRECT("'"&P$1&"'!$V$49:$V$76"),MATCH($A5,INDIRECT("'"&P$1&"'!$A$49:$A$76"),0)),0) -> 0 | R5: =IFERROR(INDEX(INDIRECT("'"&R$1&"'!$V$18:$V$45"),MATCH($A5,INDIRECT("'"&R$1&"'!$A$18:$A$45"),0)),0) -> 0 | S5: =IFERROR(INDEX(INDIRECT("'"&R$1&"'!$V$49:$V$76"),MATCH($A5,INDIRECT("'"&R$1&"'!$A$49:$A$76"),0)),0) -> 0 | T5: =IFERROR(INDEX(INDIRECT("'"&T$1&"'!$V$18:$V$45"),MATCH($A5,INDIRECT("'"&T$1&"'!$A$18:$A$45"),0)),0) -> 0 | U5: =IFERROR(INDEX(INDIRECT("'"&T$1&"'!$V$49:$V$76"),MATCH($A5,INDIRECT("'"&T$1&"'!$A$49:$A$76"),0)),0) -> 0 | V5: =B5+D5+F5+H5+J5+L5+N5+P5+R5+T5 -> 36 | W5: =C5+E5+G5+I5+K5+M5+O5+Q5+S5+U5 -> 5 | X5: =IF(V5=0,"—",ROUND(W5/V5,2)) -> 0.14 | Y5: =IFERROR(INDEX(INDIRECT("'"&B$1&"'!$V$80:$V$107"),MATCH($A5,INDIRECT("'"&B$1&"'!$A$80:$A$107"),0)),0)+IFERROR(INDEX(INDIRECT("'"&D$1&"'!$V$80:$V$107"),MATCH($A5,INDIRECT("'"&D$1&"'!$A$80:$A$107"),0)),0)+IFERROR(INDEX(INDIRECT("'"&F$1&"'!$V$80:$V$107"),MATCH($A5,INDIRECT("'"&F$1&"'!$A$80:$A$107"),0)),0)+IFERROR(INDEX(INDIRECT("'"&H$1&"'!$V$80:$V$107"),MATCH($A5,INDIRECT("'"&H$1&"'!$A$80:$A$107"),0)),0)+IFERROR(INDEX(INDIRECT("'"&J$1&"'!$V$80:$V$107"),MATCH($A5,INDIRECT("'"&J$1&"'!$A$80:$A$107"),0)),0)+IFERROR(INDEX(INDIRECT("'"&L$1&"'!$V$80:$V$107"),MATCH($A5,INDIRECT("'"&L$1&"'!$A$80:$A$107"),0)),0)+IFERROR(INDEX(INDIRECT("'"&N$1&"'!$V$80:$V$107"),MATCH($A5,INDIRECT("'"&N$1&"'!$A$80:$A$107"),0)),0)+IFERROR(INDEX(INDIRECT("'"&P$1&"'!$V$80:$V$107"),MATCH($A5,INDIRECT("'"&P$1&"'!$A$80:$A$107"),0)),0)+IFERROR(INDEX(INDIRECT("'"&R$1&"'!$V$80:$V$107"),MATCH($A5,INDIRECT("'"&R$1&"'!$A$80:$A$107"),0)),0)+IFERROR(INDEX(INDIRECT("'"&T$1&"'!$V$80:$V$107"),MATCH($A5,INDIRECT("'"&T$1&"'!$A$80:$A$107"),0)),0) -> 1
A6: Ben Merrett | B6: =IFERROR(INDEX(INDIRECT("'"&B$1&"'!$V$18:$V$45"),MATCH($A6,INDIRECT("'"&B$1&"'!$A$18:$A$45"),0)),0) -> 5 | C6: =IFERROR(INDEX(INDIRECT("'"&B$1&"'!$V$49:$V$76"),MATCH($A6,INDIRECT("'"&B$1&"'!$A$49:$A$76"),0)),0) -> 1 | D6: =IFERROR(INDEX(INDIRECT("'"&D$1&"'!$V$18:$V$45"),MATCH($A6,INDIRECT("'"&D$1&"'!$A$18:$A$45"),0)),0) -> 4 | E6: =IFERROR(INDEX(INDIRECT("'"&D$1&"'!$V$49:$V$76"),MATCH($A6,INDIRECT("'"&D$1&"'!$A$49:$A$76"),0)),0) -> 0 | F6: =IFERROR(INDEX(INDIRECT("'"&F$1&"'!$V$18:$V$45"),MATCH($A6,INDIRECT("'"&F$1&"'!$A$18:$A$45"),0)),0) -> 8 | G6: =IFERROR(INDEX(INDIRECT("'"&F$1&"'!$V$49:$V$76"),MATCH($A6,INDIRECT("'"&F$1&"'!$A$49:$A$76"),0)),0) -> 2 | H6: =IFERROR(INDEX(INDIRECT("'"&H$1&"'!$V$18:$V$45"),MATCH($A6,INDIRECT("'"&H$1&"'!$A$18:$A$45"),0)),0) -> 8 | I6: =IFERROR(INDEX(INDIRECT("'"&H$1&"'!$V$49:$V$76"),MATCH($A6,INDIRECT("'"&H$1&"'!$A$49:$A$76"),0)),0) -> 0 | J6: =IFERROR(INDEX(INDIRECT("'"&J$1&"'!$V$18:$V$45"),MATCH($A6,INDIRECT("'"&J$1&"'!$A$18:$A$45"),0)),0) -> 1 | K6: =IFERROR(INDEX(INDIRECT("'"&J$1&"'!$V$49:$V$76"),MATCH($A6,INDIRECT("'"&J$1&"'!$A$49:$A$76"),0)),0) -> 0 | L6: =IFERROR(INDEX(INDIRECT("'"&L$1&"'!$V$18:$V$45"),MATCH($A6,INDIRECT("'"&L$1&"'!$A$18:$A$45"),0)),0) -> 6 | M6: =IFERROR(INDEX(INDIRECT("'"&L$1&"'!$V$49:$V$76"),MATCH($A6,INDIRECT("'"&L$1&"'!$A$49:$A$76"),0)),0) -> 1 | N6: =IFERROR(INDEX(INDIRECT("'"&N$1&"'!$V$18:$V$45"),MATCH($A6,INDIRECT("'"&N$1&"'!$A$18:$A$45"),0)),0) -> 6 | O6: =IFERROR(INDEX(INDIRECT("'"&N$1&"'!$V$49:$V$76"),MATCH($A6,INDIRECT("'"&N$1&"'!$A$49:$A$76"),0)),0) -> 2 | P6: =IFERROR(INDEX(INDIRECT("'"&P$1&"'!$V$18:$V$45"),MATCH($A6,INDIRECT("'"&P$1&"'!$A$18:$A$45"),0)),0) -> 1 | Q6: =IFERROR(INDEX(INDIRECT("'"&P$1&"'!$V$49:$V$76"),MATCH($A6,INDIRECT("'"&P$1&"'!$A$49:$A$76"),0)),0) -> 0 | R6: =IFERROR(INDEX(INDIRECT("'"&R$1&"'!$V$18:$V$45"),MATCH($A6,INDIRECT("'"&R$1&"'!$A$18:$A$45"),0)),0) -> 0 | S6: =IFERROR(INDEX(INDIRECT("'"&R$1&"'!$V$49:$V$76"),MATCH($A6,INDIRECT("'"&R$1&"'!$A$49:$A$76"),0)),0) -> 0 | T6: =IFERROR(INDEX(INDIRECT("'"&T$1&"'!$V$18:$V$45"),MATCH($A6,INDIRECT("'"&T$1&"'!$A$18:$A$45"),0)),0) -> 0 | U6: =IFERROR(INDEX(INDIRECT("'"&T$1&"'!$V$49:$V$76"),MATCH($A6,INDIRECT("'"&T$1&"'!$A$49:$A$76"),0)),0) -> 0 | V6: =B6+D6+F6+H6+J6+L6+N6+P6+R6+T6 -> 39 | W6: =C6+E6+G6+I6+K6+M6+O6+Q6+S6+U6 -> 6 | X6: =IF(V6=0,"—",ROUND(W6/V6,2)) -> 0.15 | Y6: =IFERROR(INDEX(INDIRECT("'"&B$1&"'!$V$80:$V$107"),MATCH($A6,INDIRECT("'"&B$1&"'!$A$80:$A$107"),0)),0)+IFERROR(INDEX(INDIRECT("'"&D$1&"'!$V$80:$V$107"),MATCH($A6,INDIRECT("'"&D$1&"'!$A$80:$A$107"),0)),0)+IFERROR(INDEX(INDIRECT("'"&F$1&"'!$V$80:$V$107"),MATCH($A6,INDIRECT("'"&F$1&"'!$A$80:$A$107"),0)),0)+IFERROR(INDEX(INDIRECT("'"&H$1&"'!$V$80:$V$107"),MATCH($A6,INDIRECT("'"&H$1&"'!$A$80:$A$107"),0)),0)+IFERROR(INDEX(INDIRECT("'"&J$1&"'!$V$80:$V$107"),MATCH($A6,INDIRECT("'"&J$1&"'!$A$80:$A$107"),0)),0)+IFERROR(INDEX(INDIRECT("'"&L$1&"'!$V$80:$V$107"),MATCH($A6,INDIRECT("'"&L$1&"'!$A$80:$A$107"),0)),0)+IFERROR(INDEX(INDIRECT("'"&N$1&"'!$V$80:$V$107"),MATCH($A6,INDIRECT("'"&N$1&"'!$A$80:$A$107"),0)),0)+IFERROR(INDEX(INDIRECT("'"&P$1&"'!$V$80:$V$107"),MATCH($A6,INDIRECT("'"&P$1&"'!$A$80:$A$107"),0)),0)+IFERROR(INDEX(INDIRECT("'"&R$1&"'!$V$80:$V$107"),MATCH($A6,INDIRECT("'"&R$1&"'!$A$80:$A$107"),0)),0)+IFERROR(INDEX(INDIRECT("'"&T$1&"'!$V$80:$V$107"),MATCH($A6,INDIRECT("'"&T$1&"'!$A$80:$A$107"),0)),0) -> 2
A7: Callum McCarthy | B7: =IFERROR(INDEX(INDIRECT("'"&B$1&"'!$V$18:$V$45"),MATCH($A7,INDIRECT("'"&B$1&"'!$A$18:$A$45"),0)),0) -> 3 | C7: =IFERROR(INDEX(INDIRECT("'"&B$1&"'!$V$49:$V$76"),MATCH($A7,INDIRECT("'"&B$1&"'!$A$49:$A$76"),0)),0) -> 2 | D7: =IFERROR(INDEX(INDIRECT("'"&D$1&"'!$V$18:$V$45"),MATCH($A7,INDIRECT("'"&D$1&"'!$A$18:$A$45"),0)),0) -> 2 | E7: =IFERROR(INDEX(INDIRECT("'"&D$1&"'!$V$49:$V$76"),MATCH($A7,INDIRECT("'"&D$1&"'!$A$49:$A$76"),0)),0) -> 0 | F7: =IFERROR(INDEX(INDIRECT("'"&F$1&"'!$V$18:$V$45"),MATCH($A7,INDIRECT("'"&F$1&"'!$A$18:$A$45"),0)),0) -> 7 | G7: =IFERROR(INDEX(INDIRECT("'"&F$1&"'!$V$49:$V$76"),MATCH($A7,INDIRECT("'"&F$1&"'!$A$49:$A$76"),0)),0) -> 2 | H7: =IFERROR(INDEX(INDIRECT("'"&H$1&"'!$V$18:$V$45"),MATCH($A7,INDIRECT("'"&H$1&"'!$A$18:$A$45"),0)),0) -> 6 | I7: =IFERROR(INDEX(INDIRECT("'"&H$1&"'!$V$49:$V$76"),MATCH($A7,INDIRECT("'"&H$1&"'!$A$49:$A$76"),0)),0) -> 2 | J7: =IFERROR(INDEX(INDIRECT("'"&J$1&"'!$V$18:$V$45"),MATCH($A7,INDIRECT("'"&J$1&"'!$A$18:$A$45"),0)),0) -> 0 | K7: =IFERROR(INDEX(INDIRECT("'"&J$1&"'!$V$49:$V$76"),MATCH($A7,INDIRECT("'"&J$1&"'!$A$49:$A$76"),0)),0) -> 0 | L7: =IFERROR(INDEX(INDIRECT("'"&L$1&"'!$V$18:$V$45"),MATCH($A7,INDIRECT("'"&L$1&"'!$A$18:$A$45"),0)),0) -> 0 | M7: =IFERROR(INDEX(INDIRECT("'"&L$1&"'!$V$49:$V$76"),MATCH($A7,INDIRECT("'"&L$1&"'!$A$49:$A$76"),0)),0) -> 0 | N7: =IFERROR(INDEX(INDIRECT("'"&N$1&"'!$V$18:$V$45"),MATCH($A7,INDIRECT("'"&N$1&"'!$A$18:$A$45"),0)),0) -> 0 | O7: =IFERROR(INDEX(INDIRECT("'"&N$1&"'!$V$49:$V$76"),MATCH($A7,INDIRECT("'"&N$1&"'!$A$49:$A$76"),0)),0) -> 0 | P7: =IFERROR(INDEX(INDIRECT("'"&P$1&"'!$V$18:$V$45"),MATCH($A7,INDIRECT("'"&P$1&"'!$A$18:$A$45"),0)),0) -> 0 | Q7: =IFERROR(INDEX(INDIRECT("'"&P$1&"'!$V$49:$V$76"),MATCH($A7,INDIRECT("'"&P$1&"'!$A$49:$A$76"),0)),0) -> 0 | R7: =IFERROR(INDEX(INDIRECT("'"&R$1&"'!$V$18:$V$45"),MATCH($A7,INDIRECT("'"&R$1&"'!$A$18:$A$45"),0)),0) -> 0 | S7: =IFERROR(INDEX(INDIRECT("'"&R$1&"'!$V$49:$V$76"),MATCH($A7,INDIRECT("'"&R$1&"'!$A$49:$A$76"),0)),0) -> 0 | T7: =IFERROR(INDEX(INDIRECT("'"&T$1&"'!$V$18:$V$45"),MATCH($A7,INDIRECT("'"&T$1&"'!$A$18:$A$45"),0)),0) -> 0 | U7: =IFERROR(INDEX(INDIRECT("'"&T$1&"'!$V$49:$V$76"),MATCH($A7,INDIRECT("'"&T$1&"'!$A$49:$A$76"),0)),0) -> 0 | V7: =B7+D7+F7+H7+J7+L7+N7+P7+R7+T7 -> 18 | W7: =C7+E7+G7+I7+K7+M7+O7+Q7+S7+U7 -> 6 | X7: =IF(V7=0,"—",ROUND(W7/V7,2)) -> 0.33 | Y7: =IFERROR(INDEX(INDIRECT("'"&B$1&"'!$V$80:$V$107"),MATCH($A7,INDIRECT("'"&B$1&"'!$A$80:$A$107"),0)),0)+IFERROR(INDEX(INDIRECT("'"&D$1&"'!$V$80:$V$107"),MATCH($A7,INDIRECT("'"&D$1&"'!$A$80:$A$107"),0)),0)+IFERROR(INDEX(INDIRECT("'"&F$1&"'!$V$80:$V$107"),MATCH($A7,INDIRECT("'"&F$1&"'!$A$80:$A$107"),0)),0)+IFERROR(INDEX(INDIRECT("'"&H$1&"'!$V$80:$V$107"),MATCH($A7,INDIRECT("'"&H$1&"'!$A$80:$A$107"),0)),0)+IFERROR(INDEX(INDIRECT("'"&J$1&"'!$V$80:$V$107"),MATCH($A7,INDIRECT("'"&J$1&"'!$A$80:$A$107"),0)),0)+IFERROR(INDEX(INDIRECT("'"&L$1&"'!$V$80:$V$107"),MATCH($A7,INDIRECT("'"&L$1&"'!$A$80:$A$107"),0)),0)+IFERROR(INDEX(INDIRECT("'"&N$1&"'!$V$80:$V$107"),MATCH($A7,INDIRECT("'"&N$1&"'!$A$80:$A$107"),0)),0)+IFERROR(INDEX(INDIRECT("'"&P$1&"'!$V$80:$V$107"),MATCH($A7,INDIRECT("'"&P$1&"'!$A$80:$A$107"),0)),0)+IFERROR(INDEX(INDIRECT("'"&R$1&"'!$V$80:$V$107"),MATCH($A7,INDIRECT("'"&R$1&"'!$A$80:$A$107"),0)),0)+IFERROR(INDEX(INDIRECT("'"&T$1&"'!$V$80:$V$107"),MATCH($A7,INDIRECT("'"&T$1&"'!$A$80:$A$107"),0)),0) -> 0
A8: Cecil Watson | B8: =IFERROR(INDEX(INDIRECT("'"&B$1&"'!$V$18:$V$45"),MATCH($A8,INDIRECT("'"&B$1&"'!$A$18:$A$45"),0)),0) -> 2 | C8: =IFERROR(INDEX(INDIRECT("'"&B$1&"'!$V$49:$V$76"),MATCH($A8,INDIRECT("'"&B$1&"'!$A$49:$A$76"),0)),0) -> 0 | D8: =IFERROR(INDEX(INDIRECT("'"&D$1&"'!$V$18:$V$45"),MATCH($A8,INDIRECT("'"&D$1&"'!$A$18:$A$45"),0)),0) -> 0 | E8: =IFERROR(INDEX(INDIRECT("'"&D$1&"'!$V$49:$V$76"),MATCH($A8,INDIRECT("'"&D$1&"'!$A$49:$A$76"),0)),0) -> 0 | F8: =IFERROR(INDEX(INDIRECT("'"&F$1&"'!$V$18:$V$45"),MATCH($A8,INDIRECT("'"&F$1&"'!$A$18:$A$45"),0)),0) -> 1 | G8: =IFERROR(INDEX(INDIRECT("'"&F$1&"'!$V$49:$V$76"),MATCH($A8,INDIRECT("'"&F$1&"'!$A$49:$A$76"),0)),0) -> 0 | H8: =IFERROR(INDEX(INDIRECT("'"&H$1&"'!$V$18:$V$45"),MATCH($A8,INDIRECT("'"&H$1&"'!$A$18:$A$45"),0)),0) -> 1 | I8: =IFERROR(INDEX(INDIRECT("'"&H$1&"'!$V$49:$V$76"),MATCH($A8,INDIRECT("'"&H$1&"'!$A$49:$A$76"),0)),0) -> 0 | J8: =IFERROR(INDEX(INDIRECT("'"&J$1&"'!$V$18:$V$45"),MATCH($A8,INDIRECT("'"&J$1&"'!$A$18:$A$45"),0)),0) -> 1 | K8: =IFERROR(INDEX(INDIRECT("'"&J$1&"'!$V$49:$V$76"),MATCH($A8,INDIRECT("'"&J$1&"'!$A$49:$A$76"),0)),0) -> 0 | L8: =IFERROR(INDEX(INDIRECT("'"&L$1&"'!$V$18:$V$45"),MATCH($A8,INDIRECT("'"&L$1&"'!$A$18:$A$45"),0)),0) -> 0 | M8: =IFERROR(INDEX(INDIRECT("'"&L$1&"'!$V$49:$V$76"),MATCH($A8,INDIRECT("'"&L$1&"'!$A$49:$A$76"),0)),0) -> 0 | N8: =IFERROR(INDEX(INDIRECT("'"&N$1&"'!$V$18:$V$45"),MATCH($A8,INDIRECT("'"&N$1&"'!$A$18:$A$45"),0)),0) -> 0 | O8: =IFERROR(INDEX(INDIRECT("'"&N$1&"'!$V$49:$V$76"),MATCH($A8,INDIRECT("'"&N$1&"'!$A$49:$A$76"),0)),0) -> 0 | P8: =IFERROR(INDEX(INDIRECT("'"&P$1&"'!$V$18:$V$45"),MATCH($A8,INDIRECT("'"&P$1&"'!$A$18:$A$45"),0)),0) -> 0 | Q8: =IFERROR(INDEX(INDIRECT("'"&P$1&"'!$V$49:$V$76"),MATCH($A8,INDIRECT("'"&P$1&"'!$A$49:$A$76"),0)),0) -> 0 | R8: =IFERROR(INDEX(INDIRECT("'"&R$1&"'!$V$18:$V$45"),MATCH($A8,INDIRECT("'"&R$1&"'!$A$18:$A$45"),0)),0) -> 0 | S8: =IFERROR(INDEX(INDIRECT("'"&R$1&"'!$V$49:$V$76"),MATCH($A8,INDIRECT("'"&R$1&"'!$A$49:$A$76"),0)),0) -> 0 | T8: =IFERROR(INDEX(INDIRECT("'"&T$1&"'!$V$18:$V$45"),MATCH($A8,INDIRECT("'"&T$1&"'!$A$18:$A$45"),0)),0) -> 0 | U8: =IFERROR(INDEX(INDIRECT("'"&T$1&"'!$V$49:$V$76"),MATCH($A8,INDIRECT("'"&T$1&"'!$A$49:$A$76"),0)),0) -> 0 | V8: =B8+D8+F8+H8+J8+L8+N8+P8+R8+T8 -> 5 | W8: =C8+E8+G8+I8+K8+M8+O8+Q8+S8+U8 -> 0 | X8: =IF(V8=0,"—",ROUND(W8/V8,2)) -> 0 | Y8: =IFERROR(INDEX(INDIRECT("'"&B$1&"'!$V$80:$V$107"),MATCH($A8,INDIRECT("'"&B$1&"'!$A$80:$A$107"),0)),0)+IFERROR(INDEX(INDIRECT("'"&D$1&"'!$V$80:$V$107"),MATCH($A8,INDIRECT("'"&D$1&"'!$A$80:$A$107"),0)),0)+IFERROR(INDEX(INDIRECT("'"&F$1&"'!$V$80:$V$107"),MATCH($A8,INDIRECT("'"&F$1&"'!$A$80:$A$107"),0)),0)+IFERROR(INDEX(INDIRECT("'"&H$1&"'!$V$80:$V$107"),MATCH($A8,INDIRECT("'"&H$1&"'!$A$80:$A$107"),0)),0)+IFERROR(INDEX(INDIRECT("'"&J$1&"'!$V$80:$V$107"),MATCH($A8,INDIRECT("'"&J$1&"'!$A$80:$A$107"),0)),0)+IFERROR(INDEX(INDIRECT("'"&L$1&"'!$V$80:$V$107"),MATCH($A8,INDIRECT("'"&L$1&"'!$A$80:$A$107"),0)),0)+IFERROR(INDEX(INDIRECT("'"&N$1&"'!$V$80:$V$107"),MATCH($A8,INDIRECT("'"&N$1&"'!$A$80:$A$107"),0)),0)+IFERROR(INDEX(INDIRECT("'"&P$1&"'!$V$80:$V$107"),MATCH($A8,INDIRECT("'"&P$1&"'!$A$80:$A$107"),0)),0)+IFERROR(INDEX(INDIRECT("'"&R$1&"'!$V$80:$V$107"),MATCH($A8,INDIRECT("'"&R$1&"'!$A$80:$A$107"),0)),0)+IFERROR(INDEX(INDIRECT("'"&T$1&"'!$V$80:$V$107"),MATCH($A8,INDIRECT("'"&T$1&"'!$A$80:$A$107"),0)),0) -> 1
A9: Conall Templeman | B9: =IFERROR(INDEX(INDIRECT("'"&B$1&"'!$V$18:$V$45"),MATCH($A9,INDIRECT("'"&B$1&"'!$A$18:$A$45"),0)),0) -> 0 | C9: =IFERROR(INDEX(INDIRECT("'"&B$1&"'!$V$49:$V$76"),MATCH($A9,INDIRECT("'"&B$1&"'!$A$49:$A$76"),0)),0) -> 0 | D9: =IFERROR(INDEX(INDIRECT("'"&D$1&"'!$V$18:$V$45"),MATCH($A9,INDIRECT("'"&D$1&"'!$A$18:$A$45"),0)),0) -> 0 | E9: =IFERROR(INDEX(INDIRECT("'"&D$1&"'!$V$49:$V$76"),MATCH($A9,INDIRECT("'"&D$1&"'!$A$49:$A$76"),0)),0) -> 0 | F9: =IFERROR(INDEX(INDIRECT("'"&F$1&"'!$V$18:$V$45"),MATCH($A9,INDIRECT("'"&F$1&"'!$A$18:$A$45"),0)),0) -> 0 | G9: =IFERROR(INDEX(INDIRECT("'"&F$1&"'!$V$49:$V$76"),MATCH($A9,INDIRECT("'"&F$1&"'!$A$49:$A$76"),0)),0) -> 0 | H9: =IFERROR(INDEX(INDIRECT("'"&H$1&"'!$V$18:$V$45"),MATCH($A9,INDIRECT("'"&H$1&"'!$A$18:$A$45"),0)),0) -> 0 | I9: =IFERROR(INDEX(INDIRECT("'"&H$1&"'!$V$49:$V$76"),MATCH($A9,INDIRECT("'"&H$1&"'!$A$49:$A$76"),0)),0) -> 0 | J9: =IFERROR(INDEX(INDIRECT("'"&J$1&"'!$V$18:$V$45"),MATCH($A9,INDIRECT("'"&J$1&"'!$A$18:$A$45"),0)),0) -> 0 | K9: =IFERROR(INDEX(INDIRECT("'"&J$1&"'!$V$49:$V$76"),MATCH($A9,INDIRECT("'"&J$1&"'!$A$49:$A$76"),0)),0) -> 0 | L9: =IFERROR(INDEX(INDIRECT("'"&L$1&"'!$V$18:$V$45"),MATCH($A9,INDIRECT("'"&L$1&"'!$A$18:$A$45"),0)),0) -> 3 | M9: =IFERROR(INDEX(INDIRECT("'"&L$1&"'!$V$49:$V$76"),MATCH($A9,INDIRECT("'"&L$1&"'!$A$49:$A$76"),0)),0) -> 0 | N9: =IFERROR(INDEX(INDIRECT("'"&N$1&"'!$V$18:$V$45"),MATCH($A9,INDIRECT("'"&N$1&"'!$A$18:$A$45"),0)),0) -> 8 | O9: =IFERROR(INDEX(INDIRECT("'"&N$1&"'!$V$49:$V$76"),MATCH($A9,INDIRECT("'"&N$1&"'!$A$49:$A$76"),0)),0) -> 3 | P9: =IFERROR(INDEX(INDIRECT("'"&P$1&"'!$V$18:$V$45"),MATCH($A9,INDIRECT("'"&P$1&"'!$A$18:$A$45"),0)),0) -> 0 | Q9: =IFERROR(INDEX(INDIRECT("'"&P$1&"'!$V$49:$V$76"),MATCH($A9,INDIRECT("'"&P$1&"'!$A$49:$A$76"),0)),0) -> 0 | R9: =IFERROR(INDEX(INDIRECT("'"&R$1&"'!$V$18:$V$45"),MATCH($A9,INDIRECT("'"&R$1&"'!$A$18:$A$45"),0)),0) -> 0 | S9: =IFERROR(INDEX(INDIRECT("'"&R$1&"'!$V$49:$V$76"),MATCH($A9,INDIRECT("'"&R$1&"'!$A$49:$A$76"),0)),0) -> 0 | T9: =IFERROR(INDEX(INDIRECT("'"&T$1&"'!$V$18:$V$45"),MATCH($A9,INDIRECT("'"&T$1&"'!$A$18:$A$45"),0)),0) -> 0 | U9: =IFERROR(INDEX(INDIRECT("'"&T$1&"'!$V$49:$V$76"),MATCH($A9,INDIRECT("'"&T$1&"'!$A$49:$A$76"),0)),0) -> 0 | V9: =B9+D9+F9+H9+J9+L9+N9+P9+R9+T9 -> 11 | W9: =C9+E9+G9+I9+K9+M9+O9+Q9+S9+U9 -> 3 | X9: =IF(V9=0,"—",ROUND(W9/V9,2)) -> 0.27 | Y9: =IFERROR(INDEX(INDIRECT("'"&B$1&"'!$V$80:$V$107"),MATCH($A9,INDIRECT("'"&B$1&"'!$A$80:$A$107"),0)),0)+IFERROR(INDEX(INDIRECT("'"&D$1&"'!$V$80:$V$107"),MATCH($A9,INDIRECT("'"&D$1&"'!$A$80:$A$107"),0)),0)+IFERROR(INDEX(INDIRECT("'"&F$1&"'!$V$80:$V$107"),MATCH($A9,INDIRECT("'"&F$1&"'!$A$80:$A$107"),0)),0)+IFERROR(INDEX(INDIRECT("'"&H$1&"'!$V$80:$V$107"),MATCH($A9,INDIRECT("'"&H$1&"'!$A$80:$A$107"),0)),0)+IFERROR(INDEX(INDIRECT("'"&J$1&"'!$V$80:$V$107"),MATCH($A9,INDIRECT("'"&J$1&"'!$A$80:$A$107"),0)),0)+IFERROR(INDEX(INDIRECT("'"&L$1&"'!$V$80:$V$107"),MATCH($A9,INDIRECT("'"&L$1&"'!$A$80:$A$107"),0)),0)+IFERROR(INDEX(INDIRECT("'"&N$1&"'!$V$80:$V$107"),MATCH($A9,INDIRECT("'"&N$1&"'!$A$80:$A$107"),0)),0)+IFERROR(INDEX(INDIRECT("'"&P$1&"'!$V$80:$V$107"),MATCH($A9,INDIRECT("'"&P$1&"'!$A$80:$A$107"),0)),0)+IFERROR(INDEX(INDIRECT("'"&R$1&"'!$V$80:$V$107"),MATCH($A9,INDIRECT("'"&R$1&"'!$A$80:$A$107"),0)),0)+IFERROR(INDEX(INDIRECT("'"&T$1&"'!$V$80:$V$107"),MATCH($A9,INDIRECT("'"&T$1&"'!$A$80:$A$107"),0)),0) -> 0
A10: Eddie Ringer | B10: =IFERROR(INDEX(INDIRECT("'"&B$1&"'!$V$18:$V$45"),MATCH($A10,INDIRECT("'"&B$1&"'!$A$18:$A$45"),0)),0) -> 0 | C10: =IFERROR(INDEX(INDIRECT("'"&B$1&"'!$V$49:$V$76"),MATCH($A10,INDIRECT("'"&B$1&"'!$A$49:$A$76"),0)),0) -> 0 | D10: =IFERROR(INDEX(INDIRECT("'"&D$1&"'!$V$18:$V$45"),MATCH($A10,INDIRECT("'"&D$1&"'!$A$18:$A$45"),0)),0) -> 0 | E10: =IFERROR(INDEX(INDIRECT("'"&D$1&"'!$V$49:$V$76"),MATCH($A10,INDIRECT("'"&D$1&"'!$A$49:$A$76"),0)),0) -> 0 | F10: =IFERROR(INDEX(INDIRECT("'"&F$1&"'!$V$18:$V$45"),MATCH($A10,INDIRECT("'"&F$1&"'!$A$18:$A$45"),0)),0) -> 0 | G10: =IFERROR(INDEX(INDIRECT("'"&F$1&"'!$V$49:$V$76"),MATCH($A10,INDIRECT("'"&F$1&"'!$A$49:$A$76"),0)),0) -> 0 | H10: =IFERROR(INDEX(INDIRECT("'"&H$1&"'!$V$18:$V$45"),MATCH($A10,INDIRECT("'"&H$1&"'!$A$18:$A$45"),0)),0) -> 0 | I10: =IFERROR(INDEX(INDIRECT("'"&H$1&"'!$V$49:$V$76"),MATCH($A10,INDIRECT("'"&H$1&"'!$A$49:$A$76"),0)),0) -> 0 | J10: =IFERROR(INDEX(INDIRECT("'"&J$1&"'!$V$18:$V$45"),MATCH($A10,INDIRECT("'"&J$1&"'!$A$18:$A$45"),0)),0) -> 1 | K10: =IFERROR(INDEX(INDIRECT("'"&J$1&"'!$V$49:$V$76"),MATCH($A10,INDIRECT("'"&J$1&"'!$A$49:$A$76"),0)),0) -> 4 | L10: =IFERROR(INDEX(INDIRECT("'"&L$1&"'!$V$18:$V$45"),MATCH($A10,INDIRECT("'"&L$1&"'!$A$18:$A$45"),0)),0) -> 1 | M10: =IFERROR(INDEX(INDIRECT("'"&L$1&"'!$V$49:$V$76"),MATCH($A10,INDIRECT("'"&L$1&"'!$A$49:$A$76"),0)),0) -> 2 | N10: =IFERROR(INDEX(INDIRECT("'"&N$1&"'!$V$18:$V$45"),MATCH($A10,INDIRECT("'"&N$1&"'!$A$18:$A$45"),0)),0) -> 1 | O10: =IFERROR(INDEX(INDIRECT("'"&N$1&"'!$V$49:$V$76"),MATCH($A10,INDIRECT("'"&N$1&"'!$A$49:$A$76"),0)),0) -> 1 | P10: =IFERROR(INDEX(INDIRECT("'"&P$1&"'!$V$18:$V$45"),MATCH($A10,INDIRECT("'"&P$1&"'!$A$18:$A$45"),0)),0) -> 0 | Q10: =IFERROR(INDEX(INDIRECT("'"&P$1&"'!$V$49:$V$76"),MATCH($A10,INDIRECT("'"&P$1&"'!$A$49:$A$76"),0)),0) -> 0 | R10: =IFERROR(INDEX(INDIRECT("'"&R$1&"'!$V$18:$V$45"),MATCH($A10,INDIRECT("'"&R$1&"'!$A$18:$A$45"),0)),0) -> 0 | S10: =IFERROR(INDEX(INDIRECT("'"&R$1&"'!$V$49:$V$76"),MATCH($A10,INDIRECT("'"&R$1&"'!$A$49:$A$76"),0)),0) -> 0 | T10: =IFERROR(INDEX(INDIRECT("'"&T$1&"'!$V$18:$V$45"),MATCH($A10,INDIRECT("'"&T$1&"'!$A$18:$A$45"),0)),0) -> 0 | U10: =IFERROR(INDEX(INDIRECT("'"&T$1&"'!$V$49:$V$76"),MATCH($A10,INDIRECT("'"&T$1&"'!$A$49:$A$76"),0)),0) -> 0 | V10: =B10+D10+F10+H10+J10+L10+N10+P10+R10+T10 -> 3 | W10: =C10+E10+G10+I10+K10+M10+O10+Q10+S10+U10 -> 7 | X10: =IF(V10=0,"—",ROUND(W10/V10,2)) -> 2.33 | Y10: =IFERROR(INDEX(INDIRECT("'"&B$1&"'!$V$80:$V$107"),MATCH($A10,INDIRECT("'"&B$1&"'!$A$80:$A$107"),0)),0)+IFERROR(INDEX(INDIRECT("'"&D$1&"'!$V$80:$V$107"),MATCH($A10,INDIRECT("'"&D$1&"'!$A$80:$A$107"),0)),0)+IFERROR(INDEX(INDIRECT("'"&F$1&"'!$V$80:$V$107"),MATCH($A10,INDIRECT("'"&F$1&"'!$A$80:$A$107"),0)),0)+IFERROR(INDEX(INDIRECT("'"&H$1&"'!$V$80:$V$107"),MATCH($A10,INDIRECT("'"&H$1&"'!$A$80:$A$107"),0)),0)+IFERROR(INDEX(INDIRECT("'"&J$1&"'!$V$80:$V$107"),MATCH($A10,INDIRECT("'"&J$1&"'!$A$80:$A$107"),0)),0)+IFERROR(INDEX(INDIRECT("'"&L$1&"'!$V$80:$V$107"),MATCH($A10,INDIRECT("'"&L$1&"'!$A$80:$A$107"),0)),0)+IFERROR(INDEX(INDIRECT("'"&N$1&"'!$V$80:$V$107"),MATCH($A10,INDIRECT("'"&N$1&"'!$A$80:$A$107"),0)),0)+IFERROR(INDEX(INDIRECT("'"&P$1&"'!$V$80:$V$107"),MATCH($A10,INDIRECT("'"&P$1&"'!$A$80:$A$107"),0)),0)+IFERROR(INDEX(INDIRECT("'"&R$1&"'!$V$80:$V$107"),MATCH($A10,INDIRECT("'"&R$1&"'!$A$80:$A$107"),0)),0)+IFERROR(INDEX(INDIRECT("'"&T$1&"'!$V$80:$V$107"),MATCH($A10,INDIRECT("'"&T$1&"'!$A$80:$A$107"),0)),0) -> 0
A11: Finn Cawley | B11: =IFERROR(INDEX(INDIRECT("'"&B$1&"'!$V$18:$V$45"),MATCH($A11,INDIRECT("'"&B$1&"'!$A$18:$A$45"),0)),0) -> 0 | C11: =IFERROR(INDEX(INDIRECT("'"&B$1&"'!$V$49:$V$76"),MATCH($A11,INDIRECT("'"&B$1&"'!$A$49:$A$76"),0)),0) -> 0 | D11: =IFERROR(INDEX(INDIRECT("'"&D$1&"'!$V$18:$V$45"),MATCH($A11,INDIRECT("'"&D$1&"'!$A$18:$A$45"),0)),0) -> 4 | E11: =IFERROR(INDEX(INDIRECT("'"&D$1&"'!$V$49:$V$76"),MATCH($A11,INDIRECT("'"&D$1&"'!$A$49:$A$76"),0)),0) -> 3 | F11: =IFERROR(INDEX(INDIRECT("'"&F$1&"'!$V$18:$V$45"),MATCH($A11,INDIRECT("'"&F$1&"'!$A$18:$A$45"),0)),0) -> 7 | G11: =IFERROR(INDEX(INDIRECT("'"&F$1&"'!$V$49:$V$76"),MATCH($A11,INDIRECT("'"&F$1&"'!$A$49:$A$76"),0)),0) -> 5 | H11: =IFERROR(INDEX(INDIRECT("'"&H$1&"'!$V$18:$V$45"),MATCH($A11,INDIRECT("'"&H$1&"'!$A$18:$A$45"),0)),0) -> 4 | I11: =IFERROR(INDEX(INDIRECT("'"&H$1&"'!$V$49:$V$76"),MATCH($A11,INDIRECT("'"&H$1&"'!$A$49:$A$76"),0)),0) -> 1 | J11: =IFERROR(INDEX(INDIRECT("'"&J$1&"'!$V$18:$V$45"),MATCH($A11,INDIRECT("'"&J$1&"'!$A$18:$A$45"),0)),0) -> 1 | K11: =IFERROR(INDEX(INDIRECT("'"&J$1&"'!$V$49:$V$76"),MATCH($A11,INDIRECT("'"&J$1&"'!$A$49:$A$76"),0)),0) -> 1 | L11: =IFERROR(INDEX(INDIRECT("'"&L$1&"'!$V$18:$V$45"),MATCH($A11,INDIRECT("'"&L$1&"'!$A$18:$A$45"),0)),0) -> 3 | M11: =IFERROR(INDEX(INDIRECT("'"&L$1&"'!$V$49:$V$76"),MATCH($A11,INDIRECT("'"&L$1&"'!$A$49:$A$76"),0)),0) -> 2 | N11: =IFERROR(INDEX(INDIRECT("'"&N$1&"'!$V$18:$V$45"),MATCH($A11,INDIRECT("'"&N$1&"'!$A$18:$A$45"),0)),0) -> 2 | O11: =IFERROR(INDEX(INDIRECT("'"&N$1&"'!$V$49:$V$76"),MATCH($A11,INDIRECT("'"&N$1&"'!$A$49:$A$76"),0)),0) -> 4 | P11: =IFERROR(INDEX(INDIRECT("'"&P$1&"'!$V$18:$V$45"),MATCH($A11,INDIRECT("'"&P$1&"'!$A$18:$A$45"),0)),0) -> 1 | Q11: =IFERROR(INDEX(INDIRECT("'"&P$1&"'!$V$49:$V$76"),MATCH($A11,INDIRECT("'"&P$1&"'!$A$49:$A$76"),0)),0) -> 2 | R11: =IFERROR(INDEX(INDIRECT("'"&R$1&"'!$V$18:$V$45"),MATCH($A11,INDIRECT("'"&R$1&"'!$A$18:$A$45"),0)),0) -> 0 | S11: =IFERROR(INDEX(INDIRECT("'"&R$1&"'!$V$49:$V$76"),MATCH($A11,INDIRECT("'"&R$1&"'!$A$49:$A$76"),0)),0) -> 0 | T11: =IFERROR(INDEX(INDIRECT("'"&T$1&"'!$V$18:$V$45"),MATCH($A11,INDIRECT("'"&T$1&"'!$A$18:$A$45"),0)),0) -> 0 | U11: =IFERROR(INDEX(INDIRECT("'"&T$1&"'!$V$49:$V$76"),MATCH($A11,INDIRECT("'"&T$1&"'!$A$49:$A$76"),0)),0) -> 0 | V11: =B11+D11+F11+H11+J11+L11+N11+P11+R11+T11 -> 22 | W11: =C11+E11+G11+I11+K11+M11+O11+Q11+S11+U11 -> 18 | X11: =IF(V11=0,"—",ROUND(W11/V11,2)) -> 0.82 | Y11: =IFERROR(INDEX(INDIRECT("'"&B$1&"'!$V$80:$V$107"),MATCH($A11,INDIRECT("'"&B$1&"'!$A$80:$A$107"),0)),0)+IFERROR(INDEX(INDIRECT("'"&D$1&"'!$V$80:$V$107"),MATCH($A11,INDIRECT("'"&D$1&"'!$A$80:$A$107"),0)),0)+IFERROR(INDEX(INDIRECT("'"&F$1&"'!$V$80:$V$107"),MATCH($A11,INDIRECT("'"&F$1&"'!$A$80:$A$107"),0)),0)+IFERROR(INDEX(INDIRECT("'"&H$1&"'!$V$80:$V$107"),MATCH($A11,INDIRECT("'"&H$1&"'!$A$80:$A$107"),0)),0)+IFERROR(INDEX(INDIRECT("'"&J$1&"'!$V$80:$V$107"),MATCH($A11,INDIRECT("'"&J$1&"'!$A$80:$A$107"),0)),0)+IFERROR(INDEX(INDIRECT("'"&L$1&"'!$V$80:$V$107"),MATCH($A11,INDIRECT("'"&L$1&"'!$A$80:$A$107"),0)),0)+IFERROR(INDEX(INDIRECT("'"&N$1&"'!$V$80:$V$107"),MATCH($A11,INDIRECT("'"&N$1&"'!$A$80:$A$107"),0)),0)+IFERROR(INDEX(INDIRECT("'"&P$1&"'!$V$80:$V$107"),MATCH($A11,INDIRECT("'"&P$1&"'!$A$80:$A$107"),0)),0)+IFERROR(INDEX(INDIRECT("'"&R$1&"'!$V$80:$V$107"),MATCH($A11,INDIRECT("'"&R$1&"'!$A$80:$A$107"),0)),0)+IFERROR(INDEX(INDIRECT("'"&T$1&"'!$V$80:$V$107"),MATCH($A11,INDIRECT("'"&T$1&"'!$A$80:$A$107"),0)),0) -> 0
A12: George Barbantan | B12: =IFERROR(INDEX(INDIRECT("'"&B$1&"'!$V$18:$V$45"),MATCH($A12,INDIRECT("'"&B$1&"'!$A$18:$A$45"),0)),0) -> 5 | C12: =IFERROR(INDEX(INDIRECT("'"&B$1&"'!$V$49:$V$76"),MATCH($A12,INDIRECT("'"&B$1&"'!$A$49:$A$76"),0)),0) -> 3 | D12: =IFERROR(INDEX(INDIRECT("'"&D$1&"'!$V$18:$V$45"),MATCH($A12,INDIRECT("'"&D$1&"'!$A$18:$A$45"),0)),0) -> 5 | E12: =IFERROR(INDEX(INDIRECT("'"&D$1&"'!$V$49:$V$76"),MATCH($A12,INDIRECT("'"&D$1&"'!$A$49:$A$76"),0)),0) -> 2 | F12: =IFERROR(INDEX(INDIRECT("'"&F$1&"'!$V$18:$V$45"),MATCH($A12,INDIRECT("'"&F$1&"'!$A$18:$A$45"),0)),0) -> 5 | G12: =IFERROR(INDEX(INDIRECT("'"&F$1&"'!$V$49:$V$76"),MATCH($A12,INDIRECT("'"&F$1&"'!$A$49:$A$76"),0)),0) -> 1 | H12: =IFERROR(INDEX(INDIRECT("'"&H$1&"'!$V$18:$V$45"),MATCH($A12,INDIRECT("'"&H$1&"'!$A$18:$A$45"),0)),0) -> 9 | I12: =IFERROR(INDEX(INDIRECT("'"&H$1&"'!$V$49:$V$76"),MATCH($A12,INDIRECT("'"&H$1&"'!$A$49:$A$76"),0)),0) -> 1 | J12: =IFERROR(INDEX(INDIRECT("'"&J$1&"'!$V$18:$V$45"),MATCH($A12,INDIRECT("'"&J$1&"'!$A$18:$A$45"),0)),0) -> 10 | K12: =IFERROR(INDEX(INDIRECT("'"&J$1&"'!$V$49:$V$76"),MATCH($A12,INDIRECT("'"&J$1&"'!$A$49:$A$76"),0)),0) -> 2 | L12: =IFERROR(INDEX(INDIRECT("'"&L$1&"'!$V$18:$V$45"),MATCH($A12,INDIRECT("'"&L$1&"'!$A$18:$A$45"),0)),0) -> 0 | M12: =IFERROR(INDEX(INDIRECT("'"&L$1&"'!$V$49:$V$76"),MATCH($A12,INDIRECT("'"&L$1&"'!$A$49:$A$76"),0)),0) -> 0 | N12: =IFERROR(INDEX(INDIRECT("'"&N$1&"'!$V$18:$V$45"),MATCH($A12,INDIRECT("'"&N$1&"'!$A$18:$A$45"),0)),0) -> 3 | O12: =IFERROR(INDEX(INDIRECT("'"&N$1&"'!$V$49:$V$76"),MATCH($A12,INDIRECT("'"&N$1&"'!$A$49:$A$76"),0)),0) -> 1 | P12: =IFERROR(INDEX(INDIRECT("'"&P$1&"'!$V$18:$V$45"),MATCH($A12,INDIRECT("'"&P$1&"'!$A$18:$A$45"),0)),0) -> 0 | Q12: =IFERROR(INDEX(INDIRECT("'"&P$1&"'!$V$49:$V$76"),MATCH($A12,INDIRECT("'"&P$1&"'!$A$49:$A$76"),0)),0) -> 0 | R12: =IFERROR(INDEX(INDIRECT("'"&R$1&"'!$V$18:$V$45"),MATCH($A12,INDIRECT("'"&R$1&"'!$A$18:$A$45"),0)),0) -> 0 | S12: =IFERROR(INDEX(INDIRECT("'"&R$1&"'!$V$49:$V$76"),MATCH($A12,INDIRECT("'"&R$1&"'!$A$49:$A$76"),0)),0) -> 0 | T12: =IFERROR(INDEX(INDIRECT("'"&T$1&"'!$V$18:$V$45"),MATCH($A12,INDIRECT("'"&T$1&"'!$A$18:$A$45"),0)),0) -> 0 | U12: =IFERROR(INDEX(INDIRECT("'"&T$1&"'!$V$49:$V$76"),MATCH($A12,INDIRECT("'"&T$1&"'!$A$49:$A$76"),0)),0) -> 0 | V12: =B12+D12+F12+H12+J12+L12+N12+P12+R12+T12 -> 37 | W12: =C12+E12+G12+I12+K12+M12+O12+Q12+S12+U12 -> 10 | X12: =IF(V12=0,"—",ROUND(W12/V12,2)) -> 0.27 | Y12: =IFERROR(INDEX(INDIRECT("'"&B$1&"'!$V$80:$V$107"),MATCH($A12,INDIRECT("'"&B$1&"'!$A$80:$A$107"),0)),0)+IFERROR(INDEX(INDIRECT("'"&D$1&"'!$V$80:$V$107"),MATCH($A12,INDIRECT("'"&D$1&"'!$A$80:$A$107"),0)),0)+IFERROR(INDEX(INDIRECT("'"&F$1&"'!$V$80:$V$107"),MATCH($A12,INDIRECT("'"&F$1&"'!$A$80:$A$107"),0)),0)+IFERROR(INDEX(INDIRECT("'"&H$1&"'!$V$80:$V$107"),MATCH($A12,INDIRECT("'"&H$1&"'!$A$80:$A$107"),0)),0)+IFERROR(INDEX(INDIRECT("'"&J$1&"'!$V$80:$V$107"),MATCH($A12,INDIRECT("'"&J$1&"'!$A$80:$A$107"),0)),0)+IFERROR(INDEX(INDIRECT("'"&L$1&"'!$V$80:$V$107"),MATCH($A12,INDIRECT("'"&L$1&"'!$A$80:$A$107"),0)),0)+IFERROR(INDEX(INDIRECT("'"&N$1&"'!$V$80:$V$107"),MATCH($A12,INDIRECT("'"&N$1&"'!$A$80:$A$107"),0)),0)+IFERROR(INDEX(INDIRECT("'"&P$1&"'!$V$80:$V$107"),MATCH($A12,INDIRECT("'"&P$1&"'!$A$80:$A$107"),0)),0)+IFERROR(INDEX(INDIRECT("'"&R$1&"'!$V$80:$V$107"),MATCH($A12,INDIRECT("'"&R$1&"'!$A$80:$A$107"),0)),0)+IFERROR(INDEX(INDIRECT("'"&T$1&"'!$V$80:$V$107"),MATCH($A12,INDIRECT("'"&T$1&"'!$A$80:$A$107"),0)),0) -> 2
A13: Henry Linklater | B13: =IFERROR(INDEX(INDIRECT("'"&B$1&"'!$V$18:$V$45"),MATCH($A13,INDIRECT("'"&B$1&"'!$A$18:$A$45"),0)),0) -> 8 | C13: =IFERROR(INDEX(INDIRECT("'"&B$1&"'!$V$49:$V$76"),MATCH($A13,INDIRECT("'"&B$1&"'!$A$49:$A$76"),0)),0) -> 0 | D13: =IFERROR(INDEX(INDIRECT("'"&D$1&"'!$V$18:$V$45"),MATCH($A13,INDIRECT("'"&D$1&"'!$A$18:$A$45"),0)),0) -> 6 | E13: =IFERROR(INDEX(INDIRECT("'"&D$1&"'!$V$49:$V$76"),MATCH($A13,INDIRECT("'"&D$1&"'!$A$49:$A$76"),0)),0) -> 0 | F13: =IFERROR(INDEX(INDIRECT("'"&F$1&"'!$V$18:$V$45"),MATCH($A13,INDIRECT("'"&F$1&"'!$A$18:$A$45"),0)),0) -> 2 | G13: =IFERROR(INDEX(INDIRECT("'"&F$1&"'!$V$49:$V$76"),MATCH($A13,INDIRECT("'"&F$1&"'!$A$49:$A$76"),0)),0) -> 0 | H13: =IFERROR(INDEX(INDIRECT("'"&H$1&"'!$V$18:$V$45"),MATCH($A13,INDIRECT("'"&H$1&"'!$A$18:$A$45"),0)),0) -> 0 | I13: =IFERROR(INDEX(INDIRECT("'"&H$1&"'!$V$49:$V$76"),MATCH($A13,INDIRECT("'"&H$1&"'!$A$49:$A$76"),0)),0) -> 0 | J13: =IFERROR(INDEX(INDIRECT("'"&J$1&"'!$V$18:$V$45"),MATCH($A13,INDIRECT("'"&J$1&"'!$A$18:$A$45"),0)),0) -> 1 | K13: =IFERROR(INDEX(INDIRECT("'"&J$1&"'!$V$49:$V$76"),MATCH($A13,INDIRECT("'"&J$1&"'!$A$49:$A$76"),0)),0) -> 0 | L13: =IFERROR(INDEX(INDIRECT("'"&L$1&"'!$V$18:$V$45"),MATCH($A13,INDIRECT("'"&L$1&"'!$A$18:$A$45"),0)),0) -> 0 | M13: =IFERROR(INDEX(INDIRECT("'"&L$1&"'!$V$49:$V$76"),MATCH($A13,INDIRECT("'"&L$1&"'!$A$49:$A$76"),0)),0) -> 0 | N13: =IFERROR(INDEX(INDIRECT("'"&N$1&"'!$V$18:$V$45"),MATCH($A13,INDIRECT("'"&N$1&"'!$A$18:$A$45"),0)),0) -> 0 | O13: =IFERROR(INDEX(INDIRECT("'"&N$1&"'!$V$49:$V$76"),MATCH($A13,INDIRECT("'"&N$1&"'!$A$49:$A$76"),0)),0) -> 0 | P13: =IFERROR(INDEX(INDIRECT("'"&P$1&"'!$V$18:$V$45"),MATCH($A13,INDIRECT("'"&P$1&"'!$A$18:$A$45"),0)),0) -> 0 | Q13: =IFERROR(INDEX(INDIRECT("'"&P$1&"'!$V$49:$V$76"),MATCH($A13,INDIRECT("'"&P$1&"'!$A$49:$A$76"),0)),0) -> 0 | R13: =IFERROR(INDEX(INDIRECT("'"&R$1&"'!$V$18:$V$45"),MATCH($A13,INDIRECT("'"&R$1&"'!$A$18:$A$45"),0)),0) -> 0 | S13: =IFERROR(INDEX(INDIRECT("'"&R$1&"'!$V$49:$V$76"),MATCH($A13,INDIRECT("'"&R$1&"'!$A$49:$A$76"),0)),0) -> 0 | T13: =IFERROR(INDEX(INDIRECT("'"&T$1&"'!$V$18:$V$45"),MATCH($A13,INDIRECT("'"&T$1&"'!$A$18:$A$45"),0)),0) -> 0 | U13: =IFERROR(INDEX(INDIRECT("'"&T$1&"'!$V$49:$V$76"),MATCH($A13,INDIRECT("'"&T$1&"'!$A$49:$A$76"),0)),0) -> 0 | V13: =B13+D13+F13+H13+J13+L13+N13+P13+R13+T13 -> 17 | W13: =C13+E13+G13+I13+K13+M13+O13+Q13+S13+U13 -> 0 | X13: =IF(V13=0,"—",ROUND(W13/V13,2)) -> 0 | Y13: =IFERROR(INDEX(INDIRECT("'"&B$1&"'!$V$80:$V$107"),MATCH($A13,INDIRECT("'"&B$1&"'!$A$80:$A$107"),0)),0)+IFERROR(INDEX(INDIRECT("'"&D$1&"'!$V$80:$V$107"),MATCH($A13,INDIRECT("'"&D$1&"'!$A$80:$A$107"),0)),0)+IFERROR(INDEX(INDIRECT("'"&F$1&"'!$V$80:$V$107"),MATCH($A13,INDIRECT("'"&F$1&"'!$A$80:$A$107"),0)),0)+IFERROR(INDEX(INDIRECT("'"&H$1&"'!$V$80:$V$107"),MATCH($A13,INDIRECT("'"&H$1&"'!$A$80:$A$107"),0)),0)+IFERROR(INDEX(INDIRECT("'"&J$1&"'!$V$80:$V$107"),MATCH($A13,INDIRECT("'"&J$1&"'!$A$80:$A$107"),0)),0)+IFERROR(INDEX(INDIRECT("'"&L$1&"'!$V$80:$V$107"),MATCH($A13,INDIRECT("'"&L$1&"'!$A$80:$A$107"),0)),0)+IFERROR(INDEX(INDIRECT("'"&N$1&"'!$V$80:$V$107"),MATCH($A13,INDIRECT("'"&N$1&"'!$A$80:$A$107"),0)),0)+IFERROR(INDEX(INDIRECT("'"&P$1&"'!$V$80:$V$107"),MATCH($A13,INDIRECT("'"&P$1&"'!$A$80:$A$107"),0)),0)+IFERROR(INDEX(INDIRECT("'"&R$1&"'!$V$80:$V$107"),MATCH($A13,INDIRECT("'"&R$1&"'!$A$80:$A$107"),0)),0)+IFERROR(INDEX(INDIRECT("'"&T$1&"'!$V$80:$V$107"),MATCH($A13,INDIRECT("'"&T$1&"'!$A$80:$A$107"),0)),0) -> 0
A14: Isaac Mond | B14: =IFERROR(INDEX(INDIRECT("'"&B$1&"'!$V$18:$V$45"),MATCH($A14,INDIRECT("'"&B$1&"'!$A$18:$A$45"),0)),0) -> 8 | C14: =IFERROR(INDEX(INDIRECT("'"&B$1&"'!$V$49:$V$76"),MATCH($A14,INDIRECT("'"&B$1&"'!$A$49:$A$76"),0)),0) -> 1 | D14: =IFERROR(INDEX(INDIRECT("'"&D$1&"'!$V$18:$V$45"),MATCH($A14,INDIRECT("'"&D$1&"'!$A$18:$A$45"),0)),0) -> 3 | E14: =IFERROR(INDEX(INDIRECT("'"&D$1&"'!$V$49:$V$76"),MATCH($A14,INDIRECT("'"&D$1&"'!$A$49:$A$76"),0)),0) -> 0 | F14: =IFERROR(INDEX(INDIRECT("'"&F$1&"'!$V$18:$V$45"),MATCH($A14,INDIRECT("'"&F$1&"'!$A$18:$A$45"),0)),0) -> 10 | G14: =IFERROR(INDEX(INDIRECT("'"&F$1&"'!$V$49:$V$76"),MATCH($A14,INDIRECT("'"&F$1&"'!$A$49:$A$76"),0)),0) -> 1 | H14: =IFERROR(INDEX(INDIRECT("'"&H$1&"'!$V$18:$V$45"),MATCH($A14,INDIRECT("'"&H$1&"'!$A$18:$A$45"),0)),0) -> 9 | I14: =IFERROR(INDEX(INDIRECT("'"&H$1&"'!$V$49:$V$76"),MATCH($A14,INDIRECT("'"&H$1&"'!$A$49:$A$76"),0)),0) -> 0 | J14: =IFERROR(INDEX(INDIRECT("'"&J$1&"'!$V$18:$V$45"),MATCH($A14,INDIRECT("'"&J$1&"'!$A$18:$A$45"),0)),0) -> 8 | K14: =IFERROR(INDEX(INDIRECT("'"&J$1&"'!$V$49:$V$76"),MATCH($A14,INDIRECT("'"&J$1&"'!$A$49:$A$76"),0)),0) -> 1 | L14: =IFERROR(INDEX(INDIRECT("'"&L$1&"'!$V$18:$V$45"),MATCH($A14,INDIRECT("'"&L$1&"'!$A$18:$A$45"),0)),0) -> 6 | M14: =IFERROR(INDEX(INDIRECT("'"&L$1&"'!$V$49:$V$76"),MATCH($A14,INDIRECT("'"&L$1&"'!$A$49:$A$76"),0)),0) -> 0 | N14: =IFERROR(INDEX(INDIRECT("'"&N$1&"'!$V$18:$V$45"),MATCH($A14,INDIRECT("'"&N$1&"'!$A$18:$A$45"),0)),0) -> 4 | O14: =IFERROR(INDEX(INDIRECT("'"&N$1&"'!$V$49:$V$76"),MATCH($A14,INDIRECT("'"&N$1&"'!$A$49:$A$76"),0)),0) -> 1 | P14: =IFERROR(INDEX(INDIRECT("'"&P$1&"'!$V$18:$V$45"),MATCH($A14,INDIRECT("'"&P$1&"'!$A$18:$A$45"),0)),0) -> 1 | Q14: =IFERROR(INDEX(INDIRECT("'"&P$1&"'!$V$49:$V$76"),MATCH($A14,INDIRECT("'"&P$1&"'!$A$49:$A$76"),0)),0) -> 0 | R14: =IFERROR(INDEX(INDIRECT("'"&R$1&"'!$V$18:$V$45"),MATCH($A14,INDIRECT("'"&R$1&"'!$A$18:$A$45"),0)),0) -> 0 | S14: =IFERROR(INDEX(INDIRECT("'"&R$1&"'!$V$49:$V$76"),MATCH($A14,INDIRECT("'"&R$1&"'!$A$49:$A$76"),0)),0) -> 0 | T14: =IFERROR(INDEX(INDIRECT("'"&T$1&"'!$V$18:$V$45"),MATCH($A14,INDIRECT("'"&T$1&"'!$A$18:$A$45"),0)),0) -> 0 | U14: =IFERROR(INDEX(INDIRECT("'"&T$1&"'!$V$49:$V$76"),MATCH($A14,INDIRECT("'"&T$1&"'!$A$49:$A$76"),0)),0) -> 0 | V14: =B14+D14+F14+H14+J14+L14+N14+P14+R14+T14 -> 49 | W14: =C14+E14+G14+I14+K14+M14+O14+Q14+S14+U14 -> 4 | X14: =IF(V14=0,"—",ROUND(W14/V14,2)) -> 0.08 | Y14: =IFERROR(INDEX(INDIRECT("'"&B$1&"'!$V$80:$V$107"),MATCH($A14,INDIRECT("'"&B$1&"'!$A$80:$A$107"),0)),0)+IFERROR(INDEX(INDIRECT("'"&D$1&"'!$V$80:$V$107"),MATCH($A14,INDIRECT("'"&D$1&"'!$A$80:$A$107"),0)),0)+IFERROR(INDEX(INDIRECT("'"&F$1&"'!$V$80:$V$107"),MATCH($A14,INDIRECT("'"&F$1&"'!$A$80:$A$107"),0)),0)+IFERROR(INDEX(INDIRECT("'"&H$1&"'!$V$80:$V$107"),MATCH($A14,INDIRECT("'"&H$1&"'!$A$80:$A$107"),0)),0)+IFERROR(INDEX(INDIRECT("'"&J$1&"'!$V$80:$V$107"),MATCH($A14,INDIRECT("'"&J$1&"'!$A$80:$A$107"),0)),0)+IFERROR(INDEX(INDIRECT("'"&L$1&"'!$V$80:$V$107"),MATCH($A14,INDIRECT("'"&L$1&"'!$A$80:$A$107"),0)),0)+IFERROR(INDEX(INDIRECT("'"&N$1&"'!$V$80:$V$107"),MATCH($A14,INDIRECT("'"&N$1&"'!$A$80:$A$107"),0)),0)+IFERROR(INDEX(INDIRECT("'"&P$1&"'!$V$80:$V$107"),MATCH($A14,INDIRECT("'"&P$1&"'!$A$80:$A$107"),0)),0)+IFERROR(INDEX(INDIRECT("'"&R$1&"'!$V$80:$V$107"),MATCH($A14,INDIRECT("'"&R$1&"'!$A$80:$A$107"),0)),0)+IFERROR(INDEX(INDIRECT("'"&T$1&"'!$V$80:$V$107"),MATCH($A14,INDIRECT("'"&T$1&"'!$A$80:$A$107"),0)),0) -> 7
... A24: Seb Burgess | B24: =IFERROR(INDEX(INDIRECT("'"&B$1&"'!$V$18:$V$45"),MATCH($A24,INDIRECT("'"&B$1&"'!$A$18:$A$45"),0)),0) -> 0 | C24: =IFERROR(INDEX(INDIRECT("'"&B$1&"'!$V$49:$V$76"),MATCH($A24,INDIRECT("'"&B$1&"'!$A$49:$A$76"),0)),0) -> 0 | D24: =IFERROR(INDEX(INDIRECT("'"&D$1&"'!$V$18:$V$45"),MATCH($A24,INDIRECT("'"&D$1&"'!$A$18:$A$45"),0)),0) -> 5 | E24: =IFERROR(INDEX(INDIRECT("'"&D$1&"'!$V$49:$V$76"),MATCH($A24,INDIRECT("'"&D$1&"'!$A$49:$A$76"),0)),0) -> 5 | F24: =IFERROR(INDEX(INDIRECT("'"&F$1&"'!$V$18:$V$45"),MATCH($A24,INDIRECT("'"&F$1&"'!$A$18:$A$45"),0)),0) -> 9 | G24: =IFERROR(INDEX(INDIRECT("'"&F$1&"'!$V$49:$V$76"),MATCH($A24,INDIRECT("'"&F$1&"'!$A$49:$A$76"),0)),0) -> 6 | H24: =IFERROR(INDEX(INDIRECT("'"&H$1&"'!$V$18:$V$45"),MATCH($A24,INDIRECT("'"&H$1&"'!$A$18:$A$45"),0)),0) -> 13 | I24: =IFERROR(INDEX(INDIRECT("'"&H$1&"'!$V$49:$V$76"),MATCH($A24,INDIRECT("'"&H$1&"'!$A$49:$A$76"),0)),0) -> 14 | J24: =IFERROR(INDEX(INDIRECT("'"&J$1&"'!$V$18:$V$45"),MATCH($A24,INDIRECT("'"&J$1&"'!$A$18:$A$45"),0)),0) -> 9 | K24: =IFERROR(INDEX(INDIRECT("'"&J$1&"'!$V$49:$V$76"),MATCH($A24,INDIRECT("'"&J$1&"'!$A$49:$A$76"),0)),0) -> 10 | L24: =IFERROR(INDEX(INDIRECT("'"&L$1&"'!$V$18:$V$45"),MATCH($A24,INDIRECT("'"&L$1&"'!$A$18:$A$45"),0)),0) -> 13 | M24: =IFERROR(INDEX(INDIRECT("'"&L$1&"'!$V$49:$V$76"),MATCH($A24,INDIRECT("'"&L$1&"'!$A$49:$A$76"),0)),0) -> 15 | N24: =IFERROR(INDEX(INDIRECT("'"&N$1&"'!$V$18:$V$45"),MATCH($A24,INDIRECT("'"&N$1&"'!$A$18:$A$45"),0)),0) -> 4 | O24: =IFERROR(INDEX(INDIRECT("'"&N$1&"'!$V$49:$V$76"),MATCH($A24,INDIRECT("'"&N$1&"'!$A$49:$A$76"),0)),0) -> 5 | P24: =IFERROR(INDEX(INDIRECT("'"&P$1&"'!$V$18:$V$45"),MATCH($A24,INDIRECT("'"&P$1&"'!$A$18:$A$45"),0)),0) -> 1 | Q24: =IFERROR(INDEX(INDIRECT("'"&P$1&"'!$V$49:$V$76"),MATCH($A24,INDIRECT("'"&P$1&"'!$A$49:$A$76"),0)),0) -> 3 | R24: =IFERROR(INDEX(INDIRECT("'"&R$1&"'!$V$18:$V$45"),MATCH($A24,INDIRECT("'"&R$1&"'!$A$18:$A$45"),0)),0) -> 0 | S24: =IFERROR(INDEX(INDIRECT("'"&R$1&"'!$V$49:$V$76"),MATCH($A24,INDIRECT("'"&R$1&"'!$A$49:$A$76"),0)),0) -> 0 | T24: =IFERROR(INDEX(INDIRECT("'"&T$1&"'!$V$18:$V$45"),MATCH($A24,INDIRECT("'"&T$1&"'!$A$18:$A$45"),0)),0) -> 0 | U24: =IFERROR(INDEX(INDIRECT("'"&T$1&"'!$V$49:$V$76"),MATCH($A24,INDIRECT("'"&T$1&"'!$A$49:$A$76"),0)),0) -> 0 | V24: =B24+D24+F24+H24+J24+L24+N24+P24+R24+T24 -> 54 | W24: =C24+E24+G24+I24+K24+M24+O24+Q24+S24+U24 -> 58 | X24: =IF(V24=0,"—",ROUND(W24/V24,2)) -> 1.07 | Y24: =IFERROR(INDEX(INDIRECT("'"&B$1&"'!$V$80:$V$107"),MATCH($A24,INDIRECT("'"&B$1&"'!$A$80:$A$107"),0)),0)+IFERROR(INDEX(INDIRECT("'"&D$1&"'!$V$80:$V$107"),MATCH($A24,INDIRECT("'"&D$1&"'!$A$80:$A$107"),0)),0)+IFERROR(INDEX(INDIRECT("'"&F$1&"'!$V$80:$V$107"),MATCH($A24,INDIRECT("'"&F$1&"'!$A$80:$A$107"),0)),0)+IFERROR(INDEX(INDIRECT("'"&H$1&"'!$V$80:$V$107"),MATCH($A24,INDIRECT("'"&H$1&"'!$A$80:$A$107"),0)),0)+IFERROR(INDEX(INDIRECT("'"&J$1&"'!$V$80:$V$107"),MATCH($A24,INDIRECT("'"&J$1&"'!$A$80:$A$107"),0)),0)+IFERROR(INDEX(INDIRECT("'"&L$1&"'!$V$80:$V$107"),MATCH($A24,INDIRECT("'"&L$1&"'!$A$80:$A$107"),0)),0)+IFERROR(INDEX(INDIRECT("'"&N$1&"'!$V$80:$V$107"),MATCH($A24,INDIRECT("'"&N$1&"'!$A$80:$A$107"),0)),0)+IFERROR(INDEX(INDIRECT("'"&P$1&"'!$V$80:$V$107"),MATCH($A24,INDIRECT("'"&P$1&"'!$A$80:$A$107"),0)),0)+IFERROR(INDEX(INDIRECT("'"&R$1&"'!$V$80:$V$107"),MATCH($A24,INDIRECT("'"&R$1&"'!$A$80:$A$107"),0)),0)+IFERROR(INDEX(INDIRECT("'"&T$1&"'!$V$80:$V$107"),MATCH($A24,INDIRECT("'"&T$1&"'!$A$80:$A$107"),0)),0) -> 1
B25: =IFERROR(INDEX(INDIRECT("'"&B$1&"'!$V$18:$V$45"),MATCH($A25,INDIRECT("'"&B$1&"'!$A$18:$A$45"),0)),0) -> 0 | C25: =IFERROR(INDEX(INDIRECT("'"&B$1&"'!$V$49:$V$76"),MATCH($A25,INDIRECT("'"&B$1&"'!$A$49:$A$76"),0)),0) -> 0 | D25: =IFERROR(INDEX(INDIRECT("'"&D$1&"'!$V$18:$V$45"),MATCH($A25,INDIRECT("'"&D$1&"'!$A$18:$A$45"),0)),0) -> 0 | E25: =IFERROR(INDEX(INDIRECT("'"&D$1&"'!$V$49:$V$76"),MATCH($A25,INDIRECT("'"&D$1&"'!$A$49:$A$76"),0)),0) -> 0 | F25: =IFERROR(INDEX(INDIRECT("'"&F$1&"'!$V$18:$V$45"),MATCH($A25,INDIRECT("'"&F$1&"'!$A$18:$A$45"),0)),0) -> 0 | G25: =IFERROR(INDEX(INDIRECT("'"&F$1&"'!$V$49:$V$76"),MATCH($A25,INDIRECT("'"&F$1&"'!$A$49:$A$76"),0)),0) -> 0 | H25: =IFERROR(INDEX(INDIRECT("'"&H$1&"'!$V$18:$V$45"),MATCH($A25,INDIRECT("'"&H$1&"'!$A$18:$A$45"),0)),0) -> 0 | I25: =IFERROR(INDEX(INDIRECT("'"&H$1&"'!$V$49:$V$76"),MATCH($A25,INDIRECT("'"&H$1&"'!$A$49:$A$76"),0)),0) -> 0 | J25: =IFERROR(INDEX(INDIRECT("'"&J$1&"'!$V$18:$V$45"),MATCH($A25,INDIRECT("'"&J$1&"'!$A$18:$A$45"),0)),0) -> 0 | K25: =IFERROR(INDEX(INDIRECT("'"&J$1&"'!$V$49:$V$76"),MATCH($A25,INDIRECT("'"&J$1&"'!$A$49:$A$76"),0)),0) -> 0 | L25: =IFERROR(INDEX(INDIRECT("'"&L$1&"'!$V$18:$V$45"),MATCH($A25,INDIRECT("'"&L$1&"'!$A$18:$A$45"),0)),0) -> 0 | M25: =IFERROR(INDEX(INDIRECT("'"&L$1&"'!$V$49:$V$76"),MATCH($A25,INDIRECT("'"&L$1&"'!$A$49:$A$76"),0)),0) -> 0 | N25: =IFERROR(INDEX(INDIRECT("'"&N$1&"'!$V$18:$V$45"),MATCH($A25,INDIRECT("'"&N$1&"'!$A$18:$A$45"),0)),0) -> 0 | O25: =IFERROR(INDEX(INDIRECT("'"&N$1&"'!$V$49:$V$76"),MATCH($A25,INDIRECT("'"&N$1&"'!$A$49:$A$76"),0)),0) -> 0 | P25: =IFERROR(INDEX(INDIRECT("'"&P$1&"'!$V$18:$V$45"),MATCH($A25,INDIRECT("'"&P$1&"'!$A$18:$A$45"),0)),0) -> 0 | Q25: =IFERROR(INDEX(INDIRECT("'"&P$1&"'!$V$49:$V$76"),MATCH($A25,INDIRECT("'"&P$1&"'!$A$49:$A$76"),0)),0) -> 0 | R25: =IFERROR(INDEX(INDIRECT("'"&R$1&"'!$V$18:$V$45"),MATCH($A25,INDIRECT("'"&R$1&"'!$A$18:$A$45"),0)),0) -> 0 | S25: =IFERROR(INDEX(INDIRECT("'"&R$1&"'!$V$49:$V$76"),MATCH($A25,INDIRECT("'"&R$1&"'!$A$49:$A$76"),0)),0) -> 0 | T25: =IFERROR(INDEX(INDIRECT("'"&T$1&"'!$V$18:$V$45"),MATCH($A25,INDIRECT("'"&T$1&"'!$A$18:$A$45"),0)),0) -> 0 | U25: =IFERROR(INDEX(INDIRECT("'"&T$1&"'!$V$49:$V$76"),MATCH($A25,INDIRECT("'"&T$1&"'!$A$49:$A$76"),0)),0) -> 0 | V25: =B25+D25+F25+H25+J25+L25+N25+P25+R25+T25 -> 0 | W25: =C25+E25+G25+I25+K25+M25+O25+Q25+S25+U25 -> 0 | X25: =IF(V25=0,"—",ROUND(W25/V25,2)) -> — | Y25: =IFERROR(INDEX(INDIRECT("'"&B$1&"'!$V$80:$V$107"),MATCH($A25,INDIRECT("'"&B$1&"'!$A$80:$A$107"),0)),0)+IFERROR(INDEX(INDIRECT("'"&D$1&"'!$V$80:$V$107"),MATCH($A25,INDIRECT("'"&D$1&"'!$A$80:$A$107"),0)),0)+IFERROR(INDEX(INDIRECT("'"&F$1&"'!$V$80:$V$107"),MATCH($A25,INDIRECT("'"&F$1&"'!$A$80:$A$107"),0)),0)+IFERROR(INDEX(INDIRECT("'"&H$1&"'!$V$80:$V$107"),MATCH($A25,INDIRECT("'"&H$1&"'!$A$80:$A$107"),0)),0)+IFERROR(INDEX(INDIRECT("'"&J$1&"'!$V$80:$V$107"),MATCH($A25,INDIRECT("'"&J$1&"'!$A$80:$A$107"),0)),0)+IFERROR(INDEX(INDIRECT("'"&L$1&"'!$V$80:$V$107"),MATCH($A25,INDIRECT("'"&L$1&"'!$A$80:$A$107"),0)),0)+IFERROR(INDEX(INDIRECT("'"&N$1&"'!$V$80:$V$107"),MATCH($A25,INDIRECT("'"&N$1&"'!$A$80:$A$107"),0)),0)+IFERROR(INDEX(INDIRECT("'"&P$1&"'!$V$80:$V$107"),MATCH($A25,INDIRECT("'"&P$1&"'!$A$80:$A$107"),0)),0)+IFERROR(INDEX(INDIRECT("'"&R$1&"'!$V$80:$V$107"),MATCH($A25,INDIRECT("'"&R$1&"'!$A$80:$A$107"),0)),0)+IFERROR(INDEX(INDIRECT("'"&T$1&"'!$V$80:$V$107"),MATCH($A25,INDIRECT("'"&T$1&"'!$A$80:$A$107"),0)),0) -> 0
B26: =IFERROR(INDEX(INDIRECT("'"&B$1&"'!$V$18:$V$45"),MATCH($A26,INDIRECT("'"&B$1&"'!$A$18:$A$45"),0)),0) -> 0 | C26: =IFERROR(INDEX(INDIRECT("'"&B$1&"'!$V$49:$V$76"),MATCH($A26,INDIRECT("'"&B$1&"'!$A$49:$A$76"),0)),0) -> 0 | D26: =IFERROR(INDEX(INDIRECT("'"&D$1&"'!$V$18:$V$45"),MATCH($A26,INDIRECT("'"&D$1&"'!$A$18:$A$45"),0)),0) -> 0 | E26: =IFERROR(INDEX(INDIRECT("'"&D$1&"'!$V$49:$V$76"),MATCH($A26,INDIRECT("'"&D$1&"'!$A$49:$A$76"),0)),0) -> 0 | F26: =IFERROR(INDEX(INDIRECT("'"&F$1&"'!$V$18:$V$45"),MATCH($A26,INDIRECT("'"&F$1&"'!$A$18:$A$45"),0)),0) -> 0 | G26: =IFERROR(INDEX(INDIRECT("'"&F$1&"'!$V$49:$V$76"),MATCH($A26,INDIRECT("'"&F$1&"'!$A$49:$A$76"),0)),0) -> 0 | H26: =IFERROR(INDEX(INDIRECT("'"&H$1&"'!$V$18:$V$45"),MATCH($A26,INDIRECT("'"&H$1&"'!$A$18:$A$45"),0)),0) -> 0 | I26: =IFERROR(INDEX(INDIRECT("'"&H$1&"'!$V$49:$V$76"),MATCH($A26,INDIRECT("'"&H$1&"'!$A$49:$A$76"),0)),0) -> 0 | J26: =IFERROR(INDEX(INDIRECT("'"&J$1&"'!$V$18:$V$45"),MATCH($A26,INDIRECT("'"&J$1&"'!$A$18:$A$45"),0)),0) -> 0 | K26: =IFERROR(INDEX(INDIRECT("'"&J$1&"'!$V$49:$V$76"),MATCH($A26,INDIRECT("'"&J$1&"'!$A$49:$A$76"),0)),0) -> 0 | L26: =IFERROR(INDEX(INDIRECT("'"&L$1&"'!$V$18:$V$45"),MATCH($A26,INDIRECT("'"&L$1&"'!$A$18:$A$45"),0)),0) -> 0 | M26: =IFERROR(INDEX(INDIRECT("'"&L$1&"'!$V$49:$V$76"),MATCH($A26,INDIRECT("'"&L$1&"'!$A$49:$A$76"),0)),0) -> 0 | N26: =IFERROR(INDEX(INDIRECT("'"&N$1&"'!$V$18:$V$45"),MATCH($A26,INDIRECT("'"&N$1&"'!$A$18:$A$45"),0)),0) -> 0 | O26: =IFERROR(INDEX(INDIRECT("'"&N$1&"'!$V$49:$V$76"),MATCH($A26,INDIRECT("'"&N$1&"'!$A$49:$A$76"),0)),0) -> 0 | P26: =IFERROR(INDEX(INDIRECT("'"&P$1&"'!$V$18:$V$45"),MATCH($A26,INDIRECT("'"&P$1&"'!$A$18:$A$45"),0)),0) -> 0 | Q26: =IFERROR(INDEX(INDIRECT("'"&P$1&"'!$V$49:$V$76"),MATCH($A26,INDIRECT("'"&P$1&"'!$A$49:$A$76"),0)),0) -> 0 | R26: =IFERROR(INDEX(INDIRECT("'"&R$1&"'!$V$18:$V$45"),MATCH($A26,INDIRECT("'"&R$1&"'!$A$18:$A$45"),0)),0) -> 0 | S26: =IFERROR(INDEX(INDIRECT("'"&R$1&"'!$V$49:$V$76"),MATCH($A26,INDIRECT("'"&R$1&"'!$A$49:$A$76"),0)),0) -> 0 | T26: =IFERROR(INDEX(INDIRECT("'"&T$1&"'!$V$18:$V$45"),MATCH($A26,INDIRECT("'"&T$1&"'!$A$18:$A$45"),0)),0) -> 0 | U26: =IFERROR(INDEX(INDIRECT("'"&T$1&"'!$V$49:$V$76"),MATCH($A26,INDIRECT("'"&T$1&"'!$A$49:$A$76"),0)),0) -> 0 | V26: =B26+D26+F26+H26+J26+L26+N26+P26+R26+T26 -> 0 | W26: =C26+E26+G26+I26+K26+M26+O26+Q26+S26+U26 -> 0 | X26: =IF(V26=0,"—",ROUND(W26/V26,2)) -> — | Y26: =IFERROR(INDEX(INDIRECT("'"&B$1&"'!$V$80:$V$107"),MATCH($A26,INDIRECT("'"&B$1&"'!$A$80:$A$107"),0)),0)+IFERROR(INDEX(INDIRECT("'"&D$1&"'!$V$80:$V$107"),MATCH($A26,INDIRECT("'"&D$1&"'!$A$80:$A$107"),0)),0)+IFERROR(INDEX(INDIRECT("'"&F$1&"'!$V$80:$V$107"),MATCH($A26,INDIRECT("'"&F$1&"'!$A$80:$A$107"),0)),0)+IFERROR(INDEX(INDIRECT("'"&H$1&"'!$V$80:$V$107"),MATCH($A26,INDIRECT("'"&H$1&"'!$A$80:$A$107"),0)),0)+IFERROR(INDEX(INDIRECT("'"&J$1&"'!$V$80:$V$107"),MATCH($A26,INDIRECT("'"&J$1&"'!$A$80:$A$107"),0)),0)+IFERROR(INDEX(INDIRECT("'"&L$1&"'!$V$80:$V$107"),MATCH($A26,INDIRECT("'"&L$1&"'!$A$80:$A$107"),0)),0)+IFERROR(INDEX(INDIRECT("'"&N$1&"'!$V$80:$V$107"),MATCH($A26,INDIRECT("'"&N$1&"'!$A$80:$A$107"),0)),0)+IFERROR(INDEX(INDIRECT("'"&P$1&"'!$V$80:$V$107"),MATCH($A26,INDIRECT("'"&P$1&"'!$A$80:$A$107"),0)),0)+IFERROR(INDEX(INDIRECT("'"&R$1&"'!$V$80:$V$107"),MATCH($A26,INDIRECT("'"&R$1&"'!$A$80:$A$107"),0)),0)+IFERROR(INDEX(INDIRECT("'"&T$1&"'!$V$80:$V$107"),MATCH($A26,INDIRECT("'"&T$1&"'!$A$80:$A$107"),0)),0) -> 0
B27: =IFERROR(INDEX(INDIRECT("'"&B$1&"'!$V$18:$V$45"),MATCH($A27,INDIRECT("'"&B$1&"'!$A$18:$A$45"),0)),0) -> 0 | C27: =IFERROR(INDEX(INDIRECT("'"&B$1&"'!$V$49:$V$76"),MATCH($A27,INDIRECT("'"&B$1&"'!$A$49:$A$76"),0)),0) -> 0 | D27: =IFERROR(INDEX(INDIRECT("'"&D$1&"'!$V$18:$V$45"),MATCH($A27,INDIRECT("'"&D$1&"'!$A$18:$A$45"),0)),0) -> 0 | E27: =IFERROR(INDEX(INDIRECT("'"&D$1&"'!$V$49:$V$76"),MATCH($A27,INDIRECT("'"&D$1&"'!$A$49:$A$76"),0)),0) -> 0 | F27: =IFERROR(INDEX(INDIRECT("'"&F$1&"'!$V$18:$V$45"),MATCH($A27,INDIRECT("'"&F$1&"'!$A$18:$A$45"),0)),0) -> 0 | G27: =IFERROR(INDEX(INDIRECT("'"&F$1&"'!$V$49:$V$76"),MATCH($A27,INDIRECT("'"&F$1&"'!$A$49:$A$76"),0)),0) -> 0 | H27: =IFERROR(INDEX(INDIRECT("'"&H$1&"'!$V$18:$V$45"),MATCH($A27,INDIRECT("'"&H$1&"'!$A$18:$A$45"),0)),0) -> 0 | I27: =IFERROR(INDEX(INDIRECT("'"&H$1&"'!$V$49:$V$76"),MATCH($A27,INDIRECT("'"&H$1&"'!$A$49:$A$76"),0)),0) -> 0 | J27: =IFERROR(INDEX(INDIRECT("'"&J$1&"'!$V$18:$V$45"),MATCH($A27,INDIRECT("'"&J$1&"'!$A$18:$A$45"),0)),0) -> 0 | K27: =IFERROR(INDEX(INDIRECT("'"&J$1&"'!$V$49:$V$76"),MATCH($A27,INDIRECT("'"&J$1&"'!$A$49:$A$76"),0)),0) -> 0 | L27: =IFERROR(INDEX(INDIRECT("'"&L$1&"'!$V$18:$V$45"),MATCH($A27,INDIRECT("'"&L$1&"'!$A$18:$A$45"),0)),0) -> 0 | M27: =IFERROR(INDEX(INDIRECT("'"&L$1&"'!$V$49:$V$76"),MATCH($A27,INDIRECT("'"&L$1&"'!$A$49:$A$76"),0)),0) -> 0 | N27: =IFERROR(INDEX(INDIRECT("'"&N$1&"'!$V$18:$V$45"),MATCH($A27,INDIRECT("'"&N$1&"'!$A$18:$A$45"),0)),0) -> 0 | O27: =IFERROR(INDEX(INDIRECT("'"&N$1&"'!$V$49:$V$76"),MATCH($A27,INDIRECT("'"&N$1&"'!$A$49:$A$76"),0)),0) -> 0 | P27: =IFERROR(INDEX(INDIRECT("'"&P$1&"'!$V$18:$V$45"),MATCH($A27,INDIRECT("'"&P$1&"'!$A$18:$A$45"),0)),0) -> 0 | Q27: =IFERROR(INDEX(INDIRECT("'"&P$1&"'!$V$49:$V$76"),MATCH($A27,INDIRECT("'"&P$1&"'!$A$49:$A$76"),0)),0) -> 0 | R27: =IFERROR(INDEX(INDIRECT("'"&R$1&"'!$V$18:$V$45"),MATCH($A27,INDIRECT("'"&R$1&"'!$A$18:$A$45"),0)),0) -> 0 | S27: =IFERROR(INDEX(INDIRECT("'"&R$1&"'!$V$49:$V$76"),MATCH($A27,INDIRECT("'"&R$1&"'!$A$49:$A$76"),0)),0) -> 0 | T27: =IFERROR(INDEX(INDIRECT("'"&T$1&"'!$V$18:$V$45"),MATCH($A27,INDIRECT("'"&T$1&"'!$A$18:$A$45"),0)),0) -> 0 | U27: =IFERROR(INDEX(INDIRECT("'"&T$1&"'!$V$49:$V$76"),MATCH($A27,INDIRECT("'"&T$1&"'!$A$49:$A$76"),0)),0) -> 0 | V27: =B27+D27+F27+H27+J27+L27+N27+P27+R27+T27 -> 0 | W27: =C27+E27+G27+I27+K27+M27+O27+Q27+S27+U27 -> 0 | X27: =IF(V27=0,"—",ROUND(W27/V27,2)) -> — | Y27: =IFERROR(INDEX(INDIRECT("'"&B$1&"'!$V$80:$V$107"),MATCH($A27,INDIRECT("'"&B$1&"'!$A$80:$A$107"),0)),0)+IFERROR(INDEX(INDIRECT("'"&D$1&"'!$V$80:$V$107"),MATCH($A27,INDIRECT("'"&D$1&"'!$A$80:$A$107"),0)),0)+IFERROR(INDEX(INDIRECT("'"&F$1&"'!$V$80:$V$107"),MATCH($A27,INDIRECT("'"&F$1&"'!$A$80:$A$107"),0)),0)+IFERROR(INDEX(INDIRECT("'"&H$1&"'!$V$80:$V$107"),MATCH($A27,INDIRECT("'"&H$1&"'!$A$80:$A$107"),0)),0)+IFERROR(INDEX(INDIRECT("'"&J$1&"'!$V$80:$V$107"),MATCH($A27,INDIRECT("'"&J$1&"'!$A$80:$A$107"),0)),0)+IFERROR(INDEX(INDIRECT("'"&L$1&"'!$V$80:$V$107"),MATCH($A27,INDIRECT("'"&L$1&"'!$A$80:$A$107"),0)),0)+IFERROR(INDEX(INDIRECT("'"&N$1&"'!$V$80:$V$107"),MATCH($A27,INDIRECT("'"&N$1&"'!$A$80:$A$107"),0)),0)+IFERROR(INDEX(INDIRECT("'"&P$1&"'!$V$80:$V$107"),MATCH($A27,INDIRECT("'"&P$1&"'!$A$80:$A$107"),0)),0)+IFERROR(INDEX(INDIRECT("'"&R$1&"'!$V$80:$V$107"),MATCH($A27,INDIRECT("'"&R$1&"'!$A$80:$A$107"),0)),0)+IFERROR(INDEX(INDIRECT("'"&T$1&"'!$V$80:$V$107"),MATCH($A27,INDIRECT("'"&T$1&"'!$A$80:$A$107"),0)),0) -> 0
B28: =IFERROR(INDEX(INDIRECT("'"&B$1&"'!$V$18:$V$45"),MATCH($A28,INDIRECT("'"&B$1&"'!$A$18:$A$45"),0)),0) -> 0 | C28: =IFERROR(INDEX(INDIRECT("'"&B$1&"'!$V$49:$V$76"),MATCH($A28,INDIRECT("'"&B$1&"'!$A$49:$A$76"),0)),0) -> 0 | D28: =IFERROR(INDEX(INDIRECT("'"&D$1&"'!$V$18:$V$45"),MATCH($A28,INDIRECT("'"&D$1&"'!$A$18:$A$45"),0)),0) -> 0 | E28: =IFERROR(INDEX(INDIRECT("'"&D$1&"'!$V$49:$V$76"),MATCH($A28,INDIRECT("'"&D$1&"'!$A$49:$A$76"),0)),0) -> 0 | F28: =IFERROR(INDEX(INDIRECT("'"&F$1&"'!$V$18:$V$45"),MATCH($A28,INDIRECT("'"&F$1&"'!$A$18:$A$45"),0)),0) -> 0 | G28: =IFERROR(INDEX(INDIRECT("'"&F$1&"'!$V$49:$V$76"),MATCH($A28,INDIRECT("'"&F$1&"'!$A$49:$A$76"),0)),0) -> 0 | H28: =IFERROR(INDEX(INDIRECT("'"&H$1&"'!$V$18:$V$45"),MATCH($A28,INDIRECT("'"&H$1&"'!$A$18:$A$45"),0)),0) -> 0 | I28: =IFERROR(INDEX(INDIRECT("'"&H$1&"'!$V$49:$V$76"),MATCH($A28,INDIRECT("'"&H$1&"'!$A$49:$A$76"),0)),0) -> 0 | J28: =IFERROR(INDEX(INDIRECT("'"&J$1&"'!$V$18:$V$45"),MATCH($A28,INDIRECT("'"&J$1&"'!$A$18:$A$45"),0)),0) -> 0 | K28: =IFERROR(INDEX(INDIRECT("'"&J$1&"'!$V$49:$V$76"),MATCH($A28,INDIRECT("'"&J$1&"'!$A$49:$A$76"),0)),0) -> 0 | L28: =IFERROR(INDEX(INDIRECT("'"&L$1&"'!$V$18:$V$45"),MATCH($A28,INDIRECT("'"&L$1&"'!$A$18:$A$45"),0)),0) -> 0 | M28: =IFERROR(INDEX(INDIRECT("'"&L$1&"'!$V$49:$V$76"),MATCH($A28,INDIRECT("'"&L$1&"'!$A$49:$A$76"),0)),0) -> 0 | N28: =IFERROR(INDEX(INDIRECT("'"&N$1&"'!$V$18:$V$45"),MATCH($A28,INDIRECT("'"&N$1&"'!$A$18:$A$45"),0)),0) -> 0 | O28: =IFERROR(INDEX(INDIRECT("'"&N$1&"'!$V$49:$V$76"),MATCH($A28,INDIRECT("'"&N$1&"'!$A$49:$A$76"),0)),0) -> 0 | P28: =IFERROR(INDEX(INDIRECT("'"&P$1&"'!$V$18:$V$45"),MATCH($A28,INDIRECT("'"&P$1&"'!$A$18:$A$45"),0)),0) -> 0 | Q28: =IFERROR(INDEX(INDIRECT("'"&P$1&"'!$V$49:$V$76"),MATCH($A28,INDIRECT("'"&P$1&"'!$A$49:$A$76"),0)),0) -> 0 | R28: =IFERROR(INDEX(INDIRECT("'"&R$1&"'!$V$18:$V$45"),MATCH($A28,INDIRECT("'"&R$1&"'!$A$18:$A$45"),0)),0) -> 0 | S28: =IFERROR(INDEX(INDIRECT("'"&R$1&"'!$V$49:$V$76"),MATCH($A28,INDIRECT("'"&R$1&"'!$A$49:$A$76"),0)),0) -> 0 | T28: =IFERROR(INDEX(INDIRECT("'"&T$1&"'!$V$18:$V$45"),MATCH($A28,INDIRECT("'"&T$1&"'!$A$18:$A$45"),0)),0) -> 0 | U28: =IFERROR(INDEX(INDIRECT("'"&T$1&"'!$V$49:$V$76"),MATCH($A28,INDIRECT("'"&T$1&"'!$A$49:$A$76"),0)),0) -> 0 | V28: =B28+D28+F28+H28+J28+L28+N28+P28+R28+T28 -> 0 | W28: =C28+E28+G28+I28+K28+M28+O28+Q28+S28+U28 -> 0 | X28: =IF(V28=0,"—",ROUND(W28/V28,2)) -> — | Y28: =IFERROR(INDEX(INDIRECT("'"&B$1&"'!$V$80:$V$107"),MATCH($A28,INDIRECT("'"&B$1&"'!$A$80:$A$107"),0)),0)+IFERROR(INDEX(INDIRECT("'"&D$1&"'!$V$80:$V$107"),MATCH($A28,INDIRECT("'"&D$1&"'!$A$80:$A$107"),0)),0)+IFERROR(INDEX(INDIRECT("'"&F$1&"'!$V$80:$V$107"),MATCH($A28,INDIRECT("'"&F$1&"'!$A$80:$A$107"),0)),0)+IFERROR(INDEX(INDIRECT("'"&H$1&"'!$V$80:$V$107"),MATCH($A28,INDIRECT("'"&H$1&"'!$A$80:$A$107"),0)),0)+IFERROR(INDEX(INDIRECT("'"&J$1&"'!$V$80:$V$107"),MATCH($A28,INDIRECT("'"&J$1&"'!$A$80:$A$107"),0)),0)+IFERROR(INDEX(INDIRECT("'"&L$1&"'!$V$80:$V$107"),MATCH($A28,INDIRECT("'"&L$1&"'!$A$80:$A$107"),0)),0)+IFERROR(INDEX(INDIRECT("'"&N$1&"'!$V$80:$V$107"),MATCH($A28,INDIRECT("'"&N$1&"'!$A$80:$A$107"),0)),0)+IFERROR(INDEX(INDIRECT("'"&P$1&"'!$V$80:$V$107"),MATCH($A28,INDIRECT("'"&P$1&"'!$A$80:$A$107"),0)),0)+IFERROR(INDEX(INDIRECT("'"&R$1&"'!$V$80:$V$107"),MATCH($A28,INDIRECT("'"&R$1&"'!$A$80:$A$107"),0)),0)+IFERROR(INDEX(INDIRECT("'"&T$1&"'!$V$80:$V$107"),MATCH($A28,INDIRECT("'"&T$1&"'!$A$80:$A$107"),0)),0) -> 0
B29: =IFERROR(INDEX(INDIRECT("'"&B$1&"'!$V$18:$V$45"),MATCH($A29,INDIRECT("'"&B$1&"'!$A$18:$A$45"),0)),0) -> 0 | C29: =IFERROR(INDEX(INDIRECT("'"&B$1&"'!$V$49:$V$76"),MATCH($A29,INDIRECT("'"&B$1&"'!$A$49:$A$76"),0)),0) -> 0 | D29: =IFERROR(INDEX(INDIRECT("'"&D$1&"'!$V$18:$V$45"),MATCH($A29,INDIRECT("'"&D$1&"'!$A$18:$A$45"),0)),0) -> 0 | E29: =IFERROR(INDEX(INDIRECT("'"&D$1&"'!$V$49:$V$76"),MATCH($A29,INDIRECT("'"&D$1&"'!$A$49:$A$76"),0)),0) -> 0 | F29: =IFERROR(INDEX(INDIRECT("'"&F$1&"'!$V$18:$V$45"),MATCH($A29,INDIRECT("'"&F$1&"'!$A$18:$A$45"),0)),0) -> 0 | G29: =IFERROR(INDEX(INDIRECT("'"&F$1&"'!$V$49:$V$76"),MATCH($A29,INDIRECT("'"&F$1&"'!$A$49:$A$76"),0)),0) -> 0 | H29: =IFERROR(INDEX(INDIRECT("'"&H$1&"'!$V$18:$V$45"),MATCH($A29,INDIRECT("'"&H$1&"'!$A$18:$A$45"),0)),0) -> 0 | I29: =IFERROR(INDEX(INDIRECT("'"&H$1&"'!$V$49:$V$76"),MATCH($A29,INDIRECT("'"&H$1&"'!$A$49:$A$76"),0)),0) -> 0 | J29: =IFERROR(INDEX(INDIRECT("'"&J$1&"'!$V$18:$V$45"),MATCH($A29,INDIRECT("'"&J$1&"'!$A$18:$A$45"),0)),0) -> 0 | K29: =IFERROR(INDEX(INDIRECT("'"&J$1&"'!$V$49:$V$76"),MATCH($A29,INDIRECT("'"&J$1&"'!$A$49:$A$76"),0)),0) -> 0 | L29: =IFERROR(INDEX(INDIRECT("'"&L$1&"'!$V$18:$V$45"),MATCH($A29,INDIRECT("'"&L$1&"'!$A$18:$A$45"),0)),0) -> 0 | M29: =IFERROR(INDEX(INDIRECT("'"&L$1&"'!$V$49:$V$76"),MATCH($A29,INDIRECT("'"&L$1&"'!$A$49:$A$76"),0)),0) -> 0 | N29: =IFERROR(INDEX(INDIRECT("'"&N$1&"'!$V$18:$V$45"),MATCH($A29,INDIRECT("'"&N$1&"'!$A$18:$A$45"),0)),0) -> 0 | O29: =IFERROR(INDEX(INDIRECT("'"&N$1&"'!$V$49:$V$76"),MATCH($A29,INDIRECT("'"&N$1&"'!$A$49:$A$76"),0)),0) -> 0 | P29: =IFERROR(INDEX(INDIRECT("'"&P$1&"'!$V$18:$V$45"),MATCH($A29,INDIRECT("'"&P$1&"'!$A$18:$A$45"),0)),0) -> 0 | Q29: =IFERROR(INDEX(INDIRECT("'"&P$1&"'!$V$49:$V$76"),MATCH($A29,INDIRECT("'"&P$1&"'!$A$49:$A$76"),0)),0) -> 0 | R29: =IFERROR(INDEX(INDIRECT("'"&R$1&"'!$V$18:$V$45"),MATCH($A29,INDIRECT("'"&R$1&"'!$A$18:$A$45"),0)),0) -> 0 | S29: =IFERROR(INDEX(INDIRECT("'"&R$1&"'!$V$49:$V$76"),MATCH($A29,INDIRECT("'"&R$1&"'!$A$49:$A$76"),0)),0) -> 0 | T29: =IFERROR(INDEX(INDIRECT("'"&T$1&"'!$V$18:$V$45"),MATCH($A29,INDIRECT("'"&T$1&"'!$A$18:$A$45"),0)),0) -> 0 | U29: =IFERROR(INDEX(INDIRECT("'"&T$1&"'!$V$49:$V$76"),MATCH($A29,INDIRECT("'"&T$1&"'!$A$49:$A$76"),0)),0) -> 0 | V29: =B29+D29+F29+H29+J29+L29+N29+P29+R29+T29 -> 0 | W29: =C29+E29+G29+I29+K29+M29+O29+Q29+S29+U29 -> 0 | X29: =IF(V29=0,"—",ROUND(W29/V29,2)) -> — | Y29: =IFERROR(INDEX(INDIRECT("'"&B$1&"'!$V$80:$V$107"),MATCH($A29,INDIRECT("'"&B$1&"'!$A$80:$A$107"),0)),0)+IFERROR(INDEX(INDIRECT("'"&D$1&"'!$V$80:$V$107"),MATCH($A29,INDIRECT("'"&D$1&"'!$A$80:$A$107"),0)),0)+IFERROR(INDEX(INDIRECT("'"&F$1&"'!$V$80:$V$107"),MATCH($A29,INDIRECT("'"&F$1&"'!$A$80:$A$107"),0)),0)+IFERROR(INDEX(INDIRECT("'"&H$1&"'!$V$80:$V$107"),MATCH($A29,INDIRECT("'"&H$1&"'!$A$80:$A$107"),0)),0)+IFERROR(INDEX(INDIRECT("'"&J$1&"'!$V$80:$V$107"),MATCH($A29,INDIRECT("'"&J$1&"'!$A$80:$A$107"),0)),0)+IFERROR(INDEX(INDIRECT("'"&L$1&"'!$V$80:$V$107"),MATCH($A29,INDIRECT("'"&L$1&"'!$A$80:$A$107"),0)),0)+IFERROR(INDEX(INDIRECT("'"&N$1&"'!$V$80:$V$107"),MATCH($A29,INDIRECT("'"&N$1&"'!$A$80:$A$107"),0)),0)+IFERROR(INDEX(INDIRECT("'"&P$1&"'!$V$80:$V$107"),MATCH($A29,INDIRECT("'"&P$1&"'!$A$80:$A$107"),0)),0)+IFERROR(INDEX(INDIRECT("'"&R$1&"'!$V$80:$V$107"),MATCH($A29,INDIRECT("'"&R$1&"'!$A$80:$A$107"),0)),0)+IFERROR(INDEX(INDIRECT("'"&T$1&"'!$V$80:$V$107"),MATCH($A29,INDIRECT("'"&T$1&"'!$A$80:$A$107"),0)),0) -> 0
B30: =IFERROR(INDEX(INDIRECT("'"&B$1&"'!$V$18:$V$45"),MATCH($A30,INDIRECT("'"&B$1&"'!$A$18:$A$45"),0)),0) -> 0 | C30: =IFERROR(INDEX(INDIRECT("'"&B$1&"'!$V$49:$V$76"),MATCH($A30,INDIRECT("'"&B$1&"'!$A$49:$A$76"),0)),0) -> 0 | D30: =IFERROR(INDEX(INDIRECT("'"&D$1&"'!$V$18:$V$45"),MATCH($A30,INDIRECT("'"&D$1&"'!$A$18:$A$45"),0)),0) -> 0 | E30: =IFERROR(INDEX(INDIRECT("'"&D$1&"'!$V$49:$V$76"),MATCH($A30,INDIRECT("'"&D$1&"'!$A$49:$A$76"),0)),0) -> 0 | F30: =IFERROR(INDEX(INDIRECT("'"&F$1&"'!$V$18:$V$45"),MATCH($A30,INDIRECT("'"&F$1&"'!$A$18:$A$45"),0)),0) -> 0 | G30: =IFERROR(INDEX(INDIRECT("'"&F$1&"'!$V$49:$V$76"),MATCH($A30,INDIRECT("'"&F$1&"'!$A$49:$A$76"),0)),0) -> 0 | H30: =IFERROR(INDEX(INDIRECT("'"&H$1&"'!$V$18:$V$45"),MATCH($A30,INDIRECT("'"&H$1&"'!$A$18:$A$45"),0)),0) -> 0 | I30: =IFERROR(INDEX(INDIRECT("'"&H$1&"'!$V$49:$V$76"),MATCH($A30,INDIRECT("'"&H$1&"'!$A$49:$A$76"),0)),0) -> 0 | J30: =IFERROR(INDEX(INDIRECT("'"&J$1&"'!$V$18:$V$45"),MATCH($A30,INDIRECT("'"&J$1&"'!$A$18:$A$45"),0)),0) -> 0 | K30: =IFERROR(INDEX(INDIRECT("'"&J$1&"'!$V$49:$V$76"),MATCH($A30,INDIRECT("'"&J$1&"'!$A$49:$A$76"),0)),0) -> 0 | L30: =IFERROR(INDEX(INDIRECT("'"&L$1&"'!$V$18:$V$45"),MATCH($A30,INDIRECT("'"&L$1&"'!$A$18:$A$45"),0)),0) -> 0 | M30: =IFERROR(INDEX(INDIRECT("'"&L$1&"'!$V$49:$V$76"),MATCH($A30,INDIRECT("'"&L$1&"'!$A$49:$A$76"),0)),0) -> 0 | N30: =IFERROR(INDEX(INDIRECT("'"&N$1&"'!$V$18:$V$45"),MATCH($A30,INDIRECT("'"&N$1&"'!$A$18:$A$45"),0)),0) -> 0 | O30: =IFERROR(INDEX(INDIRECT("'"&N$1&"'!$V$49:$V$76"),MATCH($A30,INDIRECT("'"&N$1&"'!$A$49:$A$76"),0)),0) -> 0 | P30: =IFERROR(INDEX(INDIRECT("'"&P$1&"'!$V$18:$V$45"),MATCH($A30,INDIRECT("'"&P$1&"'!$A$18:$A$45"),0)),0) -> 0 | Q30: =IFERROR(INDEX(INDIRECT("'"&P$1&"'!$V$49:$V$76"),MATCH($A30,INDIRECT("'"&P$1&"'!$A$49:$A$76"),0)),0) -> 0 | R30: =IFERROR(INDEX(INDIRECT("'"&R$1&"'!$V$18:$V$45"),MATCH($A30,INDIRECT("'"&R$1&"'!$A$18:$A$45"),0)),0) -> 0 | S30: =IFERROR(INDEX(INDIRECT("'"&R$1&"'!$V$49:$V$76"),MATCH($A30,INDIRECT("'"&R$1&"'!$A$49:$A$76"),0)),0) -> 0 | T30: =IFERROR(INDEX(INDIRECT("'"&T$1&"'!$V$18:$V$45"),MATCH($A30,INDIRECT("'"&T$1&"'!$A$18:$A$45"),0)),0) -> 0 | U30: =IFERROR(INDEX(INDIRECT("'"&T$1&"'!$V$49:$V$76"),MATCH($A30,INDIRECT("'"&T$1&"'!$A$49:$A$76"),0)),0) -> 0 | V30: =B30+D30+F30+H30+J30+L30+N30+P30+R30+T30 -> 0 | W30: =C30+E30+G30+I30+K30+M30+O30+Q30+S30+U30 -> 0 | X30: =IF(V30=0,"—",ROUND(W30/V30,2)) -> — | Y30: =IFERROR(INDEX(INDIRECT("'"&B$1&"'!$V$80:$V$107"),MATCH($A30,INDIRECT("'"&B$1&"'!$A$80:$A$107"),0)),0)+IFERROR(INDEX(INDIRECT("'"&D$1&"'!$V$80:$V$107"),MATCH($A30,INDIRECT("'"&D$1&"'!$A$80:$A$107"),0)),0)+IFERROR(INDEX(INDIRECT("'"&F$1&"'!$V$80:$V$107"),MATCH($A30,INDIRECT("'"&F$1&"'!$A$80:$A$107"),0)),0)+IFERROR(INDEX(INDIRECT("'"&H$1&"'!$V$80:$V$107"),MATCH($A30,INDIRECT("'"&H$1&"'!$A$80:$A$107"),0)),0)+IFERROR(INDEX(INDIRECT("'"&J$1&"'!$V$80:$V$107"),MATCH($A30,INDIRECT("'"&J$1&"'!$A$80:$A$107"),0)),0)+IFERROR(INDEX(INDIRECT("'"&L$1&"'!$V$80:$V$107"),MATCH($A30,INDIRECT("'"&L$1&"'!$A$80:$A$107"),0)),0)+IFERROR(INDEX(INDIRECT("'"&N$1&"'!$V$80:$V$107"),MATCH($A30,INDIRECT("'"&N$1&"'!$A$80:$A$107"),0)),0)+IFERROR(INDEX(INDIRECT("'"&P$1&"'!$V$80:$V$107"),MATCH($A30,INDIRECT("'"&P$1&"'!$A$80:$A$107"),0)),0)+IFERROR(INDEX(INDIRECT("'"&R$1&"'!$V$80:$V$107"),MATCH($A30,INDIRECT("'"&R$1&"'!$A$80:$A$107"),0)),0)+IFERROR(INDEX(INDIRECT("'"&T$1&"'!$V$80:$V$107"),MATCH($A30,INDIRECT("'"&T$1&"'!$A$80:$A$107"),0)),0) -> 0
A31: Total | B31: =SUM(B3:B30) -> 68 | C31: =SUM(C3:C30) -> 23 | D31: =SUM(D3:D30) -> 56 | E31: =SUM(E3:E30) -> 16 | F31: =SUM(F3:F30) -> 86 | G31: =SUM(G3:G30) -> 34 | H31: =SUM(H3:H30) -> 85 | I31: =SUM(I3:I30) -> 23 | ... W31: =SUM(W3:W30) -> 195 | Y31: =SUM(Y3:Y30) -> 40

Sheet Money
A1: PLAYER TABS — Season 8 onward (everything before S8 is settled) | B1: S8 | C1: S9 | D1: S10
A2: Season paid by: | B2: =IFERROR(T(INDIRECT("'"&B$1&"'!$Y$12")),"") -> Isaac Mond | C2: =IFERROR(T(INDIRECT("'"&C$1&"'!$Y$12")),"") | D2: =IFERROR(T(INDIRECT("'"&D$1&"'!$Y$12")),"")
A3: Player | B3: S8 charges | C3: S9 charges | D3: S10 charges | E3: Total charged | F3: Paid | G3: Balance owed
A4: Ahmed | B4: =IFERROR(INDEX(INDIRECT("'"&B$1&"'!$W$18:$W$45"),MATCH($A4,INDIRECT("'"&B$1&"'!$A$18:$A$45"),0)),0) -> 0 | C4: =IFERROR(INDEX(INDIRECT("'"&C$1&"'!$W$18:$W$45"),MATCH($A4,INDIRECT("'"&C$1&"'!$A$18:$A$45"),0)),0) -> 0 | D4: =IFERROR(INDEX(INDIRECT("'"&D$1&"'!$W$18:$W$45"),MATCH($A4,INDIRECT("'"&D$1&"'!$A$18:$A$45"),0)),0) -> 0 | E4: =SUM(B4:D4) -> 0 | F4: =SUMIF(Payments!$B:$B,$A4,Payments!$C:$C) -> 0 | G4: =E4-F4 -> 0
A5: Alex Ruben | B5: =IFERROR(INDEX(INDIRECT("'"&B$1&"'!$W$18:$W$45"),MATCH($A5,INDIRECT("'"&B$1&"'!$A$18:$A$45"),0)),0) -> 0 | C5: =IFERROR(INDEX(INDIRECT("'"&C$1&"'!$W$18:$W$45"),MATCH($A5,INDIRECT("'"&C$1&"'!$A$18:$A$45"),0)),0) -> 0 | D5: =IFERROR(INDEX(INDIRECT("'"&D$1&"'!$W$18:$W$45"),MATCH($A5,INDIRECT("'"&D$1&"'!$A$18:$A$45"),0)),0) -> 0 | E5: =SUM(B5:D5) -> 0 | F5: =SUMIF(Payments!$B:$B,$A5,Payments!$C:$C) -> 0 | G5: =E5-F5 -> 0
A6: Andy Cowan | B6: =IFERROR(INDEX(INDIRECT("'"&B$1&"'!$W$18:$W$45"),MATCH($A6,INDIRECT("'"&B$1&"'!$A$18:$A$45"),0)),0) -> 0 | C6: =IFERROR(INDEX(INDIRECT("'"&C$1&"'!$W$18:$W$45"),MATCH($A6,INDIRECT("'"&C$1&"'!$A$18:$A$45"),0)),0) -> 0 | D6: =IFERROR(INDEX(INDIRECT("'"&D$1&"'!$W$18:$W$45"),MATCH($A6,INDIRECT("'"&D$1&"'!$A$18:$A$45"),0)),0) -> 0 | E6: =SUM(B6:D6) -> 0 | F6: =SUMIF(Payments!$B:$B,$A6,Payments!$C:$C) -> 0 | G6: =E6-F6 -> 0
A7: Ben Merrett | B7: =IFERROR(INDEX(INDIRECT("'"&B$1&"'!$W$18:$W$45"),MATCH($A7,INDIRECT("'"&B$1&"'!$A$18:$A$45"),0)),0) -> 11.421429 | C7: =IFERROR(INDEX(INDIRECT("'"&C$1&"'!$W$18:$W$45"),MATCH($A7,INDIRECT("'"&C$1&"'!$A$18:$A$45"),0)),0) -> 0 | D7: =IFERROR(INDEX(INDIRECT("'"&D$1&"'!$W$18:$W$45"),MATCH($A7,INDIRECT("'"&D$1&"'!$A$18:$A$45"),0)),0) -> 0 | E7: =SUM(B7:D7) -> 11.421429 | F7: =SUMIF(Payments!$B:$B,$A7,Payments!$C:$C) -> 0 | G7: =E7-F7 -> 11.421429
A8: Callum McCarthy | B8: =IFERROR(INDEX(INDIRECT("'"&B$1&"'!$W$18:$W$45"),MATCH($A8,INDIRECT("'"&B$1&"'!$A$18:$A$45"),0)),0) -> 0 | C8: =IFERROR(INDEX(INDIRECT("'"&C$1&"'!$W$18:$W$45"),MATCH($A8,INDIRECT("'"&C$1&"'!$A$18:$A$45"),0)),0) -> 0 | D8: =IFERROR(INDEX(INDIRECT("'"&D$1&"'!$W$18:$W$45"),MATCH($A8,INDIRECT("'"&D$1&"'!$A$18:$A$45"),0)),0) -> 0 | E8: =SUM(B8:D8) -> 0 | F8: =SUMIF(Payments!$B:$B,$A8,Payments!$C:$C) -> 0 | G8: =E8-F8 -> 0
A9: Cecil Watson | B9: =IFERROR(INDEX(INDIRECT("'"&B$1&"'!$W$18:$W$45"),MATCH($A9,INDIRECT("'"&B$1&"'!$A$18:$A$45"),0)),0) -> 0 | C9: =IFERROR(INDEX(INDIRECT("'"&C$1&"'!$W$18:$W$45"),MATCH($A9,INDIRECT("'"&C$1&"'!$A$18:$A$45"),0)),0) -> 0 | D9: =IFERROR(INDEX(INDIRECT("'"&D$1&"'!$W$18:$W$45"),MATCH($A9,INDIRECT("'"&D$1&"'!$A$18:$A$45"),0)),0) -> 0 | E9: =SUM(B9:D9) -> 0 | F9: =SUMIF(Payments!$B:$B,$A9,Payments!$C:$C) -> 0 | G9: =E9-F9 -> 0
A10: Conall Templeman | B10: =IFERROR(INDEX(INDIRECT("'"&B$1&"'!$W$18:$W$45"),MATCH($A10,INDIRECT("'"&B$1&"'!$A$18:$A$45"),0)),0) -> 0 | C10: =IFERROR(INDEX(INDIRECT("'"&C$1&"'!$W$18:$W$45"),MATCH($A10,INDIRECT("'"&C$1&"'!$A$18:$A$45"),0)),0) -> 0 | D10: =IFERROR(INDEX(INDIRECT("'"&D$1&"'!$W$18:$W$45"),MATCH($A10,INDIRECT("'"&D$1&"'!$A$18:$A$45"),0)),0) -> 0 | E10: =SUM(B10:D10) -> 0 | F10: =SUMIF(Payments!$B:$B,$A10,Payments!$C:$C) -> 0 | G10: =E10-F10 -> 0
A11: Eddie Ringer | B11: =IFERROR(INDEX(INDIRECT("'"&B$1&"'!$W$18:$W$45"),MATCH($A11,INDIRECT("'"&B$1&"'!$A$18:$A$45"),0)),0) -> 0 | C11: =IFERROR(INDEX(INDIRECT("'"&C$1&"'!$W$18:$W$45"),MATCH($A11,INDIRECT("'"&C$1&"'!$A$18:$A$45"),0)),0) -> 0 | D11: =IFERROR(INDEX(INDIRECT("'"&D$1&"'!$W$18:$W$45"),MATCH($A11,INDIRECT("'"&D$1&"'!$A$18:$A$45"),0)),0) -> 0 | E11: =SUM(B11:D11) -> 0 | F11: =SUMIF(Payments!$B:$B,$A11,Payments!$C:$C) -> 0 | G11: =E11-F11 -> 0
A12: Finn Cawley | B12: =IFERROR(INDEX(INDIRECT("'"&B$1&"'!$W$18:$W$45"),MATCH($A12,INDIRECT("'"&B$1&"'!$A$18:$A$45"),0)),0) -> 11.421429 | C12: =IFERROR(INDEX(INDIRECT("'"&C$1&"'!$W$18:$W$45"),MATCH($A12,INDIRECT("'"&C$1&"'!$A$18:$A$45"),0)),0) -> 0 | D12: =IFERROR(INDEX(INDIRECT("'"&D$1&"'!$W$18:$W$45"),MATCH($A12,INDIRECT("'"&D$1&"'!$A$18:$A$45"),0)),0) -> 0 | E12: =SUM(B12:D12) -> 11.421429 | F12: =SUMIF(Payments!$B:$B,$A12,Payments!$C:$C) -> 0 | G12: =E12-F12 -> 11.421429
A13: George Barbantan | B13: =IFERROR(INDEX(INDIRECT("'"&B$1&"'!$W$18:$W$45"),MATCH($A13,INDIRECT("'"&B$1&"'!$A$18:$A$45"),0)),0) -> 0 | C13: =IFERROR(INDEX(INDIRECT("'"&C$1&"'!$W$18:$W$45"),MATCH($A13,INDIRECT("'"&C$1&"'!$A$18:$A$45"),0)),0) -> 0 | D13: =IFERROR(INDEX(INDIRECT("'"&D$1&"'!$W$18:$W$45"),MATCH($A13,INDIRECT("'"&D$1&"'!$A$18:$A$45"),0)),0) -> 0 | E13: =SUM(B13:D13) -> 0 | F13: =SUMIF(Payments!$B:$B,$A13,Payments!$C:$C) -> 0 | G13: =E13-F13 -> 0
A14: Henry Linklater | B14: =IFERROR(INDEX(INDIRECT("'"&B$1&"'!$W$18:$W$45"),MATCH($A14,INDIRECT("'"&B$1&"'!$A$18:$A$45"),0)),0) -> 0 | C14: =IFERROR(INDEX(INDIRECT("'"&C$1&"'!$W$18:$W$45"),MATCH($A14,INDIRECT("'"&C$1&"'!$A$18:$A$45"),0)),0) -> 0 | D14: =IFERROR(INDEX(INDIRECT("'"&D$1&"'!$W$18:$W$45"),MATCH($A14,INDIRECT("'"&D$1&"'!$A$18:$A$45"),0)),0) -> 0 | E14: =SUM(B14:D14) -> 0 | F14: =SUMIF(Payments!$B:$B,$A14,Payments!$C:$C) -> 0 | G14: =E14-F14 -> 0
A15: Isaac Mond | B15: =IFERROR(INDEX(INDIRECT("'"&B$1&"'!$W$18:$W$45"),MATCH($A15,INDIRECT("'"&B$1&"'!$A$18:$A$45"),0)),0) -> 11.421429 | C15: =IFERROR(INDEX(INDIRECT("'"&C$1&"'!$W$18:$W$45"),MATCH($A15,INDIRECT("'"&C$1&"'!$A$18:$A$45"),0)),0) -> 0 | D15: =IFERROR(INDEX(INDIRECT("'"&D$1&"'!$W$18:$W$45"),MATCH($A15,INDIRECT("'"&D$1&"'!$A$18:$A$45"),0)),0) -> 0 | E15: =SUM(B15:D15) -> 11.421429 | F15: =SUMIF(Payments!$B:$B,$A15,Payments!$C:$C) -> 0 | G15: =E15-F15 -> 11.421429
... A25: Seb Burgess | B25: =IFERROR(INDEX(INDIRECT("'"&B$1&"'!$W$18:$W$45"),MATCH($A25,INDIRECT("'"&B$1&"'!$A$18:$A$45"),0)),0) -> 11.421429 | C25: =IFERROR(INDEX(INDIRECT("'"&C$1&"'!$W$18:$W$45"),MATCH($A25,INDIRECT("'"&C$1&"'!$A$18:$A$45"),0)),0) -> 0 | D25: =IFERROR(INDEX(INDIRECT("'"&D$1&"'!$W$18:$W$45"),MATCH($A25,INDIRECT("'"&D$1&"'!$A$18:$A$45"),0)),0) -> 0 | E25: =SUM(B25:D25) -> 11.421429 | F25: =SUMIF(Payments!$B:$B,$A25,Payments!$C:$C) -> 0 | G25: =E25-F25 -> 11.421429
B26: =IFERROR(INDEX(INDIRECT("'"&B$1&"'!$W$18:$W$45"),MATCH($A26,INDIRECT("'"&B$1&"'!$A$18:$A$45"),0)),0) -> 0 | C26: =IFERROR(INDEX(INDIRECT("'"&C$1&"'!$W$18:$W$45"),MATCH($A26,INDIRECT("'"&C$1&"'!$A$18:$A$45"),0)),0) -> 0 | D26: =IFERROR(INDEX(INDIRECT("'"&D$1&"'!$W$18:$W$45"),MATCH($A26,INDIRECT("'"&D$1&"'!$A$18:$A$45"),0)),0) -> 0 | E26: =SUM(B26:D26) -> 0 | F26: =SUMIF(Payments!$B:$B,$A26,Payments!$C:$C) -> 0 | G26: =E26-F26 -> 0
B27: =IFERROR(INDEX(INDIRECT("'"&B$1&"'!$W$18:$W$45"),MATCH($A27,INDIRECT("'"&B$1&"'!$A$18:$A$45"),0)),0) -> 0 | C27: =IFERROR(INDEX(INDIRECT("'"&C$1&"'!$W$18:$W$45"),MATCH($A27,INDIRECT("'"&C$1&"'!$A$18:$A$45"),0)),0) -> 0 | D27: =IFERROR(INDEX(INDIRECT("'"&D$1&"'!$W$18:$W$45"),MATCH($A27,INDIRECT("'"&D$1&"'!$A$18:$A$45"),0)),0) -> 0 | E27: =SUM(B27:D27) -> 0 | F27: =SUMIF(Payments!$B:$B,$A27,Payments!$C:$C) -> 0 | G27: =E27-F27 -> 0
B28: =IFERROR(INDEX(INDIRECT("'"&B$1&"'!$W$18:$W$45"),MATCH($A28,INDIRECT("'"&B$1&"'!$A$18:$A$45"),0)),0) -> 0 | C28: =IFERROR(INDEX(INDIRECT("'"&C$1&"'!$W$18:$W$45"),MATCH($A28,INDIRECT("'"&C$1&"'!$A$18:$A$45"),0)),0) -> 0 | D28: =IFERROR(INDEX(INDIRECT("'"&D$1&"'!$W$18:$W$45"),MATCH($A28,INDIRECT("'"&D$1&"'!$A$18:$A$45"),0)),0) -> 0 | E28: =SUM(B28:D28) -> 0 | F28: =SUMIF(Payments!$B:$B,$A28,Payments!$C:$C) -> 0 | G28: =E28-F28 -> 0
B29: =IFERROR(INDEX(INDIRECT("'"&B$1&"'!$W$18:$W$45"),MATCH($A29,INDIRECT("'"&B$1&"'!$A$18:$A$45"),0)),0) -> 0 | C29: =IFERROR(INDEX(INDIRECT("'"&C$1&"'!$W$18:$W$45"),MATCH($A29,INDIRECT("'"&C$1&"'!$A$18:$A$45"),0)),0) -> 0 | D29: =IFERROR(INDEX(INDIRECT("'"&D$1&"'!$W$18:$W$45"),MATCH($A29,INDIRECT("'"&D$1&"'!$A$18:$A$45"),0)),0) -> 0 | E29: =SUM(B29:D29) -> 0 | F29: =SUMIF(Payments!$B:$B,$A29,Payments!$C:$C) -> 0 | G29: =E29-F29 -> 0
B30: =IFERROR(INDEX(INDIRECT("'"&B$1&"'!$W$18:$W$45"),MATCH($A30,INDIRECT("'"&B$1&"'!$A$18:$A$45"),0)),0) -> 0 | C30: =IFERROR(INDEX(INDIRECT("'"&C$1&"'!$W$18:$W$45"),MATCH($A30,INDIRECT("'"&C$1&"'!$A$18:$A$45"),0)),0) -> 0 | D30: =IFERROR(INDEX(INDIRECT("'"&D$1&"'!$W$18:$W$45"),MATCH($A30,INDIRECT("'"&D$1&"'!$A$18:$A$45"),0)),0) -> 0 | E30: =SUM(B30:D30) -> 0 | F30: =SUMIF(Payments!$B:$B,$A30,Payments!$C:$C) -> 0 | G30: =E30-F30 -> 0
B31: =IFERROR(INDEX(INDIRECT("'"&B$1&"'!$W$18:$W$45"),MATCH($A31,INDIRECT("'"&B$1&"'!$A$18:$A$45"),0)),0) -> 0 | C31: =IFERROR(INDEX(INDIRECT("'"&C$1&"'!$W$18:$W$45"),MATCH($A31,INDIRECT("'"&C$1&"'!$A$18:$A$45"),0)),0) -> 0 | D31: =IFERROR(INDEX(INDIRECT("'"&D$1&"'!$W$18:$W$45"),MATCH($A31,INDIRECT("'"&D$1&"'!$A$18:$A$45"),0)),0) -> 0 | E31: =SUM(B31:D31) -> 0 | F31: =SUMIF(Payments!$B:$B,$A31,Payments!$C:$C) -> 0 | G31: =E31-F31 -> 0
A32: Total | B32: =SUM(B4:B31) -> 79.95 | C32: =SUM(C4:C31) -> 0 | D32: =SUM(D4:D31) -> 0 | E32: =SUM(E4:E31) -> 79.95 | F32: =SUM(F4:F31) -> 0 | G32: =SUM(G4:G31) -> 79.95

Sheet Payments
A1: PAYMENTS RECEIVED — one row per transfer
A2: Date | B2: Player | C2: Amount (£) | D2: Note | F2: format: 05/09/2026 · Phil Knott · 40 · bank transfer
